Workbook
Name CarteirasMatrizAtivos12: config.carteiras!$FQ$7:$FV$106
Name CarteirasLista: carteiras.!$AA$6:$AA$20
Name CarteirasPerfil1: config.carteiras!$M$4
Name CarteirasNome12: config.carteiras!$FV$2
Name CarteirasNomeAbreviado15: config.carteiras!$HO$3
Name CarteirasMatrizAtivosCompleta3: config.carteiras!$AJ$7:$AX$106
Name CarteirasAtivos: carteiras.!$A$4:$L$264
Name CarteirasPerfil7: config.carteiras!$CY$4
Name CarteirasMatrizAtivosCompleta7: config.carteiras!$CR$7:$DF$106
Name ParametrosURL: carteiras.!$AK$2
Name IFIXCHANGE: 'portfólio'!$BR$81
Name IBOVCHANGEHISTORICO: 'portfólio'!$BU$87:$BU$96
Name CarteirasNome4: config.carteiras!$BF$2
Name CarteirasPerfil8: config.carteiras!$DN$4
Name CarteirasListaCriadasAbreviada: carteiras.!$AF$6:$AF$15
Name IFIXPRICE: 'portfólio'!$BQ$81
Name CarteirasNomeAbreviado7: config.carteiras!$CY$3
Name CarteirasNomeAbreviado3: config.carteiras!$AQ$3
Name AtivosLista: carteiras.!$AH$5:$AH$264
Name PortfolioOrdenarMatriz: config.books!$CX$5:$DG$574
Name PortfolioAtivosNovos: config.books!$X$5:$X$574
Name CarteirasPerfil9: config.carteiras!$EC$4
Name IBOVPRICE: 'portfólio'!$BQ$80
Name CarteirasNome6: config.carteiras!$CJ$2
Name CarteirasNome2: config.carteiras!$AB$2
Name CarteirasMatrizAtivos3: config.carteiras!$AL$7:$AQ$106
Name CarteirasMatrizAtivos15: config.carteiras!$HJ$7:$HO$106
Name CarteirasMatrizAtivos10: config.carteiras!$EM$7:$ER$106
Name CarteirasMatrizAtivosCompleta4: config.carteiras!$AY$7:$BM$106
Name CarteirasMatrizAtivos2: config.carteiras!$W$7:$AB$106
Name ParametrosIDAbaCarteira: carteiras.!$AK$3
Name CarteirasNome9: config.carteiras!$EC$2
Name CarteirasNome14: config.carteiras!$GZ$2
Name CarteirasNomeAbreviado10: config.carteiras!$ER$3
Name CarteirasAtivosEncerrados: carteiras.!$N$4:$Y$264
Name CarteirasNomeAbreviado4: config.carteiras!$BF$3
Name CarteirasMatrizAtivos8: config.carteiras!$DI$7:$DN$106
Name CarteirasListaCriadasPerfis: carteiras.!$AG$6:$AG$15
Name IBOVCHANGE: 'portfólio'!$BR$80
Name CarteirasMatrizAtivos11: config.carteiras!$FB$7:$FG$106
Name PortfolioOrdenarAtivos: config.books!$CU$5:$CU$574
Name CarteirasMatrizAtivos5: config.carteiras!$BP$7:$BU$106
Name CarteirasNomeAbreviado13: config.carteiras!$GK$3
Name CarteirasNomeAbreviado14: config.carteiras!$GZ$3
Name IBOVCHANGEPCT: 'portfólio'!$BS$80
Name CarteirasMatrizAtivosCompleta14: config.carteiras!$GS$7:$HG$106
Name CarteirasNome15: config.carteiras!$HO$2
Name CarteirasPerfil5: config.carteiras!$BU$4
Name ParametrosVersaoPlanilhaLancada: carteiras.!$AK$4
Name CarteirasPerfil11: config.carteiras!$FG$4
Name CarteirasNomeAbreviado11: config.carteiras!$FG$3
Name CarteirasPerfil13: config.carteiras!$GK$4
Name CarteirasPerfil14: config.carteiras!$GZ$4
Name CarteirasQuantidadeCriadas: carteiras.!$AE$4
Name CarteirasMatrizAtivosCompleta9: config.carteiras!$DV$7:$EJ$106
Name AtivosDados: portfolio.!$A$4:$BP$303
Name CarteirasMatrizAtivosCompleta8: config.carteiras!$DG$7:$DU$106
Name CarteirasNome5: config.carteiras!$BU$2
Name CarteirasListaCriadas: carteiras.!$AE$6:$AE$15
Name CarteirasMatrizAtivosCompleta13: config.carteiras!$GD$7:$GR$106

Sheet leiame
A2: PLANILHA DE CONTROLE E GESTÃO DE INVESTIMENTOS
A3: dlombello®planilhas
A5: Esta planilha é desenvolvida e mantida por dlombello planilhas em parceria com mdiemer planilhas
A6: Versão: | B6: v6.4.02
A7: Última Versão Disponível: | B7: =IF($B$6<carteiras.!$AK$4,"Existe(m) atualização(ões). A última versão é "&carteiras.!AK4&". Acesse o menu dlombello -> Verificar atualizações",carteiras.!AK4)
A8: Download: | B8: https://www.dlombelloplanilhas.com
A9: URL da Dlombello de origem
A10: URL da DiemerPlanilhas
A11: Essa planilha foi criada para auxiliá-lo no gerenciamento da sua carteira de investimentos de forma online e atualizada. As informações devem ser utilizadas apenas para fins informativos, toda e qualquer informação da planilha não devem ser usadas para fins fiscais. NÃO SOLICITAR EDIÇÃO!!! FAVOR LEIA O MANUAL E INSTRUÇÕES DE USO PELO LINK ABAIXO!
B12: PLAYLIST DE VÍDEOS DE INSTRUÇÃO DE USO
A13: Assista os vídeos 2x rápido | B13: https://www.youtube.com/c/dlombelloplanilhas/playlists
A14: Manual com vídeos | B14: https://www.dlombelloplanilhas.com/faq/faq-ebook
B15: DOAÇÕES PARA DESENVOLVIMENTO E MANUTENÇÃO DO PROJETO
A16: Desenvolvedores | B16: Douglas Alves Lombello, Maglan Cristiano Diemer e Mouriac Halen Diemer
B17: Caso a planilha lhe seja útil e queira incentivar a manutenção e criação de novas ferramentas, avalie ser um usuário Alpha!
A18: WebApp | B18: Conhece nosso WebApp
B19: app.dlombelloplanilhas.com
A20: Usuário Alpha | B20: =HYPERLINK("https://www.dlombelloplanilhas.com/planos","https://www.dlombelloplanilhas.com/planos") -> https://www.dlombelloplanilhas.com/planos
B22: INFORMAÇÕES COMPLEMENTARES
A23: Site | B23: A planilha está em constante atualização, afim de melhorias e correções de possíveis problemas. A versão mais atual estará sempre disponível pelo link abaixo:
B24: dlombelloplanilhas.com
A25: Formulário Suporte | B25: Dúvidas, críticas ou sugestões entre em contato pelo formulário:
B26: bit.ly/suporte_dlombelloplanilhas
A27: Discord | B27: Grupo de usuários e suporte no Discord:
B28: https://discord.gg/UFvrHgGQ5A
A29: Facebook | B29: Grupo de usuários no Facebook:
B30: https://www.facebook.com/groups/dlombelloplanilhas
A31: Telegram | B31: Grupo de usuários no Telegram:
B32: https://t.me/dlombelloplanilhas
A33: YouTube | B33: Se inscreva no canal do YouTube e ative as notificações:
B34: https://www.youtube.com/channel/UCYOmBs3ppKsfvm6TVfnkXUQ
B35: FONTE DE DADOS EXTERNOS :
A36: Google | B36: google.com/finance
A37: Funds Explorer | B37: =HYPERLINK("www.fundsexplorer.com.br","fundsexplorer.com.br") -> fundsexplorer.com.br
A38: Fundamentus | B38: fundamentus.com.br
A39: Versão | B39: HISTÓRICO DE ATUALIZAÇÕES
A40: v6.0 | B40: Versão inicial de testes de funções básicas
A41: v6.1 | B41: Versão completa homologada
A42: v6.2 | B42: Atualizações na aba alocação, caixa, gráficos, inclusão das abas Darf e Dirpf
B43: Obrigado e bons investimentos!!!

Sheet portfólio
B1: =NOW() -> 46092.901 | M1: =HYPERLINK("bit.ly/dlombelloplanilhas","dlombello®planilhas "&leiame!B6) -> dlombello®planilhas v6.4.02 | Q1: =image("https://lh3.googleusercontent.com/fife/ABSRlIoRwkeqx455dMEAYIU3xM0jhiUWm9uF-SD8X-Y9BIuGyWBXBzbKRightO43rRoubfFk-TFbf_xIiuBaYvAW1dxafrf53XjdNoAN3pQzhDpBGay5lR8Na1lz6HsodfG-8o8Pnde0ca6e0rgrocdmN_xaCzfb5w0EhjEVhqAXuuzbPjcBPGos2EoF8Ftmiy1oCDFF0BND-SYre6Yvd3OC"&"QFkx-bgLzPG2Ex8Qaq2V7fuLzPsBNpeNYlvatsHS2tqct-7DTs_CGURMTvFAIG6oCs02BPqK64Gjlby59YLyTSuX1leLv2nU3inB_mwaV9vvTpvCIbH2HugPP13V6gQNVMysPsqY8snYckzDe1ko1i-LSOA9tfUJMJTYzSO0emPxZ8k4CdrYvWKg1WvNQbR8fbrrq0K6Nb8YEWBsbVJQjBQ0aaJlj9zXg3vxrdgQTpo5pj8at-L8Ddw488HtYnT"&"PepdXIphaOgX_BGK2oytIxUG8-L17hq9DrH7t8kLnnNA1qabqHJbAwjDU1fmbvBtHrL4Mm-XCkv5JnziYdMj1V6IcDFRLFnnTCM70VkTP0vZlde2BGbfonjDeANHP3128HQVVZ7mZgeGZ_WZGbPjOI8WdZh9N0ZGcOwDqDIdnSE3O37DgjFLA_U_NbruqnDmLZPDpoRGEhXB1T5Tn42k3yPtGErHfdNQKLxEnNqDkV7DsRj8wsj3Lvryo9fu-lZ"&"UiW3QtuiXOgBjS=ft") | R1: painel composição do portfólio | AN1: INDICADORES COMPLEMENTARES
Q2: =HYPERLINK("https://sites.google.com/view/diemerplanilhas/Videos","youtube") -> youtube
B4: SELIC | D4: iGP-M | F4: IPCA | H4: INPC | J4: USDBRL | M4: ="Você tem o plano: "&IF('config.parâmetros'!O2="GRATUITO","GRATUITO", IF('config.parâmetros'!O2="","<aguarde leitura, tecle F5>", IF(MID('config.parâmetros'!O2,1,10)="UALN_001_2","PREMIUM", IF(MID('config.parâmetros'!O2,1,10)="UALN_001_I","ULTIMATE", IF(MID('config.parâmetros'!O2,1,10)="STARTER_01","STARTER", IF(MID('config.parâmetros'!O2,1,10)="PREMIUM_01","PREMIUM", IF(MID('config.parâmetros'!O2,1,10)="ULTIMATE_0","ULTIMATE", IF(MID('config.parâmetros'!O2,1,10)="MULTI_03_L","MULTI INVESTIDOR", IF(MID('config.parâmetros'!O2,1,10)="MULTI_05_L","MULTI INVESTIDOR","PERSONALIZADO"))))))))) -> Você tem o plano: <aguarde leitura, tecle F5> | Q4: =IF(AV11,"INVESTIDOR ▶","Conheça ▶") -> Conheça ▶ | R4: TRUE | S4: =IF(NOT(AV11)," Carteiras",IF('config.parâmetros'!B17="","","Investidor "&'config.parâmetros'!B17)) -> Carteiras | U4: TRUE | V4: =IF(NOT(AV11)," Books",IF('config.parâmetros'!B18="","","Investidor "&'config.parâmetros'!B18)) -> Books | X4: TRUE | Y4: =IF(NOT(AV11),"Multi investidor",IF('config.parâmetros'!B19="","","Investidor "&'config.parâmetros'!B19)) -> Multi investidor | AA4: TRUE | AB4: =IF(NOT(AV11)," Summary",IF('config.parâmetros'!B20="","","Investidor "&'config.parâmetros'!B20)) -> Summary | AD4: TRUE | AE4: =IF(NOT(AV11),"DARF/DIRF",IF('config.parâmetros'!B21="","","Investidor "&'config.parâmetros'!B21)) -> DARF/DIRF | AG4: TRUE | AH4: =IF(NOT(AV11),"Sistema Web",IF('config.parâmetros'!B22="","","Investidor "&'config.parâmetros'!B22)) -> Sistema Web | AJ4: TRUE | AK4: =IF(NOT(AV11)," Caixa",IF('config.parâmetros'!B23="","","Investidor "&'config.parâmetros'!B23)) -> Caixa | AN4: INDICADOR | AO4: Cotação | AP4: % dia | AQ4: =CONCATENATE("% ",$AS$4," dias") -> % 30 dias | AR4: Dias do gráfico: | AS4: 30
B5: 0.1275 | D5: 0.52% | F5: 1.06% | H5: +1,04% | J5: =BT81 -> 5.1928009
M6: PORTFÓLIO | Q6: TOTAL | T6: Lucro do dia | U6: Principais operações | AB6: Operações com fundos e Renda Fixa | AH6: Demais Operações | AK6: Rentabilidade geral | AN6: IBOV | AO6: =IBOVPRICE -> 183969.34 | AP6: =IF(NOT(ConfigOn),"",IBOVCHANGEPCT/100) -> 0.0028 | AQ6: =IFERROR(__xludf.DUMMYFUNCTION("IF(NOT(ConfigOn),"""",IFERROR(AO6/INDEX(IFERROR(GOOGLEFINANCE(""INDEXBVMF:""&AN6,""price"",TODAY()-$AS$4,TODAY(),1),IFERROR(GOOGLEFINANCE(""BVMF:""&AN6,""price"",TODAY()-$AS$4,TODAY(),1),GOOGLEFINANCE(AN6,""price"",TODAY()-$AS$4,TODAY(),1))),2,2)-1))"),-0.012198217203877815) -> -0.012198217 | AR6: =IFERROR(__xludf.DUMMYFUNCTION("IF(NOT(ConfigOn),"""",IFERROR(SPARKLINE(GOOGLEFINANCE(""INDEXBVMF:""&AN6,""price"",TODAY()-$AS$4,TODAY()))))"),"") | AV6: Ativado?
B7: LTN-23 | D7: LTN-26 | F7: NTNB-26 | H7: NTNB-35 | J7: NTNB-45 | Q7: Investido | R7: Atual | S7: Lucro | U7: Investido | V7: Atual | W7: Lucro Aberto | X7: Swing Trades | Y7: Day Trades | Z7: Proventos | AA7: Lucro total | AB7: Investido | AC7: Atual | AD7: Lucro Aberto | AE7: Trades | AF7: Proventos | AG7: Lucro total | AH7: Investido | AI7: Atual | AJ7: Lucro total | AK7: TIR am% | AL7: TIR aa% | AN7: IFIX | AO7: =IFIXPRICE -> 3873.59 | AP7: =IF(NOT(ConfigOn),"",IFIXCHANGEPCT/100) -> -0.0007 | AQ7: =IFERROR(__xludf.DUMMYFUNCTION("IF(NOT(ConfigOn),"""",IFERROR(AO7/INDEX(IFERROR(GOOGLEFINANCE(""INDEXBVMF:""&AN7,""price"",TODAY()-$AS$4,TODAY(),1),IFERROR(GOOGLEFINANCE(""BVMF:""&AN7,""price"",TODAY()-$AS$4,TODAY(),1),GOOGLEFINANCE(AN7,""price"",TODAY()-$AS$4,TODAY(),1))),2,2)-1))"),0.007839290639163776) -> 0.0078392906 | AR7: =IFERROR(__xludf.DUMMYFUNCTION("IF(NOT(ConfigOn),"""",IFERROR(SPARKLINE(GOOGLEFINANCE(""INDEXBVMF:""&AN7,""price"",TODAY()-$AS$4,TODAY()))))"),"") | AV7: =config.books!$BU$1 -> FALSE
B8: 5.14% | D8: 1.32% | F8: 5.49% | H8: 5.74% | J8: 5.74% | Q8: =DF63 -> 0 | R8: =DG63 -> 0 | S8: =DM63 -> 0 | T8: =DH63 -> 0 | U8: =DF60 -> 0 | V8: =DG60 -> 0 | W8: =DL60 -> 0 | X8: =DK60-Y8 -> 0 | Y8: =DN65 -> 0 | Z8: =DJ60 -> 0 | AA8: =DM60 -> 0 | AB8: =$DF$61 -> 0 | AC8: =$DG$61 -> 0 | AD8: =DL61 -> 0 | AE8: =DK61 -> 0 | AF8: =DJ61 -> 0 | AG8: =$DM$61 -> 0 | AH8: =$DF$62 -> 0 | AI8: =DG62 -> 0 | AJ8: =DM62 -> 0 | AK8: =DN63 -> -0.0014149368 | AL8: =DO63 -> -0.016847727 | AN8: ="USD"&'config.parâmetros'!$B$8 -> USDBRL | AO8: =BT81 -> 5.1928009 | AP8: =IFERROR(__xludf.DUMMYFUNCTION("IF(NOT(ConfigOn),"""",IFERROR(AO8/INDEX(SORT(GOOGLEFINANCE(AN8,""price"",TODAY()-3,TODAY(),1),1,0),2,2)-1))"),0.005596721470206623) -> 0.0055967215 | AQ8: =IFERROR(__xludf.DUMMYFUNCTION("IF(NOT(ConfigOn),"""",IFERROR(AO8/INDEX(GOOGLEFINANCE(AN8,""price"",TODAY()-$AS$4,TODAY(),1),2,2)-1))"),2.3131789814301307E-4) -> 0.0002313179 | AR8: =IFERROR(__xludf.DUMMYFUNCTION("IF(NOT(ConfigOn),"""",IFERROR(SPARKLINE(GOOGLEFINANCE(AN8,""price"",TODAY()-$AS$4,TODAY()))))"),"") | AV8: =AND($M$20,ConfigOn,carteiras.!$AE$4>0) -> FALSE
B10: IBOVESPA | H10: gráfico últimos 10 dias | M10: FALSE | N10: BOOKS | Q10: TOTAL | R10: =IFERROR(__xludf.DUMMYFUNCTION("IF(NOT($AV$7),"""",IFERROR(TRANSPOSE(query({config.books!BN5:BV14;config.books!BN22:BV24},""select Col2 where Col2 is not null and Col4<>0 order by Col9""))))"),"") | AN10: IBOV | AO10: =AO6 -> 183969.34 | AP10: =AP6 -> 0.0028 | AQ10: =AQ6 -> -0.012198217 | AR10: =IFERROR(__xludf.DUMMYFUNCTION("IF(NOT(ConfigOn),"""",IFERROR(SPARKLINE(GOOGLEFINANCE(""INDEXBVMF:""&AN10,""price"",TODAY()-$AS$4,TODAY()))))"),"") | AV10: Multi invest
B11: =IF(NOT(ConfigOn),"",IFERROR(TEXT(IBOVPRICE,"#,##0.00"),"")) -> 183.969,34 | G11: =IF(NOT(ConfigOn),"",TEXT(IBOVCHANGE,"#,##0.00")&" ("&TEXT(IBOVCHANGEPCT,"#,##0.00")&"%)") -> 522,34 (0,28%) | AN11: IFIX | AO11: =AO7 -> 3873.59 | AP11: =AP7 -> -0.0007 | AQ11: =AQ7 -> 0.0078392906 | AR11: =IFERROR(__xludf.DUMMYFUNCTION("IF(NOT(ConfigOn),"""",IFERROR(SPARKLINE(GOOGLEFINANCE(""INDEXBVMF:""&AN11,""price"",TODAY()-$AS$4,TODAY()))))"),"") | AV11: ='config.parâmetros'!P7
B12: =IFERROR(__xludf.DUMMYFUNCTION("IF(NOT(ConfigOn),"""",IFERROR(SPARKLINE(IBOVCHANGEHISTORICO,{""charttype"",""column"";""negcolor"",""red""}),""Dados não disponíveis no momento""))"),"") | M12: PESO DESEJADO % | Q12: =IF(NOT(config.books!$BU$1),"","100%") | R12: =IFERROR(__xludf.DUMMYFUNCTION("IF(NOT($AV$7),"""",IFERROR(TRANSPOSE(query({config.books!BN5:BV14;config.books!BN22:BV24},""select Col3 where Col2 is not null and Col4<>0 order by Col9""))))"),"") | AN12: .DJI | AO12: =IFERROR(__xludf.DUMMYFUNCTION("IF(NOT(ConfigOn),"""",IFERROR(GOOGLEFINANCE(AN12)))"),47417.27) -> 47417.27 | AP12: =IFERROR(__xludf.DUMMYFUNCTION("IF(NOT(ConfigOn),"""",IFERROR(AO12/INDEX(SORT(GOOGLEFINANCE(AN12,""price"",TODAY()-3,TODAY(),1),1,0),2,2)-1))"),-0.006062904203220976) -> -0.0060629042 | AQ12: =IFERROR(__xludf.DUMMYFUNCTION("IF(NOT(ConfigOn),"""",IFERROR(AO12/INDEX(GOOGLEFINANCE(AN12,""price"",TODAY()-$AS$4,TODAY(),1),2,2)-1))"),-0.0542246499362633) -> -0.05422465 | AR12: =IFERROR(__xludf.DUMMYFUNCTION("IF(NOT(ConfigOn),"""",IFERROR(SPARKLINE(GOOGLEFINANCE(AN12,""price"",TODAY()-$AS$4,TODAY()))))"),"")
M13: PESO ATUAL% | R13: =IFERROR(__xludf.DUMMYFUNCTION("IF(NOT($AV$7),"""",IFERROR(TRANSPOSE(query({config.books!BN5:BV14;config.books!BN22:BV24},""select Col6,Col4,Col5 where Col2 is not null and Col4<>0 order by Col9""))))"),"") | AN13: .IXIC | AO13: =IFERROR(__xludf.DUMMYFUNCTION("IF(NOT(ConfigOn),"""",IFERROR(GOOGLEFINANCE(AN13)))"),22716.14) -> 22716.14 | AP13: =IFERROR(__xludf.DUMMYFUNCTION("IF(NOT(ConfigOn),"""",IFERROR(AO13/INDEX(SORT(GOOGLEFINANCE(AN13,""price"",TODAY()-3,TODAY(),1),1,0),2,2)-1))"),0.0) -> 0 | AQ13: =IFERROR(__xludf.DUMMYFUNCTION("IF(NOT(ConfigOn),"""",IFERROR(AO13/INDEX(GOOGLEFINANCE(AN13,""price"",TODAY()-$AS$4,TODAY(),1),2,2)-1))"),-0.022485365986951833) -> -0.022485366 | AR13: =IFERROR(__xludf.DUMMYFUNCTION("IF(NOT(ConfigOn),"""",IFERROR(SPARKLINE(GOOGLEFINANCE(AN13,""price"",TODAY()-$AS$4,TODAY()))))"),"") | AV13: Só ativos com indicação?
B14: IFIX | H14: gráfico últimos 10 dias | M14: FLUXO DE CAIXA | Q14: =IF(NOT(config.books!$BU$1),"",IFERROR(SUM(config.books!BQ22:BQ24),0)) | AN14: ="USD"&'config.parâmetros'!$B$8 -> USDBRL | AO14: =AO8 -> 5.1928009 | AP14: =AP8 -> 0.0055967215 | AQ14: =AQ8 -> 0.0002313179 | AR14: =IFERROR(__xludf.DUMMYFUNCTION("IF(NOT(ConfigOn),"""",IFERROR(SPARKLINE(GOOGLEFINANCE(AN14,""price"",TODAY()-$AS$4,TODAY()))))"),"") | AV14: =IF(AJ42="Ativos com posição",FALSE,TRUE) -> FALSE
B15: =IF(NOT(ConfigOn),"",IFERROR(TEXT(IFIXPRICE,"#,##0.00"),"")) -> 3.873,59 | G15: =IF(NOT(ConfigOn),"",TEXT(IFIXCHANGE,"#,##0.00")&" ("&TEXT(IFIXCHANGEPCT,"0.00")&"%)") -> -2,86 (-0,07%) | M15: VALOR DE MERCADO | Q15: =IF(NOT(config.books!$BU$1),"",IFERROR(SUM(config.books!BR22:BR24),0)) | AN15: BTCUSD | AO15: =IFERROR(__xludf.DUMMYFUNCTION("IF(NOT(ConfigOn),"""",IFERROR(GOOGLEFINANCE(AN15)))"),70264.21) -> 70264.21 | AP15: =IFERROR(__xludf.DUMMYFUNCTION("IF(NOT(ConfigOn),"""",IFERROR(AO15/INDEX(SORT(GOOGLEFINANCE(AN15,""price"",TODAY()-3,TODAY(),1),1,0),2,2)-1))"),0.004717571308724411) -> 0.0047175713 | AQ15: =IFERROR(__xludf.DUMMYFUNCTION("IF(NOT(ConfigOn),"""",IFERROR(AO15/INDEX(GOOGLEFINANCE(AN15,""price"",TODAY()-$AS$4,TODAY(),1),2,2)-1))"),-0.010452577450401956) -> -0.010452577 | AR15: =IFERROR(__xludf.DUMMYFUNCTION("IF(NOT(ConfigOn),"""",IFERROR(SPARKLINE(GOOGLEFINANCE(AN15,""price"",TODAY()-$AS$4,TODAY()))))"),"")
B16: =IFERROR(__xludf.DUMMYFUNCTION("IF(NOT(ConfigOn),"""",IFERROR(SPARKLINE(IFIXCHANGEHISTORICO,{""charttype"",""column"";""negcolor"",""red""}),""Dados não disponíveis no momento""))"),"")
M17: LUCRO TOTAL SOBRE O FLUXO DE CAIXA | Q17: =IF(NOT(config.books!$BU$1),"",SUM(config.books!BT22:BT24)) | R17: =IFERROR(__xludf.DUMMYFUNCTION("IF(NOT($AV$7),"""",IFERROR(TRANSPOSE(query({config.books!BN5:BV14;config.books!BN22:BV24},""select Col7,Col8 where Col2 is not null and Col4<>0 order by Col9""))))"),"") | AN17: =B4 -> SELIC | AO17: =B7 -> LTN-23 | AP17: =D7 -> LTN-26 | AQ17: =F7 -> NTNB-26 | AR17: =H7 -> NTNB-35 | AS17: =J7 -> NTNB-45 | AV17: Total ou sem carteiras?
Q18: =IF(NOT($AV$7),"",IFERROR(Q17/Q15,"")) | AN18: =B5 -> 0.1275 | AO18: =B8 -> 5.14% | AP18: =D8 -> 1.32% | AQ18: =H8 -> 5.74% | AR18: =H8 -> 5.74% | AS18: =J8 -> 5.74% | AV18: =OR(CW63,carteiras.!$AE$4=0,NOT(M20)) -> TRUE
B20: MAIORES LUCROS/PREJUÍZOS HOJE | I20: AÇÃO | M20: TRUE | N20: CARTEIRAS | Q20: TRUE | R20: FALSE | S20: FALSE | T20: FALSE | U20: FALSE | V20: FALSE | W20: FALSE | X20: FALSE | Y20: FALSE | Z20: FALSE | AA20: FALSE | AB20: FALSE | AC20: FALSE | AD20: FALSE | AE20: FALSE | AF20: FALSE | AG20: FALSE | AH20: FALSE | AI20: FALSE | AJ20: FALSE | AK20: FALSE | AL20: FALSE | AN20: FALSE | AP20: CORRETORA | AQ20: TOTAL (A+B) | AR20: BRL (A) | AS20: USD (B)
B21: {=TRANSPOSE(BW44:BW53)} | Q21: =IFERROR(__xludf.DUMMYFUNCTION("TRANSPOSE(IFERROR(query({CZ44:DP53;CZ55:DP58;CZ60:DP63},""select Col1,Col5,Col3,Col4 where Col1<>'' and Col1<>'-' order by Col17"",0)))"),"") | AN21: CONTROLE DO SALDO EM CAIXA
M22: PESO DESEJADO % | AN22: Saldo Inicial (+) | AP22: =IFERROR(__xludf.DUMMYFUNCTION("IF(NOT(caixa!$AC$7),"""",SUM(IFERROR(FILTER(caixa!$O$5:$O$24,caixa!$M$5:$M$24=VLOOKUP($AP$21,caixa!$AB$10:$AD$29,2,FALSE),caixa!$N$5:$N$24=VLOOKUP($AP$21,caixa!$AB$10:$AD$29,3,FALSE)),0)))"),"") | AQ22: =caixa!AE8 | AR22: =caixa!AE5 | AS22: =caixa!AE6
M23: PESO ATUAL % | AN23: Remessas e saques (+) | AP23: =IFERROR(__xludf.DUMMYFUNCTION("IF(NOT(caixa!$AC$7),"""",SUM(IFERROR(FILTER(caixa!$R$5:$R$24,caixa!$M$5:$M$24=VLOOKUP($AP$21,caixa!$AB$10:$AD$29,2,FALSE),caixa!$N$5:$N$24=VLOOKUP($AP$21,caixa!$AB$10:$AD$29,3,FALSE)),0)))"),"") | AQ23: =caixa!AF8 | AR23: =caixa!AF5 | AS23: =caixa!AF6
B24: =IFERROR(__xludf.DUMMYFUNCTION("TRANSPOSE(SPARKLINE({BV44:BV53},{""charttype"",""column"";""negcolor"",""red""}))"),"") | M24: PESO NO SUBGRUPO % | AN24: Outros créditos e débitos (+) | AP24: =IFERROR(__xludf.DUMMYFUNCTION("IF(NOT(caixa!$AC$7),"""",SUM(IFERROR(FILTER(caixa!$S$5:$S$24,caixa!$M$5:$M$24=VLOOKUP($AP$21,caixa!$AB$10:$AD$29,2,FALSE),caixa!$N$5:$N$24=VLOOKUP($AP$21,caixa!$AB$10:$AD$29,3,FALSE)),0)))"),"") | AQ24: =caixa!AG8 | AR24: =caixa!AG5 | AS24: =caixa!AG6
M26: FLUXO DE CAIXA | Q26: =IFERROR(__xludf.DUMMYFUNCTION("TRANSPOSE(IFERROR(query({CZ44:DP53;CZ55:DP58;CZ60:DP63},""select Col6,Col7,Col8 where Col1<>'' and Col1<>'-' order by Col17"",0)))"),"") | AN26: Proventos recebidos (+) | AP26: =IFERROR(__xludf.DUMMYFUNCTION("IF(NOT(caixa!$AC$7),"""",SUM(IFERROR(FILTER(caixa!$U$5:$U$24,caixa!$M$5:$M$24=VLOOKUP($AP$21,caixa!$AB$10:$AD$29,2,FALSE),caixa!$N$5:$N$24=VLOOKUP($AP$21,caixa!$AB$10:$AD$29,3,FALSE)),0)))"),"") | AQ26: =caixa!AI8 | AR26: =caixa!AI5 | AS26: =caixa!AI6
M27: VALOR INVESTIDO | AN27: Day trade (+) | AP27: =IFERROR(__xludf.DUMMYFUNCTION("IF(NOT(caixa!$AC$7),"""",SUM(IFERROR(FILTER(caixa!$T$5:$T$24,caixa!$M$5:$M$24=VLOOKUP($AP$21,caixa!$AB$10:$AD$29,2,FALSE),caixa!$N$5:$N$24=VLOOKUP($AP$21,caixa!$AB$10:$AD$29,3,FALSE)),0)))"),"") | AQ27: =caixa!AH8 | AR27: =caixa!AH5 | AS27: =caixa!AH6
M28: VALOR DE MERCADO | AN28: Operações realizadas (-) | AP28: =IFERROR(__xludf.DUMMYFUNCTION("IF(NOT(caixa!$AC$7),"""",SUM(IFERROR(FILTER(caixa!$V$5:$V$24,caixa!$M$5:$M$24=VLOOKUP($AP$21,caixa!$AB$10:$AD$29,2,FALSE),caixa!$N$5:$N$24=VLOOKUP($AP$21,caixa!$AB$10:$AD$29,3,FALSE)),0)))"),"") | AQ28: =caixa!AJ8 | AR28: =caixa!AJ5 | AS28: =caixa!AJ6
M30: LUCRO DIA | Q30: =IFERROR(__xludf.DUMMYFUNCTION("TRANSPOSE(IFERROR(query({CZ44:DP53;CZ55:DP58;CZ60:DP63},""select Col9,Col10 where Col1<>'' and Col1<>'-' order by Col17"",0)))"),"") | AN30: SALDO EM CAIXA (=) | AP30: =IFERROR(__xludf.DUMMYFUNCTION("IF(NOT(caixa!$AC$7),"""",SUM(IFERROR(FILTER(caixa!$W$5:$W$24,caixa!$M$5:$M$24=VLOOKUP($AP$21,caixa!$AB$10:$AD$29,2,FALSE),caixa!$N$5:$N$24=VLOOKUP($AP$21,caixa!$AB$10:$AD$29,3,FALSE)),0)))"),"") | AQ30: =caixa!AK8 | AR30: =caixa!AK5 | AS30: =caixa!AK6
M33: PROVENTOS | Q33: =IFERROR(__xludf.DUMMYFUNCTION("TRANSPOSE(IFERROR(query({CZ44:DP53;CZ55:DP58;CZ60:DP63},""select Col11,Col12,Col13,Col14 where Col1<>'' and Col1<>'-' order by Col17"",0)))"),"") | AN33: REMESSAS PARA INVESTIMENTO | AR33: CORRETORA | AS33: SALDO | AV33: FILTROS
M34: TRADES | AN34: Média Mensal | AO34: =caixa!Z16 | AP34: Últimos 12 m | AQ34: =caixa!Z24 | AR34: {=caixa!Y30:Z32} | AV34: =IFERROR(__xludf.DUMMYFUNCTION("IFERROR("" and (""&AZ42&""='""&join(""' or ""&AZ42&""='"",QUERY({BH44:BH343},""select Col1 where Col1 is not null""))&""') "")"),"")
M35: LUCRO ABERTO | AN35: {=caixa!Y18:Z19} -> 46112 | AP35: {=caixa!Y25:Z26} -> 2026 | AV35: =IFERROR(__xludf.DUMMYFUNCTION("IFERROR("" and (""&$BA$42&"" like '""&join(""' or ""&$BA$42&"" like '"",Filter($AI$44:$AI$62,($AJ$44:$AJ$62=TRUE)*($AI$44:$AI$62<>"""")))&""') "","" and ""&$BA$42&""='***###@@@'"")")," and Col4='***###@@@'") -> and Col4='***###@@@'
B36: {=TRANSPOSE(BS44:BS53)} | M36: LUCRO TOTAL | AN36: 46081 | AP36: 2025 | AV36: =IFERROR(__xludf.DUMMYFUNCTION("IFERROR("" and (""&$BF$42&"" like '""&join(""' or ""&$BF$42&"" like '"",Filter($AK$44:$AK$62,($AL$44:$AL$62=TRUE)*($AK$44:$AK$62<>"""")))&""') "",$BF$42&""='***###@@@'"")"),"Col20='***###@@@'") -> Col20='***###@@@'
M37: =("Col"&MATCH(M$40,portfolio.!$A$3:DQ$3,0)) -> Col68 | N37: =("Col"&MATCH(N$40,portfolio.!$A$3:$BO$3,0)) -> Col54 | P37: =("Col"&MATCH(P$40,portfolio.!$A$3:$BO$3,0)) -> Col56 | Q37: =("Col"&MATCH(Q$40,portfolio.!$A$3:$BO$3,0)) -> Col64 | R37: =("Col"&MATCH(R$40,portfolio.!$A$3:$BO$3,0)) -> Col39 | S37: =("Col"&MATCH(S$40,portfolio.!$A$3:$BO$3,0)) -> Col58 | T37: =("Col"&MATCH(T$40,portfolio.!$A$3:$BO$3,0)) -> Col15 | U37: =("Col"&MATCH(U$40,portfolio.!$A$3:$BO$3,0)) -> Col40 | V37: =("Col"&MATCH(V$40,portfolio.!$A$3:$BO$3,0)) -> Col60 | X37: =("Col"&MATCH(X$40,portfolio.!$A$3:$BO$3,0)) -> Col43 | Y37: =("Col"&MATCH(Y$40,portfolio.!$A$3:$BO$3,0)) -> Col44 | Z37: =("Col"&MATCH(Z$40,portfolio.!$A$3:$BO$3,0)) -> Col61 | AA37: =("Col"&MATCH(AA$40,portfolio.!$A$3:$BO$3,0)) -> Col63 | AB37: =("Col"&MATCH(AB$40,portfolio.!$A$3:$BO$3,0)) -> Col67 | AC37: =("Col"&MATCH(AC$40,portfolio.!$A$3:$BO$3,0)) -> Col66 | AD37: =("Col"&MATCH(AD$40,portfolio.!$A$3:$BO$3,0)) -> Col7 | AF37: =("Col"&MATCH(AF$40,portfolio.!$A$3:$BO$3,0)) -> Col45 | AN37: {=caixa!Y20:Z20} -> 46053 | AP37: {=caixa!Y27:Z27} -> 2024 | AR37: {=caixa!Y33:Z34}
M38: RENTABILIDADE (TIR) | Q38: =IFERROR(__xludf.DUMMYFUNCTION("TRANSPOSE(IFERROR(query({CZ44:DP53;CZ55:DP58;CZ60:DP63},""select Col15, Col16 where Col1<>'' and Col1<>'-' order by Col17"",0)))"),"")
AN39: {=caixa!Y21:Z21} -> 46022 | AP39: {=caixa!Y28:Z28} -> 2023 | AR39: {=caixa!Y34:Z34} | AV39: ORDENAMENTO | AZ39: FORMATACAO CONDICIONAL | BH39: FILTRO DOS ATIVOS | BP39: GRÁFICO DE MAIORES LUCROS E PREJUÍZOS DO DIA | BY39: DADOS PARA GERAÇÃO DOS GRÁFICOS | CM39: GRAFICO EXPOSIÇÃO | CO39: GRÁFICO LUCROS | CR39: SELEÇÃO DO GRÁFICO A SER EXIBIDO | CV39: CÁLCULOS DO PAINEL
M40: nome_pregao_portfolio | N40: ocorrencias | P40: qtd_atual+corretora | Q40: =if(Q41="PM","pm_atual","pm_ajust") -> pm_ajust | R40: cotacao | S40: pr_teto+upside | T40: vlr_investido | U40: vlr_mercado | V40: lucro_dia+pct | X40: lucro_aberto | Y40: lucro_aberto_pct | Z40: trades+pct | AA40: provento+pct | AB40: lucro_total | AC40: tir_am+aa | AD40: =IF(AD41="Setor","setor","subsetor") -> setor | AF40: dias_pct
B41: CARTEIRAS ONDE HÁ EXPOSIÇÃO | M41: ▼ | N41: Em x cart. | O41: Peso % | P41: Custódia | Q41: PM (PM Ajust) | R41: Cotação | S41: Preço Teto | T41: Valor Investido | U41: Valor de Mercado | V41: Lucro Dia | X41: =IFERROR(__xludf.DUMMYFUNCTION("""Lucros | Média Mensal Proventos: ""&IF(ConfigOn,TEXT(IFERROR(query({AtivosDados},""select sum(""&BH42&"") where Col1 is not null ""&AV34&AV35&AV36&"" label sum(""&BH42&"") ''""),0),""#,###,##0.00""),"""")"),"Lucros | Média Mensal Proventos: 0,00") -> Lucros | Média Mensal Proventos: 0,00 | AC41: TIR | AD41: Setor | AF41: Desempenho | AI41: OPÇÕES DE FILTROS | AN41: EXPOSIÇÃO POR SETOR | AV41: lucro_dia | AW41: provento | AX41: trades | AZ41: ativo | BA41: classe | BB41: tir_am | BC41: trades | BD41: lucro_dia_pct | BE41: upside | BF41: corretora_investidor | BH41: provento_avg | BP41: MAX (+) | BQ41: =IF(ConfigOn,COUNTIFS(portfolio.!$D$4:$D343,$BT$41,portfolio.!$AO$4:$AO343,">=0"),0) -> 0 | BR41: =IF(NOT(ConfigOn),"",IF(BQ41+BQ42<10,BQ41,IF(BQ42<5,10-BQ42,IF(BQ41<5,BQ41,5)))) -> 0 | BS41: CLASSE -> | BT41: =I20 -> AÇÃO | BY41: PERFIL | BZ41: VALOR MERCADO POR PERFIL | CA41: LUCRO POR PERFIL | CB41: NOME DAS CARTEIRAS | CC41: VALOR MERCADO POR CARTEIRA | CD41: LUCRO POR CARTEIRA | CE41: NOME DOS BOOKS | CF41: VALOR MERCADO POR BOOK | CG41: LUCRO POR BOOK | CH41: ATIVO | CI41: SETOR | CJ41: CLASSE | CK41: VLR DE MERCADO POR ATIVO | CL41: LUCRO POR ATIVO | CM41: LEGENDA | CN41: VALOR | CO41: LEGENDA | CP41: VALOR | CR41: LISTA GRÁFICOS 1 | CS41: QUERY
M42: LUCRO DIA % | V42: ='config.parâmetros'!B8 -> BRL | W42: % | X42: Aberto | Y42: % | Z42: Trades | AA42: Proventos | AB42: Total | AC42: ="% am"&" % aa" -> % am % aa | AF42: =AF43&" dias (%)" -> 30 dias (%) | AG42: ="Gráfico "&AF43&" dias" -> Gráfico 30 dias | AI42: Exibir ▶ | AJ42: Ativos com posição | AV42: ="Col"&MATCH(AV41,portfolio.!$A$3:$BO$3,0) -> Col41 | AW42: ="Col"&MATCH(AW41,portfolio.!$A$3:$BO$3,0) -> Col50 | AX42: ="Col"&MATCH(AX41,portfolio.!$A$3:$BO$3,0) -> Col52 | AZ42: ="Col"&MATCH(AZ41,portfolio.!$A$3:$BO$3,0) -> Col1 | BA42: ="Col"&MATCH(BA41,portfolio.!$A$3:$BO$3,0) -> Col4 | BB42: ="Col"&MATCH(BB41,portfolio.!$A$3:$BO$3,0) -> Col65 | BC42: ="Col"&MATCH(BC41,portfolio.!$A$3:$BO$3,0) -> Col52 | BD42: ="Col"&MATCH(BD41,portfolio.!$A$3:$BO$3,0) -> Col42 | BE42: ="Col"&MATCH(BE41,portfolio.!$A$3:$BO$3,0) -> Col57 | BF42: ="Col"&MATCH(BF41,portfolio.!$A$3:$BO$3,0) -> Col20 | BH42: ="Col"&MATCH(BH41,portfolio.!$A$3:$BO$3,0) -> Col51 | BP42: MAX( -) | BQ42: =IF(ConfigOn,COUNTIFS(portfolio.!$D$4:$D343,$BT$41,portfolio.!$AO$4:$AO343,"<0"),0) -> 0 | BR42: =IF(NOT(ConfigOn),"",IF(BQ42+BQ41<10,BQ42,IF(BQ41<5,10-BQ41,IF(BQ42<5,BQ42,5)))) -> 0 | BS42: ATIVOS 5+ e 5- NOBLANK | BT42: LUCRO DIA 5+ NOBLANK | BU42: LUCRO DIA 5- NOBLANK | BV42: LUCRO DIA 10 AÇÕES | BW42: LUCRO DIA 10 AÇÕES | CR42: EXPOSIÇÃO POR ATIVO | CS42: ="select Col10, Col13 where Col10 is not null" -> select Col10, Col13 where Col10 is not null | CZ42: 1 | DA42: 2 | DB42: 3 | DC42: 4 | DD42: 5 | DE42: 6 | DF42: 7 | DG42: 8 | DH42: 9 | DI42: 10 | DJ42: 11 | DK42: 12 | DL42: 13 | DM42: 14 | DN42: 15 | DO42: 16 | DP42: 17
B43: {=IF(AV8,TRANSPOSE(CarteirasListaCriadasAbreviada),"")} | M43: ATIVOS | O43: =IF(ConfigOn,SUM(O44:O343),"") -> 0 | P43: CUSTÓDIA E VALOR DOS ATIVOS POR UNIDADE | T43: =IF(ConfigOn,SUM(T44:T343),"") -> 0 | U43: =IF(ConfigOn,SUM(U44:U343),"") -> 0 | V43: =IFERROR(__xludf.DUMMYFUNCTION("IF(ConfigOn,IFERROR(query({AtivosDados},""select sum(""&AV42&"") where Col1 is not null ""&AV34&AV35&AV36&"" label sum(""&AV42&"") ''""),0),"""")"),0.0) -> 0 | W43: =IF(ConfigOn,IFERROR(V43/T43,0),"") -> 0 | X43: =IF(ConfigOn,SUM(X44:X343),"") -> 0 | Y43: =IF(ConfigOn,IFERROR(X43/U43,0),"") -> 0 | Z43: =IFERROR(__xludf.DUMMYFUNCTION("IF(ConfigOn,IFERROR(query({AtivosDados},""select sum(""&AX42&"") where Col1 is not null ""&AV34&AV35&AV36&"" label sum(""&AX42&"") ''""),0),"""")"),0.0) -> 0 | AA43: =IFERROR(__xludf.DUMMYFUNCTION("IF(ConfigOn,IFERROR(query({AtivosDados},""select sum(""&AW42&"") where Col1 is not null ""&AV34&AV35&AV36&"" label sum(""&AW42&"") ''""),0),"""")"),0.0) -> 0 | AB43: =IF(ConfigOn,AA43+Z43+X43,"") -> 0 | AF43: 30 | AG43: Gráfico de linha | AI43: filtrar por classe | AK43: filtrar por corretora | AV43: ORDEM | AW43: NOME DA COLUNA | AX43: COLUNA | AZ43: ATIVOS ORDENADOS | BA43: CLASSE ORDENADOS | BB43: TIR MENSAL | BD43: LUCRO DIA | BE43: PRECO TETO UPSIZE | BF43: LUCRO DIA ABS | BH43: SELECTED | BI43: SUBTOTAL 01 | BJ43: GRUPO 01 | BK43: SUBTOTAL 02 | BL43: GRUPO 02 | BM43: SUBTOTAL 03 | BP43: ATIVOS 5+ e 5- | BQ43: LUCRO DIA 5+ | BR43: LUCRO DIA 5- | BY43: 1 | BZ43: 2 | CA43: 3 | CB43: 4 | CC43: 5 | CD43: 6 | CE43: 7 | CF43: 8 | CG43: 9 | CH43: 10 | CI43: 11 | CJ43: 12 | CK43: 13 | CL43: 14 | CM43: =AN41 -> EXPOSIÇÃO POR SETOR | CO43: =AN50 -> LUCRO POR SETOR | CR43: ="EXPOSIÇÃO POR "&UPPER(AD41) -> EXPOSIÇÃO POR SETOR | CS43: select Col11, sum(Col13) where Col11 is not null group by Col11 label sum(Col13) '' | CV43: GRUPO | CW43: CHECK | CX43: CATEGORIA SUBTOTAL | CY43: PERFIL CRIADAS | CZ43: CARTEIRAS CRIADAS | DB43: PESO % | DC43: PESO GRUPO % | DD43: PESO DESEJADO % | DE43: Valor Aportado | DF43: Valor Investido | DG43: Valor Mercado | DH43: Lucro dia R$ | DI43: Lucro dia % | DJ43: Valor Proventos | DK43: Valor Trades | DL43: Lucro Aberto | DM43: Lucro Total | DN43: TIR am | DO43: TIR aa | DP43: ORDER
B44: =IFERROR(__xludf.DUMMYFUNCTION("IF(B$43="""","""",IF($AZ44="""","""",IFERROR(Query({CarteirasAtivos},""Select Col3 where Col1 = '""&$AZ44&""'and Col2 = '""&S$21&""'""))))"),"") | C44: =IFERROR(__xludf.DUMMYFUNCTION("IF(C$43="""","""",IF($AZ44="""","""",IFERROR(Query({CarteirasAtivos},""Select Col3 where Col1 = '""&$AZ44&""'and Col2 = '""&T$21&""'""))))"),"") | D44: =IFERROR(__xludf.DUMMYFUNCTION("IF(D$43="""","""",IF($AZ44="""","""",IFERROR(Query({CarteirasAtivos},""Select Col3 where Col1 = '""&$AZ44&""'and Col2 = '""&U$21&""'""))))"),"") | E44: =IFERROR(__xludf.DUMMYFUNCTION("IF(E$43="""","""",IF($AZ44="""","""",IFERROR(Query({CarteirasAtivos},""Select Col3 where Col1 = '""&$AZ44&""'and Col2 = '""&V$21&""'""))))"),"") | F44: =IFERROR(__xludf.DUMMYFUNCTION("IF(F$43="""","""",IF($AZ44="""","""",IFERROR(Query({CarteirasAtivos},""Select Col3 where Col1 = '""&$AZ44&""'and Col2 = '""&W$21&""'""))))"),"") | G44: =IFERROR(__xludf.DUMMYFUNCTION("IF(G$43="""","""",IF($AZ44="""","""",IFERROR(Query({CarteirasAtivos},""Select Col3 where Col1 = '""&$AZ44&""'and Col2 = '""&X$21&""'""))))"),"") | H44: =IFERROR(__xludf.DUMMYFUNCTION("IF(H$43="""","""",IF($AZ44="""","""",IFERROR(Query({CarteirasAtivos},""Select Col3 where Col1 = '""&$AZ44&""'and Col2 = '""&Y$21&""'""))))"),"") | I44: =IFERROR(__xludf.DUMMYFUNCTION("IF(I$43="""","""",IF($AZ44="""","""",IFERROR(Query({CarteirasAtivos},""Select Col3 where Col1 = '""&$AZ44&""'and Col2 = '""&Z$21&""'""))))"),"") | J44: =IFERROR(__xludf.DUMMYFUNCTION("IF(J$43="""","""",IF($AZ44="""","""",IFERROR(Query({CarteirasAtivos},""Select Col3 where Col1 = '""&$AZ44&""'and Col2 = '""&AA$21&""'""))))"),"") | K44: =IFERROR(__xludf.DUMMYFUNCTION("IF(K$43="""","""",IF($AZ44="""","""",IFERROR(Query({CarteirasAtivos},""Select Col3 where Col1 = '""&$AZ44&""'and Col2 = '""&AB$21&""'""))))"),"") | L44: 1 | M44: =IFERROR(__xludf.DUMMYFUNCTION("IF(NOT(ConfigOn),"""",IFERROR(query({AtivosDados},""select ""&join("","",$M$37:$N$37)&"" where Col1 is not null ""&AV34&AV35&AV36&IFERROR(VLOOKUP($M$42,'portfólio'!AV44:AX56,3, FALSE)))))"),"") | O44: {=IF(M44:M343="","",IFERROR(U44:U343/SUM($U44:$U343),""))} | P44: =IFERROR(__xludf.DUMMYFUNCTION("IF(NOT(ConfigOn),"""",IFERROR(query({AtivosDados},""select ""&join("","",$P$37:$V$37)&"" where Col1 is not null ""&AV34&AV35&AV36&IFERROR(VLOOKUP($M$42,'portfólio'!AV44:AX56,3, FALSE)))))"),"") | W44: =IFERROR(__xludf.DUMMYFUNCTION("IF(M44="""","""",sparkline(IFERROR(BF44*100/MAX($BF$44:$BF343),0),{""charttype"",""bar"";""max"",100;""color1"",IF(BD44>=0,""#4760a5"",""red"")}))"),"") | X44: =IFERROR(__xludf.DUMMYFUNCTION("IF(NOT(ConfigOn),"""",IFERROR(query({AtivosDados},""select ""&join("","",$X$37:$AD$37)&"" where Col1 is not null ""&AV34&AV35&AV36&IFERROR(VLOOKUP($M$42,'portfólio'!AV44:AX56,3, FALSE)))))"),"") | AF44: =IFERROR(__xludf.DUMMYFUNCTION("IF(NOT(ConfigOn),"""",IFERROR(query({AtivosDados},""select ""&join("","",$AF$37)&"" where Col1 is not null ""&AV34&AV35&AV36&IFERROR(VLOOKUP($M$42,'portfólio'!AV44:AX56,3, FALSE)))))"),"") | AG44: =IFERROR(__xludf.DUMMYFUNCTION("IF($M44="""","""",IFERROR(sparkline(query(GOOGLEFINANCE($AZ44,""price"",TODAY()-$AF$43,TODAY(),1),""select Col2 label Col2 ''""),IF($AG$43=""Gráfico de barras"",{""charttype"",""column"";""highcolor"",""red""},{""chartype"",""line""}))))"),"") | AI44: {=SORT(UNIQUE(portfolio.!D4:D343))} | AJ44: TRUE | AK44: {=SORT(UNIQUE(portfolio.!T4:T343))} | AL44: TRUE | AU44: 1 | AV44: RANKING | AW44: ranking | AX44: ="order by Col"&MATCH(AW44,portfolio.!$A$3:$BO$3,0)&" "&IFERROR(VLOOKUP($M$41,$AV$57:$AX$58,3, FALSE),"") -> order by Col53 asc | AY44: 1 | AZ44: =IFERROR(__xludf.DUMMYFUNCTION("IFERROR(query({AtivosDados},""select ""&JOIN("","",$AZ$42:$BE$42)&"" where Col1 is not null ""&AV34&AV35&AV36&IFERROR(VLOOKUP($M$42,'portfólio'!AV44:AX56,3, FALSE))))"),"") | BF44: {=IF(AZ44:AZ343="","",abs(BD44:BD343))} | BG44: 1 | BH44: =IFERROR(__xludf.DUMMYFUNCTION("IF($AV$18,{AtivosLista},UNIQUE(IFERROR(QUERY({BI44:BI343;BJ44:BJ343;BK44:BK343;BL44:BL343;BM44:BM343},""select Col1 where Col1 is not null limit 300""))))"),"") | BI44: =IFERROR(__xludf.DUMMYFUNCTION("IF(AV18,"""",IF(CW60,IFERROR(FILTER(portfolio.!A4:A303,portfolio.!U4:U303=CX60)),""""))"),"") | BJ44: =IFERROR(__xludf.DUMMYFUNCTION("IF(AV18,"""",IF(NOT(CW60),unique(IFERROR(query(IF($AV$14,{CarteirasAtivos},{CarteirasAtivos;CarteirasAtivosEncerrados}),""Select Col1 where Col1 is not null and (Col2 = '""&join(""' or Col2 = '"",filter(CZ44:CZ53,CW44:CW53))&""') order by Col3 limit 300"""&"))),""""))"),"") | BK44: =IFERROR(__xludf.DUMMYFUNCTION("IF(AV18,"""",IF(CW61,IFERROR(FILTER(portfolio.!A4:A303,(portfolio.!U4:U303=CX55)+(portfolio.!U4:U303=CX56)+(portfolio.!U4:U303=CX57)+(portfolio.!U4:U303=CX58))),""""))"),"") | BL44: =IFERROR(__xludf.DUMMYFUNCTION("IF(AV18,"""",IF(NOT(CW61),IFERROR(query({IF(CW55,IFERROR(filter(portfolio.!A4:A303,portfolio.!U4:U303=CX55)),{""""});IF(CW56,IFERROR(filter(portfolio.!A4:A303,portfolio.!U4:U303=CX56)),{""""});IF(CW57,IFERROR(filter(portfolio.!A4:A303,portfolio.!U4:U303=C"&"X57)),{""""});IF(CW58,IFERROR(filter(portfolio.!A4:A303,portfolio.!U4:U303=CX58)),{""""})},""select Col1 where Col1 is not null"")),""""))"),"") | BM44: =IFERROR(__xludf.DUMMYFUNCTION("IF(AV18,"""",IF(CW62,IFERROR(FILTER(portfolio.!A4:A303,portfolio.!U4:U303=CX62)),""""))"),"") | BO44: 1 | BP44: =IFERROR(__xludf.DUMMYFUNCTION("IF(NOT(ConfigOn),query({BP65:BQ74},""select Col1, Col2 where Col2 >= 0 ORDER BY Col2 DESC"",0),IFERROR(query({AtivosDados},""select Col""&MATCH(""ativo"",portfolio.!$A$3:DQ$3,0)&"",Col""&MATCH(""lucro_dia"",portfolio.!$A$3:DQ$3,0)&"" where Col""&MATCH(""c"&"lasse"",portfolio.!$A$3:DQ$3,0)&""='""&$BT$41&""' and Col""&MATCH(""lucro_dia"",portfolio.!$A$3:DQ$3,0)&"">=0 ORDER BY Col""&MATCH(""lucro_dia"",portfolio.!$A$3:DQ$3,0)&"" DESC LIMIT ""&BR41)))"),"") | BS44: =IFERROR(__xludf.DUMMYFUNCTION("IFERROR(query({IFERROR(query({BP44:BR53},""select Col1, Col2, Col3 where Col1 is not null""),{"""","""",""""});IFERROR(query({BP54:BR63},""select Col1, Col2, Col3 where Col1 is not null""),{"""","""",""""})},""select Col1,Col2,Col3 where Col1 is not null"&"""))"),"") | BV44: =IF(AND(BT44="",BU44=""),0,IF(BT44="",BU44,BT44)) -> 0 | BW44: =IF(BV44=0,"",BV44) | BX44: 1 | BY44: {=sort(unique({CY44:CY53;CY55:CY58}))} | BZ44: {=IF(AV8="","",IF(BY44:BY58="",0,SUMIF(CY44:CY58,CONCAT("=",BY44:BY58),DG44:DG58)))} -> 0 | CA44: {=IF(AV8="","",IF(BY44:BY58="",0,SUMIF(CY44:CY58,CONCAT("=",BY44:BY58),DM44:DM58)))} -> 0 | CB44: {={CZ44:CZ53;CZ55:CZ58}} | CC44: {={DG44:DG53;DG55:DG58}} | CD44: {={DM44:DM53;DM55:DM58}} | CE44: {=config.books!BN28:BP38} | CH44: {=AZ44:AZ343} | CI44: {=AD44:AD343} | CJ44: {=BA44:BA343} | CK44: {=U44:U343} | CL44: {=IF(CH44:CH343="","",VLOOKUP(CH44:CH343,AtivosDados,MATCH("lucro_total",portfolio.!$A$3:DQ$3,0),FALSE))} | CM44: =IFERROR(__xludf.DUMMYFUNCTION("IFERROR(query({BY44:CL343},VLOOKUP(CM43,CR42:CS54,2,0)))"),"") | CO44: =IFERROR(__xludf.DUMMYFUNCTION("IFERROR(query({BY44:CL343},VLOOKUP(CO43,CR42:CS54,2,0)))"),"") | CR44: EXPOSIÇÃO POR CLASSE | CS44: select Col12, sum(Col13) where Col11 is not null group by Col12 label sum(Col13) '' | CU44: 1 | CV44: CARTEIRAS | CW44: =IFERROR(__xludf.DUMMYFUNCTION("IFERROR(query({$Q$20:$AL$20},""select Col""&MATCH(CZ44,$Q$21:$AL$21,0)))"),"") | CY44: {=if(AV8,CarteirasListaCriadasPerfis,"")} | CZ44: {=IF(AV8,CarteirasListaCriadas,"")} | DB44: =IFERROR(DG44/$DG$63,"") | DC44: =IFERROR(DB44/SUM($DB$44:$DB$53),"") | DD44: {=IF(NOT($AV$8),"",IF(CZ44="","",VLOOKUP(CZ44,config.carteiras!$C$9:$D$23,2,FALSE)))} | DE44: =IF($CZ44="","",DF44-DK44-DJ44) | DF44: {=IF($CZ44="","",VLOOKUP($CZ44,carteiras..!$B$2:$I$16,2,FALSE))} | DG44: {=IF($CZ44="","",VLOOKUP($CZ44,carteiras..!$B$2:$I$16,3,FALSE))} | DH44: {=IF($CZ44="","",VLOOKUP($CZ44,carteiras..!$B$2:$I$16,4,FALSE))} | DI44: =IF($CZ44="","",IFERROR(DH44/DF44,0)) | DJ44: {=IF($CZ44="","",VLOOKUP($CZ44,carteiras..!$B$2:$I$16,5,FALSE))} | DK44: {=IF($CZ44="","",VLOOKUP($CZ44,carteiras..!$B$2:$I$16,6,FALSE))} | DL44: =IF(ConfigOn,DG44-DF44,0) -> 0 | DM44: =IF($CZ44="","",SUM(DJ44:DL44)) | DN44: {=IF($CZ44="","",VLOOKUP($CZ44,carteiras..!$B$2:$I$16,7,FALSE))} | DO44: {=IF($CZ44="","",VLOOKUP($CZ44,carteiras..!$B$2:$I$16,8,FALSE))} | DP44: 2
B45: =IFERROR(__xludf.DUMMYFUNCTION("IF(B$43="""","""",IF($AZ45="""","""",IFERROR(Query({CarteirasAtivos},""Select Col3 where Col1 = '""&$AZ45&""'and Col2 = '""&S$21&""'""))))"),"") | C45: =IFERROR(__xludf.DUMMYFUNCTION("IF(C$43="""","""",IF($AZ45="""","""",IFERROR(Query({CarteirasAtivos},""Select Col3 where Col1 = '""&$AZ45&""'and Col2 = '""&T$21&""'""))))"),"") | D45: =IFERROR(__xludf.DUMMYFUNCTION("IF(D$43="""","""",IF($AZ45="""","""",IFERROR(Query({CarteirasAtivos},""Select Col3 where Col1 = '""&$AZ45&""'and Col2 = '""&U$21&""'""))))"),"") | E45: =IFERROR(__xludf.DUMMYFUNCTION("IF(E$43="""","""",IF($AZ45="""","""",IFERROR(Query({CarteirasAtivos},""Select Col3 where Col1 = '""&$AZ45&""'and Col2 = '""&V$21&""'""))))"),"") | F45: =IFERROR(__xludf.DUMMYFUNCTION("IF(F$43="""","""",IF($AZ45="""","""",IFERROR(Query({CarteirasAtivos},""Select Col3 where Col1 = '""&$AZ45&""'and Col2 = '""&W$21&""'""))))"),"") | G45: =IFERROR(__xludf.DUMMYFUNCTION("IF(G$43="""","""",IF($AZ45="""","""",IFERROR(Query({CarteirasAtivos},""Select Col3 where Col1 = '""&$AZ45&""'and Col2 = '""&X$21&""'""))))"),"") | H45: =IFERROR(__xludf.DUMMYFUNCTION("IF(H$43="""","""",IF($AZ45="""","""",IFERROR(Query({CarteirasAtivos},""Select Col3 where Col1 = '""&$AZ45&""'and Col2 = '""&Y$21&""'""))))"),"") | I45: =IFERROR(__xludf.DUMMYFUNCTION("IF(I$43="""","""",IF($AZ45="""","""",IFERROR(Query({CarteirasAtivos},""Select Col3 where Col1 = '""&$AZ45&""'and Col2 = '""&Z$21&""'""))))"),"") | J45: =IFERROR(__xludf.DUMMYFUNCTION("IF(J$43="""","""",IF($AZ45="""","""",IFERROR(Query({CarteirasAtivos},""Select Col3 where Col1 = '""&$AZ45&""'and Col2 = '""&AA$21&""'""))))"),"") | K45: =IFERROR(__xludf.DUMMYFUNCTION("IF(K$43="""","""",IF($AZ45="""","""",IFERROR(Query({CarteirasAtivos},""Select Col3 where Col1 = '""&$AZ45&""'and Col2 = '""&AB$21&""'""))))"),"") | L45: 2 | W45: =IFERROR(__xludf.DUMMYFUNCTION("IF(M45="""","""",sparkline(IFERROR(BF45*100/MAX($BF$44:$BF$153),0),{""charttype"",""bar"";""max"",100;""color1"",IF(BD45>=0,""#4760a5"",""red"")}))"),"") | AG45: =IFERROR(__xludf.DUMMYFUNCTION("IF($M45="""","""",IFERROR(sparkline(query(GOOGLEFINANCE($AZ45,""price"",TODAY()-$AF$43,TODAY(),1),""select Col2 label Col2 ''""),IF($AG$43=""Gráfico de barras"",{""charttype"",""column"";""highcolor"",""red""},{""chartype"",""line""}))))"),"") | AJ45: TRUE | AL45: TRUE | AU45: 2 | AV45: LUCRO DIA | AW45: lucro_dia | AX45: ="order by Col"&MATCH(AW45,portfolio.!$A$3:$BO$3,0)&" "&IFERROR(VLOOKUP($M$41,$AV$57:$AX$58,3, FALSE),"") -> order by Col41 asc | AY45: 2 | BG45: 2 | BO45: 2 | BV45: =IF(AND(BT45="",BU45=""),0,IF(BT45="",BU45,BT45)) -> 0 | BW45: =IF(BV45=0,"",BV45) | BX45: 2 | BY45: Outros | BZ45: 0 | CA45: 0 | CR45: =if(AV7,"EXPOSIÇÃO POR BOOK","") | CS45: select Col7, Col8 where Col8>0 | CU45: 2 | CV45: CARTEIRAS | CW45: =IFERROR(__xludf.DUMMYFUNCTION("IFERROR(query({$Q$20:$AL$20},""select Col""&MATCH(CZ45,$Q$21:$AL$21,0)))"),"") | DB45: =IFERROR(DG45/$DG$63,"") | DC45: =IFERROR(DB45/SUM($DB$44:$DB$53),"") | DD45: {=IF(NOT($AV$8),"",IF(CZ45="","",VLOOKUP(CZ45,config.carteiras!$C$9:$D$23,2,FALSE)))} | DE45: =IF($CZ45="","",DF45-DK45-DJ45) | DF45: {=IF($CZ45="","",VLOOKUP($CZ45,carteiras..!$B$2:$I$16,2,FALSE))} | DG45: {=IF($CZ45="","",VLOOKUP($CZ45,carteiras..!$B$2:$I$16,3,FALSE))} | DH45: {=IF($CZ45="","",VLOOKUP($CZ45,carteiras..!$B$2:$I$16,4,FALSE))} | DI45: =IF($CZ45="","",IFERROR(DH45/DF45,0)) | DJ45: {=IF($CZ45="","",VLOOKUP($CZ45,carteiras..!$B$2:$I$16,5,FALSE))} | DK45: {=IF($CZ45="","",VLOOKUP($CZ45,carteiras..!$B$2:$I$16,6,FALSE))} | DL45: =IF(ConfigOn,DG45-DF45,0) -> 0 | DM45: =IF($CZ45="","",SUM(DJ45:DL45)) | DN45: {=IF($CZ45="","",VLOOKUP($CZ45,carteiras..!$B$2:$I$16,7,FALSE))} | DO45: {=IF($CZ45="","",VLOOKUP($CZ45,carteiras..!$B$2:$I$16,8,FALSE))} | DP45: 2
B46: =IFERROR(__xludf.DUMMYFUNCTION("IF(B$43="""","""",IF($AZ46="""","""",IFERROR(Query({CarteirasAtivos},""Select Col3 where Col1 = '""&$AZ46&""'and Col2 = '""&S$21&""'""))))"),"") | C46: =IFERROR(__xludf.DUMMYFUNCTION("IF(C$43="""","""",IF($AZ46="""","""",IFERROR(Query({CarteirasAtivos},""Select Col3 where Col1 = '""&$AZ46&""'and Col2 = '""&T$21&""'""))))"),"") | D46: =IFERROR(__xludf.DUMMYFUNCTION("IF(D$43="""","""",IF($AZ46="""","""",IFERROR(Query({CarteirasAtivos},""Select Col3 where Col1 = '""&$AZ46&""'and Col2 = '""&U$21&""'""))))"),"") | E46: =IFERROR(__xludf.DUMMYFUNCTION("IF(E$43="""","""",IF($AZ46="""","""",IFERROR(Query({CarteirasAtivos},""Select Col3 where Col1 = '""&$AZ46&""'and Col2 = '""&V$21&""'""))))"),"") | F46: =IFERROR(__xludf.DUMMYFUNCTION("IF(F$43="""","""",IF($AZ46="""","""",IFERROR(Query({CarteirasAtivos},""Select Col3 where Col1 = '""&$AZ46&""'and Col2 = '""&W$21&""'""))))"),"") | G46: =IFERROR(__xludf.DUMMYFUNCTION("IF(G$43="""","""",IF($AZ46="""","""",IFERROR(Query({CarteirasAtivos},""Select Col3 where Col1 = '""&$AZ46&""'and Col2 = '""&X$21&""'""))))"),"") | H46: =IFERROR(__xludf.DUMMYFUNCTION("IF(H$43="""","""",IF($AZ46="""","""",IFERROR(Query({CarteirasAtivos},""Select Col3 where Col1 = '""&$AZ46&""'and Col2 = '""&Y$21&""'""))))"),"") | I46: =IFERROR(__xludf.DUMMYFUNCTION("IF(I$43="""","""",IF($AZ46="""","""",IFERROR(Query({CarteirasAtivos},""Select Col3 where Col1 = '""&$AZ46&""'and Col2 = '""&Z$21&""'""))))"),"") | J46: =IFERROR(__xludf.DUMMYFUNCTION("IF(J$43="""","""",IF($AZ46="""","""",IFERROR(Query({CarteirasAtivos},""Select Col3 where Col1 = '""&$AZ46&""'and Col2 = '""&AA$21&""'""))))"),"") | K46: =IFERROR(__xludf.DUMMYFUNCTION("IF(K$43="""","""",IF($AZ46="""","""",IFERROR(Query({CarteirasAtivos},""Select Col3 where Col1 = '""&$AZ46&""'and Col2 = '""&AB$21&""'""))))"),"") | L46: 3 | W46: =IFERROR(__xludf.DUMMYFUNCTION("IF(M46="""","""",sparkline(IFERROR(BF46*100/MAX($BF$44:$BF$153),0),{""charttype"",""bar"";""max"",100;""color1"",IF(BD46>=0,""#4760a5"",""red"")}))"),"") | AG46: =IFERROR(__xludf.DUMMYFUNCTION("IF($M46="""","""",IFERROR(sparkline(query(GOOGLEFINANCE($AZ46,""price"",TODAY()-$AF$43,TODAY(),1),""select Col2 label Col2 ''""),IF($AG$43=""Gráfico de barras"",{""charttype"",""column"";""highcolor"",""red""},{""chartype"",""line""}))))"),"") | AJ46: TRUE | AL46: TRUE | AU46: 3 | AV46: LUCRO DIA % | AW46: lucro_dia_pct | AX46: ="order by Col"&MATCH(AW46,portfolio.!$A$3:$BO$3,0)&" "&IFERROR(VLOOKUP($M$41,$AV$57:$AX$58,3, FALSE),"") -> order by Col42 asc | AY46: 3 | BG46: 3 | BO46: 3 | BV46: =IF(AND(BT46="",BU46=""),0,IF(BT46="",BU46,BT46)) -> 0 | BW46: =IF(BV46=0,"",BV46) | BX46: 3 | BZ46: 0 | CA46: 0 | CR46: =if(AV8,"EXPOSIÇÃO POR CARTEIRA","") | CS46: select Col4, Col5 where Col5>0 and Col4 is not null | CU46: 3 | CV46: CARTEIRAS | CW46: =IFERROR(__xludf.DUMMYFUNCTION("IFERROR(query({$Q$20:$AL$20},""select Col""&MATCH(CZ46,$Q$21:$AL$21,0)))"),"") | DB46: =IFERROR(DG46/$DG$63,"") | DC46: =IFERROR(DB46/SUM($DB$44:$DB$53),"") | DD46: {=IF(NOT($AV$8),"",IF(CZ46="","",VLOOKUP(CZ46,config.carteiras!$C$9:$D$23,2,FALSE)))} | DE46: =IF($CZ46="","",DF46-DK46-DJ46) | DF46: {=IF($CZ46="","",VLOOKUP($CZ46,carteiras..!$B$2:$I$16,2,FALSE))} | DG46: {=IF($CZ46="","",VLOOKUP($CZ46,carteiras..!$B$2:$I$16,3,FALSE))} | DH46: {=IF($CZ46="","",VLOOKUP($CZ46,carteiras..!$B$2:$I$16,4,FALSE))} | DI46: =IF($CZ46="","",IFERROR(DH46/DF46,0)) | DJ46: {=IF($CZ46="","",VLOOKUP($CZ46,carteiras..!$B$2:$I$16,5,FALSE))} | DK46: {=IF($CZ46="","",VLOOKUP($CZ46,carteiras..!$B$2:$I$16,6,FALSE))} | DL46: =IF(ConfigOn,DG46-DF46,0) -> 0 | DM46: =IF($CZ46="","",SUM(DJ46:DL46)) | DN46: {=IF($CZ46="","",VLOOKUP($CZ46,carteiras..!$B$2:$I$16,7,FALSE))} | DO46: {=IF($CZ46="","",VLOOKUP($CZ46,carteiras..!$B$2:$I$16,8,FALSE))} | DP46: 2
B47: =IFERROR(__xludf.DUMMYFUNCTION("IF(B$43="""","""",IF($AZ47="""","""",IFERROR(Query({CarteirasAtivos},""Select Col3 where Col1 = '""&$AZ47&""'and Col2 = '""&S$21&""'""))))"),"") | C47: =IFERROR(__xludf.DUMMYFUNCTION("IF(C$43="""","""",IF($AZ47="""","""",IFERROR(Query({CarteirasAtivos},""Select Col3 where Col1 = '""&$AZ47&""'and Col2 = '""&T$21&""'""))))"),"") | D47: =IFERROR(__xludf.DUMMYFUNCTION("IF(D$43="""","""",IF($AZ47="""","""",IFERROR(Query({CarteirasAtivos},""Select Col3 where Col1 = '""&$AZ47&""'and Col2 = '""&U$21&""'""))))"),"") | E47: =IFERROR(__xludf.DUMMYFUNCTION("IF(E$43="""","""",IF($AZ47="""","""",IFERROR(Query({CarteirasAtivos},""Select Col3 where Col1 = '""&$AZ47&""'and Col2 = '""&V$21&""'""))))"),"") | F47: =IFERROR(__xludf.DUMMYFUNCTION("IF(F$43="""","""",IF($AZ47="""","""",IFERROR(Query({CarteirasAtivos},""Select Col3 where Col1 = '""&$AZ47&""'and Col2 = '""&W$21&""'""))))"),"") | G47: =IFERROR(__xludf.DUMMYFUNCTION("IF(G$43="""","""",IF($AZ47="""","""",IFERROR(Query({CarteirasAtivos},""Select Col3 where Col1 = '""&$AZ47&""'and Col2 = '""&X$21&""'""))))"),"") | H47: =IFERROR(__xludf.DUMMYFUNCTION("IF(H$43="""","""",IF($AZ47="""","""",IFERROR(Query({CarteirasAtivos},""Select Col3 where Col1 = '""&$AZ47&""'and Col2 = '""&Y$21&""'""))))"),"") | I47: =IFERROR(__xludf.DUMMYFUNCTION("IF(I$43="""","""",IF($AZ47="""","""",IFERROR(Query({CarteirasAtivos},""Select Col3 where Col1 = '""&$AZ47&""'and Col2 = '""&Z$21&""'""))))"),"") | J47: =IFERROR(__xludf.DUMMYFUNCTION("IF(J$43="""","""",IF($AZ47="""","""",IFERROR(Query({CarteirasAtivos},""Select Col3 where Col1 = '""&$AZ47&""'and Col2 = '""&AA$21&""'""))))"),"") | K47: =IFERROR(__xludf.DUMMYFUNCTION("IF(K$43="""","""",IF($AZ47="""","""",IFERROR(Query({CarteirasAtivos},""Select Col3 where Col1 = '""&$AZ47&""'and Col2 = '""&AB$21&""'""))))"),"") | L47: 4 | W47: =IFERROR(__xludf.DUMMYFUNCTION("IF(M47="""","""",sparkline(IFERROR(BF47*100/MAX($BF$44:$BF$153),0),{""charttype"",""bar"";""max"",100;""color1"",IF(BD47>=0,""#4760a5"",""red"")}))"),"") | AG47: =IFERROR(__xludf.DUMMYFUNCTION("IF($M47="""","""",IFERROR(sparkline(query(GOOGLEFINANCE($AZ47,""price"",TODAY()-$AF$43,TODAY(),1),""select Col2 label Col2 ''""),IF($AG$43=""Gráfico de barras"",{""charttype"",""column"";""highcolor"",""red""},{""chartype"",""line""}))))"),"") | AJ47: TRUE | AL47: TRUE | AU47: 4 | AV47: LUCRO ABERTO | AW47: lucro_aberto | AX47: ="order by Col"&MATCH(AW47,portfolio.!$A$3:$BO$3,0)&" "&IFERROR(VLOOKUP($M$41,$AV$57:$AX$58,3, FALSE),"") -> order by Col43 asc | AY47: 4 | BG47: 4 | BO47: 4 | BV47: =IF(AND(BT47="",BU47=""),0,IF(BT47="",BU47,BT47)) -> 0 | BW47: =IF(BV47=0,"",BV47) | BX47: 4 | BZ47: 0 | CA47: 0 | CR47: =if(AV8,"EXPOSIÇÃO POR PERFIL DE CARTEIRA","") | CS47: select Col1, Col2 where Col2>0 and Col1 is not null | CU47: 4 | CV47: CARTEIRAS | CW47: =IFERROR(__xludf.DUMMYFUNCTION("IFERROR(query({$Q$20:$AL$20},""select Col""&MATCH(CZ47,$Q$21:$AL$21,0)))"),"") | DB47: =IFERROR(DG47/$DG$63,"") | DC47: =IFERROR(DB47/SUM($DB$44:$DB$53),"") | DD47: {=IF(NOT($AV$8),"",IF(CZ47="","",VLOOKUP(CZ47,config.carteiras!$C$9:$D$23,2,FALSE)))} | DE47: =IF($CZ47="","",DF47-DK47-DJ47) | DF47: {=IF($CZ47="","",VLOOKUP($CZ47,carteiras..!$B$2:$I$16,2,FALSE))} | DG47: {=IF($CZ47="","",VLOOKUP($CZ47,carteiras..!$B$2:$I$16,3,FALSE))} | DH47: {=IF($CZ47="","",VLOOKUP($CZ47,carteiras..!$B$2:$I$16,4,FALSE))} | DI47: =IF($CZ47="","",IFERROR(DH47/DF47,0)) | DJ47: {=IF($CZ47="","",VLOOKUP($CZ47,carteiras..!$B$2:$I$16,5,FALSE))} | DK47: {=IF($CZ47="","",VLOOKUP($CZ47,carteiras..!$B$2:$I$16,6,FALSE))} | DL47: =IF(ConfigOn,DG47-DF47,0) -> 0 | DM47: =IF($CZ47="","",SUM(DJ47:DL47)) | DN47: {=IF($CZ47="","",VLOOKUP($CZ47,carteiras..!$B$2:$I$16,7,FALSE))} | DO47: {=IF($CZ47="","",VLOOKUP($CZ47,carteiras..!$B$2:$I$16,8,FALSE))} | DP47: 2
B48: =IFERROR(__xludf.DUMMYFUNCTION("IF(B$43="""","""",IF($AZ48="""","""",IFERROR(Query({CarteirasAtivos},""Select Col3 where Col1 = '""&$AZ48&""'and Col2 = '""&S$21&""'""))))"),"") | C48: =IFERROR(__xludf.DUMMYFUNCTION("IF(C$43="""","""",IF($AZ48="""","""",IFERROR(Query({CarteirasAtivos},""Select Col3 where Col1 = '""&$AZ48&""'and Col2 = '""&T$21&""'""))))"),"") | D48: =IFERROR(__xludf.DUMMYFUNCTION("IF(D$43="""","""",IF($AZ48="""","""",IFERROR(Query({CarteirasAtivos},""Select Col3 where Col1 = '""&$AZ48&""'and Col2 = '""&U$21&""'""))))"),"") | E48: =IFERROR(__xludf.DUMMYFUNCTION("IF(E$43="""","""",IF($AZ48="""","""",IFERROR(Query({CarteirasAtivos},""Select Col3 where Col1 = '""&$AZ48&""'and Col2 = '""&V$21&""'""))))"),"") | F48: =IFERROR(__xludf.DUMMYFUNCTION("IF(F$43="""","""",IF($AZ48="""","""",IFERROR(Query({CarteirasAtivos},""Select Col3 where Col1 = '""&$AZ48&""'and Col2 = '""&W$21&""'""))))"),"") | G48: =IFERROR(__xludf.DUMMYFUNCTION("IF(G$43="""","""",IF($AZ48="""","""",IFERROR(Query({CarteirasAtivos},""Select Col3 where Col1 = '""&$AZ48&""'and Col2 = '""&X$21&""'""))))"),"") | H48: =IFERROR(__xludf.DUMMYFUNCTION("IF(H$43="""","""",IF($AZ48="""","""",IFERROR(Query({CarteirasAtivos},""Select Col3 where Col1 = '""&$AZ48&""'and Col2 = '""&Y$21&""'""))))"),"") | I48: =IFERROR(__xludf.DUMMYFUNCTION("IF(I$43="""","""",IF($AZ48="""","""",IFERROR(Query({CarteirasAtivos},""Select Col3 where Col1 = '""&$AZ48&""'and Col2 = '""&Z$21&""'""))))"),"") | J48: =IFERROR(__xludf.DUMMYFUNCTION("IF(J$43="""","""",IF($AZ48="""","""",IFERROR(Query({CarteirasAtivos},""Select Col3 where Col1 = '""&$AZ48&""'and Col2 = '""&AA$21&""'""))))"),"") | K48: =IFERROR(__xludf.DUMMYFUNCTION("IF(K$43="""","""",IF($AZ48="""","""",IFERROR(Query({CarteirasAtivos},""Select Col3 where Col1 = '""&$AZ48&""'and Col2 = '""&AB$21&""'""))))"),"") | L48: 5 | W48: =IFERROR(__xludf.DUMMYFUNCTION("IF(M48="""","""",sparkline(IFERROR(BF48*100/MAX($BF$44:$BF$153),0),{""charttype"",""bar"";""max"",100;""color1"",IF(BD48>=0,""#4760a5"",""red"")}))"),"") | AG48: =IFERROR(__xludf.DUMMYFUNCTION("IF($M48="""","""",IFERROR(sparkline(query(GOOGLEFINANCE($AZ48,""price"",TODAY()-$AF$43,TODAY(),1),""select Col2 label Col2 ''""),IF($AG$43=""Gráfico de barras"",{""charttype"",""column"";""highcolor"",""red""},{""chartype"",""line""}))))"),"") | AJ48: TRUE | AL48: TRUE | AU48: 5 | AV48: LUCRO ABERTO % | AW48: lucro_aberto_pct | AX48: ="order by Col"&MATCH(AW48,portfolio.!$A$3:$BO$3,0)&" "&IFERROR(VLOOKUP($M$41,$AV$57:$AX$58,3, FALSE),"") -> order by Col44 asc | AY48: 5 | BG48: 5 | BO48: 5 | BV48: =IF(AND(BT48="",BU48=""),0,IF(BT48="",BU48,BT48)) -> 0 | BW48: =IF(BV48=0,"",BV48) | BX48: 5 | BZ48: 0 | CA48: 0 | CR48: LISTA GRÁFICOS 2 | CS48: QUERY | CU48: 5 | CV48: CARTEIRAS | CW48: =IFERROR(__xludf.DUMMYFUNCTION("IFERROR(query({$Q$20:$AL$20},""select Col""&MATCH(CZ48,$Q$21:$AL$21,0)))"),"") | DB48: =IFERROR(DG48/$DG$63,"") | DC48: =IFERROR(DB48/SUM($DB$44:$DB$53),"") | DD48: {=IF(NOT($AV$8),"",IF(CZ48="","",VLOOKUP(CZ48,config.carteiras!$C$9:$D$23,2,FALSE)))} | DE48: =IF($CZ48="","",DF48-DK48-DJ48) | DF48: {=IF($CZ48="","",VLOOKUP($CZ48,carteiras..!$B$2:$I$16,2,FALSE))} | DG48: {=IF($CZ48="","",VLOOKUP($CZ48,carteiras..!$B$2:$I$16,3,FALSE))} | DH48: {=IF($CZ48="","",VLOOKUP($CZ48,carteiras..!$B$2:$I$16,4,FALSE))} | DI48: =IF($CZ48="","",IFERROR(DH48/DF48,0)) | DJ48: {=IF($CZ48="","",VLOOKUP($CZ48,carteiras..!$B$2:$I$16,5,FALSE))} | DK48: {=IF($CZ48="","",VLOOKUP($CZ48,carteiras..!$B$2:$I$16,6,FALSE))} | DL48: =IF(ConfigOn,DG48-DF48,0) -> 0 | DM48: =IF($CZ48="","",SUM(DJ48:DL48)) | DN48: {=IF($CZ48="","",VLOOKUP($CZ48,carteiras..!$B$2:$I$16,7,FALSE))} | DO48: {=IF($CZ48="","",VLOOKUP($CZ48,carteiras..!$B$2:$I$16,8,FALSE))} | DP48: 2
B49: =IFERROR(__xludf.DUMMYFUNCTION("IF(B$43="""","""",IF($AZ49="""","""",IFERROR(Query({CarteirasAtivos},""Select Col3 where Col1 = '""&$AZ49&""'and Col2 = '""&S$21&""'""))))"),"") | C49: =IFERROR(__xludf.DUMMYFUNCTION("IF(C$43="""","""",IF($AZ49="""","""",IFERROR(Query({CarteirasAtivos},""Select Col3 where Col1 = '""&$AZ49&""'and Col2 = '""&T$21&""'""))))"),"") | D49: =IFERROR(__xludf.DUMMYFUNCTION("IF(D$43="""","""",IF($AZ49="""","""",IFERROR(Query({CarteirasAtivos},""Select Col3 where Col1 = '""&$AZ49&""'and Col2 = '""&U$21&""'""))))"),"") | E49: =IFERROR(__xludf.DUMMYFUNCTION("IF(E$43="""","""",IF($AZ49="""","""",IFERROR(Query({CarteirasAtivos},""Select Col3 where Col1 = '""&$AZ49&""'and Col2 = '""&V$21&""'""))))"),"") | F49: =IFERROR(__xludf.DUMMYFUNCTION("IF(F$43="""","""",IF($AZ49="""","""",IFERROR(Query({CarteirasAtivos},""Select Col3 where Col1 = '""&$AZ49&""'and Col2 = '""&W$21&""'""))))"),"") | G49: =IFERROR(__xludf.DUMMYFUNCTION("IF(G$43="""","""",IF($AZ49="""","""",IFERROR(Query({CarteirasAtivos},""Select Col3 where Col1 = '""&$AZ49&""'and Col2 = '""&X$21&""'""))))"),"") | H49: =IFERROR(__xludf.DUMMYFUNCTION("IF(H$43="""","""",IF($AZ49="""","""",IFERROR(Query({CarteirasAtivos},""Select Col3 where Col1 = '""&$AZ49&""'and Col2 = '""&Y$21&""'""))))"),"") | I49: =IFERROR(__xludf.DUMMYFUNCTION("IF(I$43="""","""",IF($AZ49="""","""",IFERROR(Query({CarteirasAtivos},""Select Col3 where Col1 = '""&$AZ49&""'and Col2 = '""&Z$21&""'""))))"),"") | J49: =IFERROR(__xludf.DUMMYFUNCTION("IF(J$43="""","""",IF($AZ49="""","""",IFERROR(Query({CarteirasAtivos},""Select Col3 where Col1 = '""&$AZ49&""'and Col2 = '""&AA$21&""'""))))"),"") | K49: =IFERROR(__xludf.DUMMYFUNCTION("IF(K$43="""","""",IF($AZ49="""","""",IFERROR(Query({CarteirasAtivos},""Select Col3 where Col1 = '""&$AZ49&""'and Col2 = '""&AB$21&""'""))))"),"") | L49: 6 | W49: =IFERROR(__xludf.DUMMYFUNCTION("IF(M49="""","""",sparkline(IFERROR(BF49*100/MAX($BF$44:$BF$153),0),{""charttype"",""bar"";""max"",100;""color1"",IF(BD49>=0,""#4760a5"",""red"")}))"),"") | AG49: =IFERROR(__xludf.DUMMYFUNCTION("IF($M49="""","""",IFERROR(sparkline(query(GOOGLEFINANCE($AZ49,""price"",TODAY()-$AF$43,TODAY(),1),""select Col2 label Col2 ''""),IF($AG$43=""Gráfico de barras"",{""charttype"",""column"";""highcolor"",""red""},{""chartype"",""line""}))))"),"") | AJ49: TRUE | AL49: TRUE | AU49: 6 | AV49: PROVENTOS | AW49: provento | AX49: ="order by Col"&MATCH(AW49,portfolio.!$A$3:$BO$3,0)&" "&IFERROR(VLOOKUP($M$41,$AV$57:$AX$58,3, FALSE),"") -> order by Col50 asc | AY49: 6 | BG49: 6 | BO49: 6 | BV49: =IF(AND(BT49="",BU49=""),0,IF(BT49="",BU49,BT49)) -> 0 | BW49: =IF(BV49=0,"",BV49) | BX49: 6 | BZ49: 0 | CA49: 0 | CR49: LUCRO POR ATIVO | CS49: select Col10, Col14 where Col10 is not null and Col14<>0 | CU49: 6 | CV49: CARTEIRAS | CW49: =IFERROR(__xludf.DUMMYFUNCTION("IFERROR(query({$Q$20:$AL$20},""select Col""&MATCH(CZ49,$Q$21:$AL$21,0)))"),"") | DB49: =IFERROR(DG49/$DG$63,"") | DC49: =IFERROR(DB49/SUM($DB$44:$DB$53),"") | DD49: {=IF(NOT($AV$8),"",IF(CZ49="","",VLOOKUP(CZ49,config.carteiras!$C$9:$D$23,2,FALSE)))} | DE49: =IF($CZ49="","",DF49-DK49-DJ49) | DF49: {=IF($CZ49="","",VLOOKUP($CZ49,carteiras..!$B$2:$I$16,2,FALSE))} | DG49: {=IF($CZ49="","",VLOOKUP($CZ49,carteiras..!$B$2:$I$16,3,FALSE))} | DH49: {=IF($CZ49="","",VLOOKUP($CZ49,carteiras..!$B$2:$I$16,4,FALSE))} | DI49: =IF($CZ49="","",IFERROR(DH49/DF49,0)) | DJ49: {=IF($CZ49="","",VLOOKUP($CZ49,carteiras..!$B$2:$I$16,5,FALSE))} | DK49: {=IF($CZ49="","",VLOOKUP($CZ49,carteiras..!$B$2:$I$16,6,FALSE))} | DL49: =IF(ConfigOn,DG49-DF49,0) -> 0 | DM49: =IF($CZ49="","",SUM(DJ49:DL49)) | DN49: {=IF($CZ49="","",VLOOKUP($CZ49,carteiras..!$B$2:$I$16,7,FALSE))} | DO49: {=IF($CZ49="","",VLOOKUP($CZ49,carteiras..!$B$2:$I$16,8,FALSE))} | DP49: 2
B50: =IFERROR(__xludf.DUMMYFUNCTION("IF(B$43="""","""",IF($AZ50="""","""",IFERROR(Query({CarteirasAtivos},""Select Col3 where Col1 = '""&$AZ50&""'and Col2 = '""&S$21&""'""))))"),"") | C50: =IFERROR(__xludf.DUMMYFUNCTION("IF(C$43="""","""",IF($AZ50="""","""",IFERROR(Query({CarteirasAtivos},""Select Col3 where Col1 = '""&$AZ50&""'and Col2 = '""&T$21&""'""))))"),"") | D50: =IFERROR(__xludf.DUMMYFUNCTION("IF(D$43="""","""",IF($AZ50="""","""",IFERROR(Query({CarteirasAtivos},""Select Col3 where Col1 = '""&$AZ50&""'and Col2 = '""&U$21&""'""))))"),"") | E50: =IFERROR(__xludf.DUMMYFUNCTION("IF(E$43="""","""",IF($AZ50="""","""",IFERROR(Query({CarteirasAtivos},""Select Col3 where Col1 = '""&$AZ50&""'and Col2 = '""&V$21&""'""))))"),"") | F50: =IFERROR(__xludf.DUMMYFUNCTION("IF(F$43="""","""",IF($AZ50="""","""",IFERROR(Query({CarteirasAtivos},""Select Col3 where Col1 = '""&$AZ50&""'and Col2 = '""&W$21&""'""))))"),"") | G50: =IFERROR(__xludf.DUMMYFUNCTION("IF(G$43="""","""",IF($AZ50="""","""",IFERROR(Query({CarteirasAtivos},""Select Col3 where Col1 = '""&$AZ50&""'and Col2 = '""&X$21&""'""))))"),"") | H50: =IFERROR(__xludf.DUMMYFUNCTION("IF(H$43="""","""",IF($AZ50="""","""",IFERROR(Query({CarteirasAtivos},""Select Col3 where Col1 = '""&$AZ50&""'and Col2 = '""&Y$21&""'""))))"),"") | I50: =IFERROR(__xludf.DUMMYFUNCTION("IF(I$43="""","""",IF($AZ50="""","""",IFERROR(Query({CarteirasAtivos},""Select Col3 where Col1 = '""&$AZ50&""'and Col2 = '""&Z$21&""'""))))"),"") | J50: =IFERROR(__xludf.DUMMYFUNCTION("IF(J$43="""","""",IF($AZ50="""","""",IFERROR(Query({CarteirasAtivos},""Select Col3 where Col1 = '""&$AZ50&""'and Col2 = '""&AA$21&""'""))))"),"") | K50: =IFERROR(__xludf.DUMMYFUNCTION("IF(K$43="""","""",IF($AZ50="""","""",IFERROR(Query({CarteirasAtivos},""Select Col3 where Col1 = '""&$AZ50&""'and Col2 = '""&AB$21&""'""))))"),"") | L50: 7 | W50: =IFERROR(__xludf.DUMMYFUNCTION("IF(M50="""","""",sparkline(IFERROR(BF50*100/MAX($BF$44:$BF$153),0),{""charttype"",""bar"";""max"",100;""color1"",IF(BD50>=0,""#4760a5"",""red"")}))"),"") | AG50: =IFERROR(__xludf.DUMMYFUNCTION("IF($M50="""","""",IFERROR(sparkline(query(GOOGLEFINANCE($AZ50,""price"",TODAY()-$AF$43,TODAY(),1),""select Col2 label Col2 ''""),IF($AG$43=""Gráfico de barras"",{""charttype"",""column"";""highcolor"",""red""},{""chartype"",""line""}))))"),"") | AJ50: TRUE | AL50: TRUE | AN50: LUCRO POR SETOR | AU50: 7 | AV50: PROVENTOS % | AW50: provento_pct | AX50: ="order by Col"&MATCH(AW50,portfolio.!$A$3:$BO$3,0)&" "&IFERROR(VLOOKUP($M$41,$AV$57:$AX$58,3, FALSE),"") -> order by Col62 asc | AY50: 7 | BG50: 7 | BO50: 7 | BV50: =IF(AND(BT50="",BU50=""),0,IF(BT50="",BU50,BT50)) -> 0 | BW50: =IF(BV50=0,"",BV50) | BX50: 7 | BZ50: 0 | CA50: 0 | CR50: ="LUCRO POR "&UPPER(AD41) -> LUCRO POR SETOR | CS50: select Col11, sum(Col14) where Col11 is not null and Col14<>0 group by Col11 label sum(Col14) '' | CU50: 7 | CV50: CARTEIRAS | CW50: =IFERROR(__xludf.DUMMYFUNCTION("IFERROR(query({$Q$20:$AL$20},""select Col""&MATCH(CZ50,$Q$21:$AL$21,0)))"),"") | DB50: =IFERROR(DG50/$DG$63,"") | DC50: =IFERROR(DB50/SUM($DB$44:$DB$53),"") | DD50: {=IF(NOT($AV$8),"",IF(CZ50="","",VLOOKUP(CZ50,config.carteiras!$C$9:$D$23,2,FALSE)))} | DE50: =IF($CZ50="","",DF50-DK50-DJ50) | DF50: {=IF($CZ50="","",VLOOKUP($CZ50,carteiras..!$B$2:$I$16,2,FALSE))} | DG50: {=IF($CZ50="","",VLOOKUP($CZ50,carteiras..!$B$2:$I$16,3,FALSE))} | DH50: {=IF($CZ50="","",VLOOKUP($CZ50,carteiras..!$B$2:$I$16,4,FALSE))} | DI50: =IF($CZ50="","",IFERROR(DH50/DF50,0)) | DJ50: {=IF($CZ50="","",VLOOKUP($CZ50,carteiras..!$B$2:$I$16,5,FALSE))} | DK50: {=IF($CZ50="","",VLOOKUP($CZ50,carteiras..!$B$2:$I$16,6,FALSE))} | DL50: =IF(ConfigOn,DG50-DF50,0) -> 0 | DM50: =IF($CZ50="","",SUM(DJ50:DL50)) | DN50: {=IF($CZ50="","",VLOOKUP($CZ50,carteiras..!$B$2:$I$16,7,FALSE))} | DO50: {=IF($CZ50="","",VLOOKUP($CZ50,carteiras..!$B$2:$I$16,8,FALSE))} | DP50: 2
B51: =IFERROR(__xludf.DUMMYFUNCTION("IF(B$43="""","""",IF($AZ51="""","""",IFERROR(Query({CarteirasAtivos},""Select Col3 where Col1 = '""&$AZ51&""'and Col2 = '""&S$21&""'""))))"),"") | C51: =IFERROR(__xludf.DUMMYFUNCTION("IF(C$43="""","""",IF($AZ51="""","""",IFERROR(Query({CarteirasAtivos},""Select Col3 where Col1 = '""&$AZ51&""'and Col2 = '""&T$21&""'""))))"),"") | D51: =IFERROR(__xludf.DUMMYFUNCTION("IF(D$43="""","""",IF($AZ51="""","""",IFERROR(Query({CarteirasAtivos},""Select Col3 where Col1 = '""&$AZ51&""'and Col2 = '""&U$21&""'""))))"),"") | E51: =IFERROR(__xludf.DUMMYFUNCTION("IF(E$43="""","""",IF($AZ51="""","""",IFERROR(Query({CarteirasAtivos},""Select Col3 where Col1 = '""&$AZ51&""'and Col2 = '""&V$21&""'""))))"),"") | F51: =IFERROR(__xludf.DUMMYFUNCTION("IF(F$43="""","""",IF($AZ51="""","""",IFERROR(Query({CarteirasAtivos},""Select Col3 where Col1 = '""&$AZ51&""'and Col2 = '""&W$21&""'""))))"),"") | G51: =IFERROR(__xludf.DUMMYFUNCTION("IF(G$43="""","""",IF($AZ51="""","""",IFERROR(Query({CarteirasAtivos},""Select Col3 where Col1 = '""&$AZ51&""'and Col2 = '""&X$21&""'""))))"),"") | H51: =IFERROR(__xludf.DUMMYFUNCTION("IF(H$43="""","""",IF($AZ51="""","""",IFERROR(Query({CarteirasAtivos},""Select Col3 where Col1 = '""&$AZ51&""'and Col2 = '""&Y$21&""'""))))"),"") | I51: =IFERROR(__xludf.DUMMYFUNCTION("IF(I$43="""","""",IF($AZ51="""","""",IFERROR(Query({CarteirasAtivos},""Select Col3 where Col1 = '""&$AZ51&""'and Col2 = '""&Z$21&""'""))))"),"") | J51: =IFERROR(__xludf.DUMMYFUNCTION("IF(J$43="""","""",IF($AZ51="""","""",IFERROR(Query({CarteirasAtivos},""Select Col3 where Col1 = '""&$AZ51&""'and Col2 = '""&AA$21&""'""))))"),"") | K51: =IFERROR(__xludf.DUMMYFUNCTION("IF(K$43="""","""",IF($AZ51="""","""",IFERROR(Query({CarteirasAtivos},""Select Col3 where Col1 = '""&$AZ51&""'and Col2 = '""&AB$21&""'""))))"),"") | L51: 8 | W51: =IFERROR(__xludf.DUMMYFUNCTION("IF(M51="""","""",sparkline(IFERROR(BF51*100/MAX($BF$44:$BF$153),0),{""charttype"",""bar"";""max"",100;""color1"",IF(BD51>=0,""#4760a5"",""red"")}))"),"") | AG51: =IFERROR(__xludf.DUMMYFUNCTION("IF($M51="""","""",IFERROR(sparkline(query(GOOGLEFINANCE($AZ51,""price"",TODAY()-$AF$43,TODAY(),1),""select Col2 label Col2 ''""),IF($AG$43=""Gráfico de barras"",{""charttype"",""column"";""highcolor"",""red""},{""chartype"",""line""}))))"),"") | AJ51: TRUE | AL51: TRUE | AU51: 8 | AV51: ANUAL % | AW51: tir | AX51: ="order by Col"&MATCH(AW51,portfolio.!$A$3:$BO$3,0)&" "&IFERROR(VLOOKUP($M$41,$AV$57:$AX$58,3, FALSE),"") -> order by Col37 asc | AY51: 8 | BG51: 8 | BO51: 8 | BV51: =IF(AND(BT51="",BU51=""),0,IF(BT51="",BU51,BT51)) -> 0 | BW51: =IF(BV51=0,"",BV51) | BX51: 8 | BZ51: 0 | CA51: 0 | CR51: LUCRO POR CLASSE | CS51: select Col12, sum(Col14) where Col12 is not null and Col14<>0 group by Col12 label sum(Col14) '' | CU51: 8 | CV51: CARTEIRAS | CW51: =IFERROR(__xludf.DUMMYFUNCTION("IFERROR(query({$Q$20:$AL$20},""select Col""&MATCH(CZ51,$Q$21:$AL$21,0)))"),"") | DB51: =IFERROR(DG51/$DG$63,"") | DC51: =IFERROR(DB51/SUM($DB$44:$DB$53),"") | DD51: {=IF(NOT($AV$8),"",IF(CZ51="","",VLOOKUP(CZ51,config.carteiras!$C$9:$D$23,2,FALSE)))} | DE51: =IF($CZ51="","",DF51-DK51-DJ51) | DF51: {=IF($CZ51="","",VLOOKUP($CZ51,carteiras..!$B$2:$I$16,2,FALSE))} | DG51: {=IF($CZ51="","",VLOOKUP($CZ51,carteiras..!$B$2:$I$16,3,FALSE))} | DH51: {=IF($CZ51="","",VLOOKUP($CZ51,carteiras..!$B$2:$I$16,4,FALSE))} | DI51: =IF($CZ51="","",IFERROR(DH51/DF51,0)) | DJ51: {=IF($CZ51="","",VLOOKUP($CZ51,carteiras..!$B$2:$I$16,5,FALSE))} | DK51: {=IF($CZ51="","",VLOOKUP($CZ51,carteiras..!$B$2:$I$16,6,FALSE))} | DL51: =IF(ConfigOn,DG51-DF51,0) -> 0 | DM51: =IF($CZ51="","",SUM(DJ51:DL51)) | DN51: {=IF($CZ51="","",VLOOKUP($CZ51,carteiras..!$B$2:$I$16,7,FALSE))} | DO51: {=IF($CZ51="","",VLOOKUP($CZ51,carteiras..!$B$2:$I$16,8,FALSE))} | DP51: 2
B52: =IFERROR(__xludf.DUMMYFUNCTION("IF(B$43="""","""",IF($AZ52="""","""",IFERROR(Query({CarteirasAtivos},""Select Col3 where Col1 = '""&$AZ52&""'and Col2 = '""&S$21&""'""))))"),"") | C52: =IFERROR(__xludf.DUMMYFUNCTION("IF(C$43="""","""",IF($AZ52="""","""",IFERROR(Query({CarteirasAtivos},""Select Col3 where Col1 = '""&$AZ52&""'and Col2 = '""&T$21&""'""))))"),"") | D52: =IFERROR(__xludf.DUMMYFUNCTION("IF(D$43="""","""",IF($AZ52="""","""",IFERROR(Query({CarteirasAtivos},""Select Col3 where Col1 = '""&$AZ52&""'and Col2 = '""&U$21&""'""))))"),"") | E52: =IFERROR(__xludf.DUMMYFUNCTION("IF(E$43="""","""",IF($AZ52="""","""",IFERROR(Query({CarteirasAtivos},""Select Col3 where Col1 = '""&$AZ52&""'and Col2 = '""&V$21&""'""))))"),"") | F52: =IFERROR(__xludf.DUMMYFUNCTION("IF(F$43="""","""",IF($AZ52="""","""",IFERROR(Query({CarteirasAtivos},""Select Col3 where Col1 = '""&$AZ52&""'and Col2 = '""&W$21&""'""))))"),"") | G52: =IFERROR(__xludf.DUMMYFUNCTION("IF(G$43="""","""",IF($AZ52="""","""",IFERROR(Query({CarteirasAtivos},""Select Col3 where Col1 = '""&$AZ52&""'and Col2 = '""&X$21&""'""))))"),"") | H52: =IFERROR(__xludf.DUMMYFUNCTION("IF(H$43="""","""",IF($AZ52="""","""",IFERROR(Query({CarteirasAtivos},""Select Col3 where Col1 = '""&$AZ52&""'and Col2 = '""&Y$21&""'""))))"),"") | I52: =IFERROR(__xludf.DUMMYFUNCTION("IF(I$43="""","""",IF($AZ52="""","""",IFERROR(Query({CarteirasAtivos},""Select Col3 where Col1 = '""&$AZ52&""'and Col2 = '""&Z$21&""'""))))"),"") | J52: =IFERROR(__xludf.DUMMYFUNCTION("IF(J$43="""","""",IF($AZ52="""","""",IFERROR(Query({CarteirasAtivos},""Select Col3 where Col1 = '""&$AZ52&""'and Col2 = '""&AA$21&""'""))))"),"") | K52: =IFERROR(__xludf.DUMMYFUNCTION("IF(K$43="""","""",IF($AZ52="""","""",IFERROR(Query({CarteirasAtivos},""Select Col3 where Col1 = '""&$AZ52&""'and Col2 = '""&AB$21&""'""))))"),"") | L52: 9 | W52: =IFERROR(__xludf.DUMMYFUNCTION("IF(M52="""","""",sparkline(IFERROR(BF52*100/MAX($BF$44:$BF$153),0),{""charttype"",""bar"";""max"",100;""color1"",IF(BD52>=0,""#4760a5"",""red"")}))"),"") | AG52: =IFERROR(__xludf.DUMMYFUNCTION("IF($M52="""","""",IFERROR(sparkline(query(GOOGLEFINANCE($AZ52,""price"",TODAY()-$AF$43,TODAY(),1),""select Col2 label Col2 ''""),IF($AG$43=""Gráfico de barras"",{""charttype"",""column"";""highcolor"",""red""},{""chartype"",""line""}))))"),"") | AJ52: TRUE | AL52: TRUE | AU52: 9 | AV52: VALOR INVESTIDO | AW52: vlr_investido | AX52: ="order by Col"&MATCH(AW52,portfolio.!$A$3:$BO$3,0)&" "&IFERROR(VLOOKUP($M$41,$AV$57:$AX$58,3, FALSE),"") -> order by Col15 asc | AY52: 9 | BG52: 9 | BO52: 9 | BV52: =IF(AND(BT52="",BU52=""),0,IF(BT52="",BU52,BT52)) -> 0 | BW52: =IF(BV52=0,"",BV52) | BX52: 9 | BZ52: 0 | CA52: 0 | CR52: =if(AV7,"LUCRO POR BOOK","") | CS52: select Col7, Col9 where Col9<>0 and Col7 is not null | CU52: 9 | CV52: CARTEIRAS | CW52: =IFERROR(__xludf.DUMMYFUNCTION("IFERROR(query({$Q$20:$AL$20},""select Col""&MATCH(CZ52,$Q$21:$AL$21,0)))"),"") | DB52: =IFERROR(DG52/$DG$63,"") | DC52: =IFERROR(DB52/SUM($DB$44:$DB$53),"") | DD52: {=IF(NOT($AV$8),"",IF(CZ52="","",VLOOKUP(CZ52,config.carteiras!$C$9:$D$23,2,FALSE)))} | DE52: =IF($CZ52="","",DF52-DK52-DJ52) | DF52: {=IF($CZ52="","",VLOOKUP($CZ52,carteiras..!$B$2:$I$16,2,FALSE))} | DG52: {=IF($CZ52="","",VLOOKUP($CZ52,carteiras..!$B$2:$I$16,3,FALSE))} | DH52: {=IF($CZ52="","",VLOOKUP($CZ52,carteiras..!$B$2:$I$16,4,FALSE))} | DI52: =IF($CZ52="","",IFERROR(DH52/DF52,0)) | DJ52: {=IF($CZ52="","",VLOOKUP($CZ52,carteiras..!$B$2:$I$16,5,FALSE))} | DK52: {=IF($CZ52="","",VLOOKUP($CZ52,carteiras..!$B$2:$I$16,6,FALSE))} | DL52: =IF(ConfigOn,DG52-DF52,0) -> 0 | DM52: =IF($CZ52="","",SUM(DJ52:DL52)) | DN52: {=IF($CZ52="","",VLOOKUP($CZ52,carteiras..!$B$2:$I$16,7,FALSE))} | DO52: {=IF($CZ52="","",VLOOKUP($CZ52,carteiras..!$B$2:$I$16,8,FALSE))} | DP52: 2
B53: =IFERROR(__xludf.DUMMYFUNCTION("IF(B$43="""","""",IF($AZ53="""","""",IFERROR(Query({CarteirasAtivos},""Select Col3 where Col1 = '""&$AZ53&""'and Col2 = '""&S$21&""'""))))"),"") | C53: =IFERROR(__xludf.DUMMYFUNCTION("IF(C$43="""","""",IF($AZ53="""","""",IFERROR(Query({CarteirasAtivos},""Select Col3 where Col1 = '""&$AZ53&""'and Col2 = '""&T$21&""'""))))"),"") | D53: =IFERROR(__xludf.DUMMYFUNCTION("IF(D$43="""","""",IF($AZ53="""","""",IFERROR(Query({CarteirasAtivos},""Select Col3 where Col1 = '""&$AZ53&""'and Col2 = '""&U$21&""'""))))"),"") | E53: =IFERROR(__xludf.DUMMYFUNCTION("IF(E$43="""","""",IF($AZ53="""","""",IFERROR(Query({CarteirasAtivos},""Select Col3 where Col1 = '""&$AZ53&""'and Col2 = '""&V$21&""'""))))"),"") | F53: =IFERROR(__xludf.DUMMYFUNCTION("IF(F$43="""","""",IF($AZ53="""","""",IFERROR(Query({CarteirasAtivos},""Select Col3 where Col1 = '""&$AZ53&""'and Col2 = '""&W$21&""'""))))"),"") | G53: =IFERROR(__xludf.DUMMYFUNCTION("IF(G$43="""","""",IF($AZ53="""","""",IFERROR(Query({CarteirasAtivos},""Select Col3 where Col1 = '""&$AZ53&""'and Col2 = '""&X$21&""'""))))"),"") | H53: =IFERROR(__xludf.DUMMYFUNCTION("IF(H$43="""","""",IF($AZ53="""","""",IFERROR(Query({CarteirasAtivos},""Select Col3 where Col1 = '""&$AZ53&""'and Col2 = '""&Y$21&""'""))))"),"") | I53: =IFERROR(__xludf.DUMMYFUNCTION("IF(I$43="""","""",IF($AZ53="""","""",IFERROR(Query({CarteirasAtivos},""Select Col3 where Col1 = '""&$AZ53&""'and Col2 = '""&Z$21&""'""))))"),"") | J53: =IFERROR(__xludf.DUMMYFUNCTION("IF(J$43="""","""",IF($AZ53="""","""",IFERROR(Query({CarteirasAtivos},""Select Col3 where Col1 = '""&$AZ53&""'and Col2 = '""&AA$21&""'""))))"),"") | K53: =IFERROR(__xludf.DUMMYFUNCTION("IF(K$43="""","""",IF($AZ53="""","""",IFERROR(Query({CarteirasAtivos},""Select Col3 where Col1 = '""&$AZ53&""'and Col2 = '""&AB$21&""'""))))"),"") | L53: 10 | W53: =IFERROR(__xludf.DUMMYFUNCTION("IF(M53="""","""",sparkline(IFERROR(BF53*100/MAX($BF$44:$BF$153),0),{""charttype"",""bar"";""max"",100;""color1"",IF(BD53>=0,""#4760a5"",""red"")}))"),"") | AG53: =IFERROR(__xludf.DUMMYFUNCTION("IF($M53="""","""",IFERROR(sparkline(query(GOOGLEFINANCE($AZ53,""price"",TODAY()-$AF$43,TODAY(),1),""select Col2 label Col2 ''""),IF($AG$43=""Gráfico de barras"",{""charttype"",""column"";""highcolor"",""red""},{""chartype"",""line""}))))"),"") | AJ53: TRUE | AL53: TRUE | AU53: 10 | AV53: VALOR MERCADO | AW53: vlr_mercado | AX53: ="order by Col"&MATCH(AW53,portfolio.!$A$3:$BO$3,0)&" "&IFERROR(VLOOKUP($M$41,$AV$57:$AX$58,3, FALSE),"") -> order by Col40 asc | AY53: 10 | BG53: 10 | BO53: 10 | BV53: =IF(AND(BT53="",BU53=""),0,IF(BT53="",BU53,BT53)) -> 0 | BW53: =IF(BV53=0,"",BV53) | BX53: 10 | BZ53: 0 | CA53: 0 | CR53: =IF(AV8,"LUCRO POR CARTEIRA","") | CS53: select Col4, Col6 where Col6<>0 and Col4 is not null | CU53: 10 | CV53: CARTEIRAS | CW53: =IFERROR(__xludf.DUMMYFUNCTION("IFERROR(query({$Q$20:$AL$20},""select Col""&MATCH(CZ53,$Q$21:$AL$21,0)))"),"") | DB53: =IFERROR(DG53/$DG$63,"") | DC53: =IFERROR(DB53/SUM($DB$44:$DB$53),"") | DD53: {=IF(NOT($AV$8),"",IF(CZ53="","",VLOOKUP(CZ53,config.carteiras!$C$9:$D$23,2,FALSE)))} | DE53: =IF($CZ53="","",DF53-DK53-DJ53) | DF53: {=IF($CZ53="","",VLOOKUP($CZ53,carteiras..!$B$2:$I$16,2,FALSE))} | DG53: {=IF($CZ53="","",VLOOKUP($CZ53,carteiras..!$B$2:$I$16,3,FALSE))} | DH53: {=IF($CZ53="","",VLOOKUP($CZ53,carteiras..!$B$2:$I$16,4,FALSE))} | DI53: =IF($CZ53="","",IFERROR(DH53/DF53,0)) | DJ53: {=IF($CZ53="","",VLOOKUP($CZ53,carteiras..!$B$2:$I$16,5,FALSE))} | DK53: {=IF($CZ53="","",VLOOKUP($CZ53,carteiras..!$B$2:$I$16,6,FALSE))} | DL53: =IF(ConfigOn,DG53-DF53,0) -> 0 | DM53: =IF($CZ53="","",SUM(DJ53:DL53)) | DN53: {=IF($CZ53="","",VLOOKUP($CZ53,carteiras..!$B$2:$I$16,7,FALSE))} | DO53: {=IF($CZ53="","",VLOOKUP($CZ53,carteiras..!$B$2:$I$16,8,FALSE))} | DP53: 2
B54: =IFERROR(__xludf.DUMMYFUNCTION("IF(B$43="""","""",IF($AZ54="""","""",IFERROR(Query({CarteirasAtivos},""Select Col3 where Col1 = '""&$AZ54&""'and Col2 = '""&S$21&""'""))))"),"") | C54: =IFERROR(__xludf.DUMMYFUNCTION("IF(C$43="""","""",IF($AZ54="""","""",IFERROR(Query({CarteirasAtivos},""Select Col3 where Col1 = '""&$AZ54&""'and Col2 = '""&T$21&""'""))))"),"") | D54: =IFERROR(__xludf.DUMMYFUNCTION("IF(D$43="""","""",IF($AZ54="""","""",IFERROR(Query({CarteirasAtivos},""Select Col3 where Col1 = '""&$AZ54&""'and Col2 = '""&U$21&""'""))))"),"") | E54: =IFERROR(__xludf.DUMMYFUNCTION("IF(E$43="""","""",IF($AZ54="""","""",IFERROR(Query({CarteirasAtivos},""Select Col3 where Col1 = '""&$AZ54&""'and Col2 = '""&V$21&""'""))))"),"") | F54: =IFERROR(__xludf.DUMMYFUNCTION("IF(F$43="""","""",IF($AZ54="""","""",IFERROR(Query({CarteirasAtivos},""Select Col3 where Col1 = '""&$AZ54&""'and Col2 = '""&W$21&""'""))))"),"") | G54: =IFERROR(__xludf.DUMMYFUNCTION("IF(G$43="""","""",IF($AZ54="""","""",IFERROR(Query({CarteirasAtivos},""Select Col3 where Col1 = '""&$AZ54&""'and Col2 = '""&X$21&""'""))))"),"") | H54: =IFERROR(__xludf.DUMMYFUNCTION("IF(H$43="""","""",IF($AZ54="""","""",IFERROR(Query({CarteirasAtivos},""Select Col3 where Col1 = '""&$AZ54&""'and Col2 = '""&Y$21&""'""))))"),"") | I54: =IFERROR(__xludf.DUMMYFUNCTION("IF(I$43="""","""",IF($AZ54="""","""",IFERROR(Query({CarteirasAtivos},""Select Col3 where Col1 = '""&$AZ54&""'and Col2 = '""&Z$21&""'""))))"),"") | J54: =IFERROR(__xludf.DUMMYFUNCTION("IF(J$43="""","""",IF($AZ54="""","""",IFERROR(Query({CarteirasAtivos},""Select Col3 where Col1 = '""&$AZ54&""'and Col2 = '""&AA$21&""'""))))"),"") | K54: =IFERROR(__xludf.DUMMYFUNCTION("IF(K$43="""","""",IF($AZ54="""","""",IFERROR(Query({CarteirasAtivos},""Select Col3 where Col1 = '""&$AZ54&""'and Col2 = '""&AB$21&""'""))))"),"") | L54: 11 | W54: =IFERROR(__xludf.DUMMYFUNCTION("IF(M54="""","""",sparkline(IFERROR(BF54*100/MAX($BF$44:$BF$153),0),{""charttype"",""bar"";""max"",100;""color1"",IF(BD54>=0,""#4760a5"",""red"")}))"),"") | AG54: =IFERROR(__xludf.DUMMYFUNCTION("IF($M54="""","""",IFERROR(sparkline(query(GOOGLEFINANCE($AZ54,""price"",TODAY()-$AF$43,TODAY(),1),""select Col2 label Col2 ''""),IF($AG$43=""Gráfico de barras"",{""charttype"",""column"";""highcolor"",""red""},{""chartype"",""line""}))))"),"") | AJ54: TRUE | AL54: TRUE | AU54: 11 | AV54: PREÇO TETO % | AW54: upside | AX54: ="order by Col"&MATCH(AW54,portfolio.!$A$3:$BO$3,0)&" "&IFERROR(VLOOKUP($M$41,$AV$57:$AX$58,3, FALSE),"") -> order by Col57 asc | AY54: 11 | BG54: 11 | BO54: 1 | BP54: =IFERROR(__xludf.DUMMYFUNCTION("IF(NOT(ConfigOn),query({BP65:BQ74},""select Col1 where Col2 <= 0 ORDER BY Col2 DESC"",0),IFERROR(query({AtivosDados},CONCAT(""select Col""&MATCH(""ativo"",portfolio.!$A$3:DQ$3,0)&"" where Col""&MATCH(""classe"",portfolio.!$A$3:DQ$3,0)&""='""&$BT$41&""' AN"&"D Col""&MATCH(""lucro_dia"",portfolio.!$A$3:DQ$3,0)&""<0 ORDER BY Col""&MATCH(""lucro_dia"",portfolio.!$A$3:DQ$3,0)&"" desc limit 10 OFFSET "",BQ42-BR42),0)))"),"") | BR54: =IFERROR(__xludf.DUMMYFUNCTION("IF(NOT(ConfigOn),query({BP65:BQ74},""select Col2 where Col2 <= 0 ORDER BY Col2 DESC"",0),IFERROR(query({AtivosDados},CONCAT(""select Col""&MATCH(""lucro_dia"",portfolio.!$A$3:DQ$3,0)&"" where Col""&MATCH(""classe"",portfolio.!$A$3:DQ$3,0)&""='""&BT41&""' "&"AND Col""&MATCH(""lucro_dia"",portfolio.!$A$3:DQ$3,0)&""<0 ORDER BY Col""&MATCH(""lucro_dia"",portfolio.!$A$3:DQ$3,0)&"" DESC limit 10 OFFSET "",BQ42-BR42),0)))"),"") | BX54: 11 | BZ54: 0 | CA54: 0 | CB54: - | CC54: 0 | CD54: 0 | CE54: Sem Book | CF54: 0 | CG54: 0 | CR54: =IF(AV8,"LUCRO POR PERFIL DE CARTEIRA","") | CS54: select Col1, Col3 where Col3<>0 and Col1 is not null | CV54: GRUPO | CW54: CHECK | CX54: CATEGORIA SUBTOTAL | CY54: PERFIL CRIADAS | CZ54: CARTEIRA | DB54: PESO % | DC54: PESO GRUPO % | DE54: Valor Aportado | DF54: vlr_investido | DG54: vlr_mercado | DH54: lucro_dia | DI54: Lucro dia % | DJ54: Valor Proventos | DK54: Valor Trades | DL54: Lucro Aberto | DM54: Lucro Total | DN54: TIR am | DO54: TIR aa | DP54: ORDER
B55: =IFERROR(__xludf.DUMMYFUNCTION("IF(B$43="""","""",IF($AZ55="""","""",IFERROR(Query({CarteirasAtivos},""Select Col3 where Col1 = '""&$AZ55&""'and Col2 = '""&S$21&""'""))))"),"") | C55: =IFERROR(__xludf.DUMMYFUNCTION("IF(C$43="""","""",IF($AZ55="""","""",IFERROR(Query({CarteirasAtivos},""Select Col3 where Col1 = '""&$AZ55&""'and Col2 = '""&T$21&""'""))))"),"") | D55: =IFERROR(__xludf.DUMMYFUNCTION("IF(D$43="""","""",IF($AZ55="""","""",IFERROR(Query({CarteirasAtivos},""Select Col3 where Col1 = '""&$AZ55&""'and Col2 = '""&U$21&""'""))))"),"") | E55: =IFERROR(__xludf.DUMMYFUNCTION("IF(E$43="""","""",IF($AZ55="""","""",IFERROR(Query({CarteirasAtivos},""Select Col3 where Col1 = '""&$AZ55&""'and Col2 = '""&V$21&""'""))))"),"") | F55: =IFERROR(__xludf.DUMMYFUNCTION("IF(F$43="""","""",IF($AZ55="""","""",IFERROR(Query({CarteirasAtivos},""Select Col3 where Col1 = '""&$AZ55&""'and Col2 = '""&W$21&""'""))))"),"") | G55: =IFERROR(__xludf.DUMMYFUNCTION("IF(G$43="""","""",IF($AZ55="""","""",IFERROR(Query({CarteirasAtivos},""Select Col3 where Col1 = '""&$AZ55&""'and Col2 = '""&X$21&""'""))))"),"") | H55: =IFERROR(__xludf.DUMMYFUNCTION("IF(H$43="""","""",IF($AZ55="""","""",IFERROR(Query({CarteirasAtivos},""Select Col3 where Col1 = '""&$AZ55&""'and Col2 = '""&Y$21&""'""))))"),"") | I55: =IFERROR(__xludf.DUMMYFUNCTION("IF(I$43="""","""",IF($AZ55="""","""",IFERROR(Query({CarteirasAtivos},""Select Col3 where Col1 = '""&$AZ55&""'and Col2 = '""&Z$21&""'""))))"),"") | J55: =IFERROR(__xludf.DUMMYFUNCTION("IF(J$43="""","""",IF($AZ55="""","""",IFERROR(Query({CarteirasAtivos},""Select Col3 where Col1 = '""&$AZ55&""'and Col2 = '""&AA$21&""'""))))"),"") | K55: =IFERROR(__xludf.DUMMYFUNCTION("IF(K$43="""","""",IF($AZ55="""","""",IFERROR(Query({CarteirasAtivos},""Select Col3 where Col1 = '""&$AZ55&""'and Col2 = '""&AB$21&""'""))))"),"") | L55: 12 | W55: =IFERROR(__xludf.DUMMYFUNCTION("IF(M55="""","""",sparkline(IFERROR(BF55*100/MAX($BF$44:$BF$153),0),{""charttype"",""bar"";""max"",100;""color1"",IF(BD55>=0,""#4760a5"",""red"")}))"),"") | AG55: =IFERROR(__xludf.DUMMYFUNCTION("IF($M55="""","""",IFERROR(sparkline(query(GOOGLEFINANCE($AZ55,""price"",TODAY()-$AF$43,TODAY(),1),""select Col2 label Col2 ''""),IF($AG$43=""Gráfico de barras"",{""charttype"",""column"";""highcolor"",""red""},{""chartype"",""line""}))))"),"") | AJ55: TRUE | AL55: TRUE | AU55: 12 | AV55: ALFABETICA | AW55: ativo | AX55: ="order by Col"&MATCH("classe",portfolio.!$A$3:$BO$3,0)&", Col"&MATCH(AW55,portfolio.!$A$3:$BO$3,0)&" "&IFERROR(VLOOKUP($M$41,$AV$57:$AX$58,3, FALSE),"") -> order by Col4, Col1 asc | AY55: 12 | BG55: 12 | BO55: 2 | BX55: 12 | BZ55: 0 | CA55: 0 | CB55: - | CC55: 0 | CD55: 0 | CU55: 11 | CV55: OUTROS | CW55: =IFERROR(__xludf.DUMMYFUNCTION("IFERROR(query({$Q$20:$AL$20},""select Col""&MATCH(CZ55,$Q$21:$AL$21,0)),FALSE)"),FALSE) -> FALSE | CX55: FUNDO_RF_1 | CY55: Outros | CZ55: =IF(AV8,IF(DF55<>0,UPPER('config.parâmetros'!H5),"-"),"-") -> - | DB55: =IFERROR(DG55/$DG$63,"") | DC55: =IFERROR(DB55/SUM($DB$55:$DB$58),"") | DE55: =DF55-DJ55-DK55 -> 0 | DF55: =IF(ConfigOn,IFERROR(IFERROR(SUMIFS(portfolio.!$O$4:$O$303,portfolio.!$U$4:$U$303,CX55),0),0)) -> 0 | DG55: =IF(ConfigOn,IFERROR(IFERROR(SUMIFS(portfolio.!$AN$4:$AN$303,portfolio.!$U$4:$U$303,CX55),0),0)) -> 0 | DH55: =IF(ConfigOn,IFERROR(IFERROR(SUMIFS(portfolio.!$AO$4:$AO$303,portfolio.!$U$4:$U$303,CX55),0),0)) -> 0 | DI55: =IFERROR(DH55/DF55,0) -> 0 | DJ55: =IF(ConfigOn,IFERROR(IFERROR(SUMIFS(proventos!$Q$4:$Q343,proventos!$S$4:$S343,CX55),0),0)) -> 0 | DK55: =IF(ConfigOn,IFERROR(SUMIFS(op.normal!$P$4:$P343,op.normal!$AD$4:$AD343,CX55),0)) -> 0 | DL55: =IF(ConfigOn,DG55-DF55,0) -> 0 | DM55: =SUM(DJ55:DL55) -> 0 | DN55: =IF(AV8,((1+DO55)^(1/12))-1,"-") -> - | DO55: 0.032616841 | DP55: 4
B56: =IFERROR(__xludf.DUMMYFUNCTION("IF(B$43="""","""",IF($AZ56="""","""",IFERROR(Query({CarteirasAtivos},""Select Col3 where Col1 = '""&$AZ56&""'and Col2 = '""&S$21&""'""))))"),"") | C56: =IFERROR(__xludf.DUMMYFUNCTION("IF(C$43="""","""",IF($AZ56="""","""",IFERROR(Query({CarteirasAtivos},""Select Col3 where Col1 = '""&$AZ56&""'and Col2 = '""&T$21&""'""))))"),"") | D56: =IFERROR(__xludf.DUMMYFUNCTION("IF(D$43="""","""",IF($AZ56="""","""",IFERROR(Query({CarteirasAtivos},""Select Col3 where Col1 = '""&$AZ56&""'and Col2 = '""&U$21&""'""))))"),"") | E56: =IFERROR(__xludf.DUMMYFUNCTION("IF(E$43="""","""",IF($AZ56="""","""",IFERROR(Query({CarteirasAtivos},""Select Col3 where Col1 = '""&$AZ56&""'and Col2 = '""&V$21&""'""))))"),"") | F56: =IFERROR(__xludf.DUMMYFUNCTION("IF(F$43="""","""",IF($AZ56="""","""",IFERROR(Query({CarteirasAtivos},""Select Col3 where Col1 = '""&$AZ56&""'and Col2 = '""&W$21&""'""))))"),"") | G56: =IFERROR(__xludf.DUMMYFUNCTION("IF(G$43="""","""",IF($AZ56="""","""",IFERROR(Query({CarteirasAtivos},""Select Col3 where Col1 = '""&$AZ56&""'and Col2 = '""&X$21&""'""))))"),"") | H56: =IFERROR(__xludf.DUMMYFUNCTION("IF(H$43="""","""",IF($AZ56="""","""",IFERROR(Query({CarteirasAtivos},""Select Col3 where Col1 = '""&$AZ56&""'and Col2 = '""&Y$21&""'""))))"),"") | I56: =IFERROR(__xludf.DUMMYFUNCTION("IF(I$43="""","""",IF($AZ56="""","""",IFERROR(Query({CarteirasAtivos},""Select Col3 where Col1 = '""&$AZ56&""'and Col2 = '""&Z$21&""'""))))"),"") | J56: =IFERROR(__xludf.DUMMYFUNCTION("IF(J$43="""","""",IF($AZ56="""","""",IFERROR(Query({CarteirasAtivos},""Select Col3 where Col1 = '""&$AZ56&""'and Col2 = '""&AA$21&""'""))))"),"") | K56: =IFERROR(__xludf.DUMMYFUNCTION("IF(K$43="""","""",IF($AZ56="""","""",IFERROR(Query({CarteirasAtivos},""Select Col3 where Col1 = '""&$AZ56&""'and Col2 = '""&AB$21&""'""))))"),"") | L56: 13 | W56: =IFERROR(__xludf.DUMMYFUNCTION("IF(M56="""","""",sparkline(IFERROR(BF56*100/MAX($BF$44:$BF$153),0),{""charttype"",""bar"";""max"",100;""color1"",IF(BD56>=0,""#4760a5"",""red"")}))"),"") | AG56: =IFERROR(__xludf.DUMMYFUNCTION("IF($M56="""","""",IFERROR(sparkline(query(GOOGLEFINANCE($AZ56,""price"",TODAY()-$AF$43,TODAY(),1),""select Col2 label Col2 ''""),IF($AG$43=""Gráfico de barras"",{""charttype"",""column"";""highcolor"",""red""},{""chartype"",""line""}))))"),"") | AJ56: TRUE | AL56: TRUE | AU56: 13 | AV56: SETOR | AW56: setor | AX56: ="order by Col"&MATCH(AW56,portfolio.!$A$3:$BO$3,0)&" "&IFERROR(VLOOKUP($M$41,$AV$57:$AX$58,3, FALSE),"") -> order by Col7 asc | AY56: 13 | BG56: 13 | BO56: 3 | BX56: 13 | BZ56: 0 | CA56: 0 | CB56: - | CC56: 0 | CD56: 0 | CU56: 12 | CV56: OUTROS | CW56: =IFERROR(__xludf.DUMMYFUNCTION("IFERROR(query({$Q$20:$AL$20},""select Col""&MATCH(CZ56,$Q$21:$AL$21,0)),FALSE)"),FALSE) -> FALSE | CX56: FUNDO_RF_2 | CY56: Outros | CZ56: =IF(AV8,IF(DF56<>0,UPPER('config.parâmetros'!I5),"-"),"-") -> - | DB56: =IFERROR(DG56/$DG$63,"") | DC56: =IFERROR(DB56/SUM($DB$55:$DB$58),"") | DE56: =DF56-DJ56-DK56 -> 0 | DF56: =IF(ConfigOn,IFERROR(IFERROR(SUMIFS(portfolio.!$O$4:$O$303,portfolio.!$U$4:$U$303,CX56),0),0)) -> 0 | DG56: =IF(ConfigOn,IFERROR(IFERROR(SUMIFS(portfolio.!$AN$4:$AN$303,portfolio.!$U$4:$U$303,CX56),0),0)) -> 0 | DH56: =IF(ConfigOn,IFERROR(IFERROR(SUMIFS(portfolio.!$AO$4:$AO$303,portfolio.!$U$4:$U$303,CX56),0),0)) -> 0 | DI56: =IFERROR(DH56/DF56,0) -> 0 | DJ56: =IF(ConfigOn,IFERROR(IFERROR(SUMIFS(proventos!$Q$4:$Q343,proventos!$S$4:$S343,CX56),0),0)) -> 0 | DK56: =IF(ConfigOn,IFERROR(SUMIFS(op.normal!$P$4:$P343,op.normal!$AD$4:$AD343,CX56),0)) -> 0 | DL56: =IF(ConfigOn,DG56-DF56,0) -> 0 | DM56: =SUM(DJ56:DL56) -> 0 | DN56: =IF(AV8,((1+DO56)^(1/12))-1,"-") -> - | DO56: 0 | DP56: 4
B57: =IFERROR(__xludf.DUMMYFUNCTION("IF(B$43="""","""",IF($AZ57="""","""",IFERROR(Query({CarteirasAtivos},""Select Col3 where Col1 = '""&$AZ57&""'and Col2 = '""&S$21&""'""))))"),"") | C57: =IFERROR(__xludf.DUMMYFUNCTION("IF(C$43="""","""",IF($AZ57="""","""",IFERROR(Query({CarteirasAtivos},""Select Col3 where Col1 = '""&$AZ57&""'and Col2 = '""&T$21&""'""))))"),"") | D57: =IFERROR(__xludf.DUMMYFUNCTION("IF(D$43="""","""",IF($AZ57="""","""",IFERROR(Query({CarteirasAtivos},""Select Col3 where Col1 = '""&$AZ57&""'and Col2 = '""&U$21&""'""))))"),"") | E57: =IFERROR(__xludf.DUMMYFUNCTION("IF(E$43="""","""",IF($AZ57="""","""",IFERROR(Query({CarteirasAtivos},""Select Col3 where Col1 = '""&$AZ57&""'and Col2 = '""&V$21&""'""))))"),"") | F57: =IFERROR(__xludf.DUMMYFUNCTION("IF(F$43="""","""",IF($AZ57="""","""",IFERROR(Query({CarteirasAtivos},""Select Col3 where Col1 = '""&$AZ57&""'and Col2 = '""&W$21&""'""))))"),"") | G57: =IFERROR(__xludf.DUMMYFUNCTION("IF(G$43="""","""",IF($AZ57="""","""",IFERROR(Query({CarteirasAtivos},""Select Col3 where Col1 = '""&$AZ57&""'and Col2 = '""&X$21&""'""))))"),"") | H57: =IFERROR(__xludf.DUMMYFUNCTION("IF(H$43="""","""",IF($AZ57="""","""",IFERROR(Query({CarteirasAtivos},""Select Col3 where Col1 = '""&$AZ57&""'and Col2 = '""&Y$21&""'""))))"),"") | I57: =IFERROR(__xludf.DUMMYFUNCTION("IF(I$43="""","""",IF($AZ57="""","""",IFERROR(Query({CarteirasAtivos},""Select Col3 where Col1 = '""&$AZ57&""'and Col2 = '""&Z$21&""'""))))"),"") | J57: =IFERROR(__xludf.DUMMYFUNCTION("IF(J$43="""","""",IF($AZ57="""","""",IFERROR(Query({CarteirasAtivos},""Select Col3 where Col1 = '""&$AZ57&""'and Col2 = '""&AA$21&""'""))))"),"") | K57: =IFERROR(__xludf.DUMMYFUNCTION("IF(K$43="""","""",IF($AZ57="""","""",IFERROR(Query({CarteirasAtivos},""Select Col3 where Col1 = '""&$AZ57&""'and Col2 = '""&AB$21&""'""))))"),"") | L57: 14 | W57: =IFERROR(__xludf.DUMMYFUNCTION("IF(M57="""","""",sparkline(IFERROR(BF57*100/MAX($BF$44:$BF$153),0),{""charttype"",""bar"";""max"",100;""color1"",IF(BD57>=0,""#4760a5"",""red"")}))"),"") | AG57: =IFERROR(__xludf.DUMMYFUNCTION("IF($M57="""","""",IFERROR(sparkline(query(GOOGLEFINANCE($AZ57,""price"",TODAY()-$AF$43,TODAY(),1),""select Col2 label Col2 ''""),IF($AG$43=""Gráfico de barras"",{""charttype"",""column"";""highcolor"",""red""},{""chartype"",""line""}))))"),"") | AJ57: TRUE | AL57: TRUE | AV57: ▲ | AX57: desc | AY57: 14 | BG57: 14 | BO57: 4 | BX57: 14 | BZ57: 0 | CA57: 0 | CB57: - | CC57: 0 | CD57: 0 | CU57: 13 | CV57: OUTROS | CW57: =IFERROR(__xludf.DUMMYFUNCTION("IFERROR(query({$Q$20:$AL$20},""select Col""&MATCH(CZ57,$Q$21:$AL$21,0)),FALSE)"),FALSE) -> FALSE | CX57: FUNDO_RF_3 | CY57: Outros | CZ57: =IF(AV8,IF(DF57<>0,UPPER('config.parâmetros'!J5),"-"),"-") -> - | DB57: =IFERROR(DG57/$DG$63,"") | DC57: =IFERROR(DB57/SUM($DB$55:$DB$58),"") | DE57: =DF57-DJ57-DK57 -> 0 | DF57: =IF(ConfigOn,IFERROR(IFERROR(SUMIFS(portfolio.!$O$4:$O$303,portfolio.!$U$4:$U$303,CX57),0),0)) -> 0 | DG57: =IF(ConfigOn,IFERROR(IFERROR(SUMIFS(portfolio.!$AN$4:$AN$303,portfolio.!$U$4:$U$303,CX57),0),0)) -> 0 | DH57: =IF(ConfigOn,IFERROR(IFERROR(SUMIFS(portfolio.!$AO$4:$AO$303,portfolio.!$U$4:$U$303,CX57),0),0)) -> 0 | DI57: =IFERROR(DH57/DF57,0) -> 0 | DJ57: =IF(ConfigOn,IFERROR(IFERROR(SUMIFS(proventos!$Q$4:$Q343,proventos!$S$4:$S343,CX57),0),0)) -> 0 | DK57: =IF(ConfigOn,IFERROR(SUMIFS(op.normal!$P$4:$P343,op.normal!$AD$4:$AD343,CX57),0)) -> 0 | DL57: =IF(ConfigOn,DG57-DF57,0) -> 0 | DM57: =SUM(DJ57:DL57) -> 0 | DN57: =IF(AV8,((1+DO57)^(1/12))-1,"-") -> - | DO57: 0.12725654 | DP57: 4
B58: =IFERROR(__xludf.DUMMYFUNCTION("IF(B$43="""","""",IF($AZ58="""","""",IFERROR(Query({CarteirasAtivos},""Select Col3 where Col1 = '""&$AZ58&""'and Col2 = '""&S$21&""'""))))"),"") | C58: =IFERROR(__xludf.DUMMYFUNCTION("IF(C$43="""","""",IF($AZ58="""","""",IFERROR(Query({CarteirasAtivos},""Select Col3 where Col1 = '""&$AZ58&""'and Col2 = '""&T$21&""'""))))"),"") | D58: =IFERROR(__xludf.DUMMYFUNCTION("IF(D$43="""","""",IF($AZ58="""","""",IFERROR(Query({CarteirasAtivos},""Select Col3 where Col1 = '""&$AZ58&""'and Col2 = '""&U$21&""'""))))"),"") | E58: =IFERROR(__xludf.DUMMYFUNCTION("IF(E$43="""","""",IF($AZ58="""","""",IFERROR(Query({CarteirasAtivos},""Select Col3 where Col1 = '""&$AZ58&""'and Col2 = '""&V$21&""'""))))"),"") | F58: =IFERROR(__xludf.DUMMYFUNCTION("IF(F$43="""","""",IF($AZ58="""","""",IFERROR(Query({CarteirasAtivos},""Select Col3 where Col1 = '""&$AZ58&""'and Col2 = '""&W$21&""'""))))"),"") | G58: =IFERROR(__xludf.DUMMYFUNCTION("IF(G$43="""","""",IF($AZ58="""","""",IFERROR(Query({CarteirasAtivos},""Select Col3 where Col1 = '""&$AZ58&""'and Col2 = '""&X$21&""'""))))"),"") | H58: =IFERROR(__xludf.DUMMYFUNCTION("IF(H$43="""","""",IF($AZ58="""","""",IFERROR(Query({CarteirasAtivos},""Select Col3 where Col1 = '""&$AZ58&""'and Col2 = '""&Y$21&""'""))))"),"") | I58: =IFERROR(__xludf.DUMMYFUNCTION("IF(I$43="""","""",IF($AZ58="""","""",IFERROR(Query({CarteirasAtivos},""Select Col3 where Col1 = '""&$AZ58&""'and Col2 = '""&Z$21&""'""))))"),"") | J58: =IFERROR(__xludf.DUMMYFUNCTION("IF(J$43="""","""",IF($AZ58="""","""",IFERROR(Query({CarteirasAtivos},""Select Col3 where Col1 = '""&$AZ58&""'and Col2 = '""&AA$21&""'""))))"),"") | K58: =IFERROR(__xludf.DUMMYFUNCTION("IF(K$43="""","""",IF($AZ58="""","""",IFERROR(Query({CarteirasAtivos},""Select Col3 where Col1 = '""&$AZ58&""'and Col2 = '""&AB$21&""'""))))"),"") | L58: 15 | W58: =IFERROR(__xludf.DUMMYFUNCTION("IF(M58="""","""",sparkline(IFERROR(BF58*100/MAX($BF$44:$BF$153),0),{""charttype"",""bar"";""max"",100;""color1"",IF(BD58>=0,""#4760a5"",""red"")}))"),"") | AG58: =IFERROR(__xludf.DUMMYFUNCTION("IF($M58="""","""",IFERROR(sparkline(query(GOOGLEFINANCE($AZ58,""price"",TODAY()-$AF$43,TODAY(),1),""select Col2 label Col2 ''""),IF($AG$43=""Gráfico de barras"",{""charttype"",""column"";""highcolor"",""red""},{""chartype"",""line""}))))"),"") | AJ58: TRUE | AL58: TRUE | AV58: ▼ | AX58: asc | AY58: 15 | BG58: 15 | BO58: 5 | BX58: 15 | BZ58: 0 | CA58: 0 | CU58: 14 | CV58: OUTROS | CW58: =IFERROR(__xludf.DUMMYFUNCTION("IFERROR(query({$Q$20:$AL$20},""select Col""&MATCH(CZ58,$Q$21:$AL$21,0)),FALSE)"),FALSE) -> FALSE | CX58: FUNDO_RF_4 | CY58: Outros | CZ58: =IF(AV8,IF(DF58<>0,UPPER('config.parâmetros'!K5),"-"),"-") -> - | DB58: =IFERROR(DG58/$DG$63,"") | DC58: =IFERROR(DB58/SUM($DB$55:$DB$58),"") | DE58: =DF58-DJ58-DK58 -> 0 | DF58: =IF(ConfigOn,IFERROR(IFERROR(SUMIFS(portfolio.!$O$4:$O$303,portfolio.!$U$4:$U$303,CX58),0),0)) -> 0 | DG58: =IF(ConfigOn,IFERROR(IFERROR(SUMIFS(portfolio.!$AN$4:$AN$303,portfolio.!$U$4:$U$303,CX58),0),0)) -> 0 | DH58: =IF(ConfigOn,IFERROR(IFERROR(SUMIFS(portfolio.!$AO$4:$AO$303,portfolio.!$U$4:$U$303,CX58),0),0)) -> 0 | DI58: =IFERROR(DH58/DF58,0) -> 0 | DJ58: =IF(ConfigOn,IFERROR(IFERROR(SUMIFS(proventos!$Q$4:$Q343,proventos!$S$4:$S343,CX58),0),0)) -> 0 | DK58: =IF(ConfigOn,IFERROR(SUMIFS(op.normal!$P$4:$P343,op.normal!$AD$4:$AD343,CX58),0)) -> 0 | DL58: =IF(ConfigOn,DG58-DF58,0) -> 0 | DM58: =SUM(DJ58:DL58) -> 0 | DN58: =IF(AV8,((1+DO58)^(1/12))-1,"-") -> - | DO58: 0 | DP58: 4
B59: =IFERROR(__xludf.DUMMYFUNCTION("IF(B$43="""","""",IF($AZ59="""","""",IFERROR(Query({CarteirasAtivos},""Select Col3 where Col1 = '""&$AZ59&""'and Col2 = '""&S$21&""'""))))"),"") | C59: =IFERROR(__xludf.DUMMYFUNCTION("IF(C$43="""","""",IF($AZ59="""","""",IFERROR(Query({CarteirasAtivos},""Select Col3 where Col1 = '""&$AZ59&""'and Col2 = '""&T$21&""'""))))"),"") | D59: =IFERROR(__xludf.DUMMYFUNCTION("IF(D$43="""","""",IF($AZ59="""","""",IFERROR(Query({CarteirasAtivos},""Select Col3 where Col1 = '""&$AZ59&""'and Col2 = '""&U$21&""'""))))"),"") | E59: =IFERROR(__xludf.DUMMYFUNCTION("IF(E$43="""","""",IF($AZ59="""","""",IFERROR(Query({CarteirasAtivos},""Select Col3 where Col1 = '""&$AZ59&""'and Col2 = '""&V$21&""'""))))"),"") | F59: =IFERROR(__xludf.DUMMYFUNCTION("IF(F$43="""","""",IF($AZ59="""","""",IFERROR(Query({CarteirasAtivos},""Select Col3 where Col1 = '""&$AZ59&""'and Col2 = '""&W$21&""'""))))"),"") | G59: =IFERROR(__xludf.DUMMYFUNCTION("IF(G$43="""","""",IF($AZ59="""","""",IFERROR(Query({CarteirasAtivos},""Select Col3 where Col1 = '""&$AZ59&""'and Col2 = '""&X$21&""'""))))"),"") | H59: =IFERROR(__xludf.DUMMYFUNCTION("IF(H$43="""","""",IF($AZ59="""","""",IFERROR(Query({CarteirasAtivos},""Select Col3 where Col1 = '""&$AZ59&""'and Col2 = '""&Y$21&""'""))))"),"") | I59: =IFERROR(__xludf.DUMMYFUNCTION("IF(I$43="""","""",IF($AZ59="""","""",IFERROR(Query({CarteirasAtivos},""Select Col3 where Col1 = '""&$AZ59&""'and Col2 = '""&Z$21&""'""))))"),"") | J59: =IFERROR(__xludf.DUMMYFUNCTION("IF(J$43="""","""",IF($AZ59="""","""",IFERROR(Query({CarteirasAtivos},""Select Col3 where Col1 = '""&$AZ59&""'and Col2 = '""&AA$21&""'""))))"),"") | K59: =IFERROR(__xludf.DUMMYFUNCTION("IF(K$43="""","""",IF($AZ59="""","""",IFERROR(Query({CarteirasAtivos},""Select Col3 where Col1 = '""&$AZ59&""'and Col2 = '""&AB$21&""'""))))"),"") | L59: 16 | W59: =IFERROR(__xludf.DUMMYFUNCTION("IF(M59="""","""",sparkline(IFERROR(BF59*100/MAX($BF$44:$BF$153),0),{""charttype"",""bar"";""max"",100;""color1"",IF(BD59>=0,""#4760a5"",""red"")}))"),"") | AG59: =IFERROR(__xludf.DUMMYFUNCTION("IF($M59="""","""",IFERROR(sparkline(query(GOOGLEFINANCE($AZ59,""price"",TODAY()-$AF$43,TODAY(),1),""select Col2 label Col2 ''""),IF($AG$43=""Gráfico de barras"",{""charttype"",""column"";""highcolor"",""red""},{""chartype"",""line""}))))"),"") | AJ59: TRUE | AL59: TRUE | AY59: 16 | BG59: 16 | BO59: 6 | CV59: GRUPO | CW59: CHECK | CX59: CATEGORIA SUBTOTAL | CY59: PERFIL CRIADAS | CZ59: CARTEIRA | DB59: PESO % | DC59: PESO NORMALIZADO % | DE59: Valor Aportado | DF59: Valor Investido | DG59: Valor Mercado | DH59: Lucro dia R$ | DI59: Lucro dia % | DJ59: Valor Proventos | DK59: Valor Trades | DL59: Lucro Aberto | DM59: Lucro Total | DN59: TIR am | DO59: TIR aa | DP59: ORDER
B60: =IFERROR(__xludf.DUMMYFUNCTION("IF(B$43="""","""",IF($AZ60="""","""",IFERROR(Query({CarteirasAtivos},""Select Col3 where Col1 = '""&$AZ60&""'and Col2 = '""&S$21&""'""))))"),"") | C60: =IFERROR(__xludf.DUMMYFUNCTION("IF(C$43="""","""",IF($AZ60="""","""",IFERROR(Query({CarteirasAtivos},""Select Col3 where Col1 = '""&$AZ60&""'and Col2 = '""&T$21&""'""))))"),"") | D60: =IFERROR(__xludf.DUMMYFUNCTION("IF(D$43="""","""",IF($AZ60="""","""",IFERROR(Query({CarteirasAtivos},""Select Col3 where Col1 = '""&$AZ60&""'and Col2 = '""&U$21&""'""))))"),"") | E60: =IFERROR(__xludf.DUMMYFUNCTION("IF(E$43="""","""",IF($AZ60="""","""",IFERROR(Query({CarteirasAtivos},""Select Col3 where Col1 = '""&$AZ60&""'and Col2 = '""&V$21&""'""))))"),"") | F60: =IFERROR(__xludf.DUMMYFUNCTION("IF(F$43="""","""",IF($AZ60="""","""",IFERROR(Query({CarteirasAtivos},""Select Col3 where Col1 = '""&$AZ60&""'and Col2 = '""&W$21&""'""))))"),"") | G60: =IFERROR(__xludf.DUMMYFUNCTION("IF(G$43="""","""",IF($AZ60="""","""",IFERROR(Query({CarteirasAtivos},""Select Col3 where Col1 = '""&$AZ60&""'and Col2 = '""&X$21&""'""))))"),"") | H60: =IFERROR(__xludf.DUMMYFUNCTION("IF(H$43="""","""",IF($AZ60="""","""",IFERROR(Query({CarteirasAtivos},""Select Col3 where Col1 = '""&$AZ60&""'and Col2 = '""&Y$21&""'""))))"),"") | I60: =IFERROR(__xludf.DUMMYFUNCTION("IF(I$43="""","""",IF($AZ60="""","""",IFERROR(Query({CarteirasAtivos},""Select Col3 where Col1 = '""&$AZ60&""'and Col2 = '""&Z$21&""'""))))"),"") | J60: =IFERROR(__xludf.DUMMYFUNCTION("IF(J$43="""","""",IF($AZ60="""","""",IFERROR(Query({CarteirasAtivos},""Select Col3 where Col1 = '""&$AZ60&""'and Col2 = '""&AA$21&""'""))))"),"") | K60: =IFERROR(__xludf.DUMMYFUNCTION("IF(K$43="""","""",IF($AZ60="""","""",IFERROR(Query({CarteirasAtivos},""Select Col3 where Col1 = '""&$AZ60&""'and Col2 = '""&AB$21&""'""))))"),"") | L60: 17 | W60: =IFERROR(__xludf.DUMMYFUNCTION("IF(M60="""","""",sparkline(IFERROR(BF60*100/MAX($BF$44:$BF$153),0),{""charttype"",""bar"";""max"",100;""color1"",IF(BD60>=0,""#4760a5"",""red"")}))"),"") | AG60: =IFERROR(__xludf.DUMMYFUNCTION("IF($M60="""","""",IFERROR(sparkline(query(GOOGLEFINANCE($AZ60,""price"",TODAY()-$AF$43,TODAY(),1),""select Col2 label Col2 ''""),IF($AG$43=""Gráfico de barras"",{""charttype"",""column"";""highcolor"",""red""},{""chartype"",""line""}))))"),"") | AJ60: TRUE | AL60: TRUE | AY60: 17 | BG60: 17 | BO60: 7 | CU60: 15 | CV60: CARTEIRAS | CW60: =IFERROR(__xludf.DUMMYFUNCTION("IFERROR(query({$Q$20:$AL$20},""select Col""&MATCH(CZ60,$Q$21:$AL$21,0)))"),"") | CX60: PRINCIPAL | CY60: sem uso no momento | CZ60: =IF(AV8,IF(ConfigOn,"PRINCIPAIS OPERAÇÕES","-"),"-") -> - | DB60: =IFERROR(DG60/$DG$63,"") | DC60: 1 | DD60: =SUM(DD44:DD53) -> 0 | DE60: =DF60-DJ60-DK60 -> 0 | DF60: =IF(ConfigOn,IFERROR(IFERROR(SUMIFS(portfolio.!$O$4:$O$303,portfolio.!$U$4:$U$303,CX60),0),0)) -> 0 | DG60: =IF(ConfigOn,IFERROR(IFERROR(SUMIFS(portfolio.!$AN$4:$AN$303,portfolio.!$U$4:$U$303,CX60),0),0)) -> 0 | DH60: =IF(ConfigOn,IFERROR(IFERROR(SUMIFS(portfolio.!$AO$4:$AO$303,portfolio.!$U$4:$U$303,CX60),0),0)) -> 0 | DI60: =IFERROR(DH60/DF60,0) -> 0 | DJ60: =IF(ConfigOn,IFERROR(IFERROR(SUMIFS(proventos!$Q$4:$Q343,proventos!$S$4:$S343,CX60),0),0)) -> 0 | DK60: =IF(ConfigOn,IFERROR(SUMIFS(op.normal!$P$4:$P343,op.normal!$AD$4:$AD343,CX60),0)+DN65) -> 0 | DL60: =IF(ConfigOn,DG60-DF60,0) -> 0 | DM60: =SUM(DJ60:DL60) -> 0 | DN60: =IF(AV8,((1+DO60)^(1/12))-1,"-") -> - | DO60: -0.027730554 | DP60: 1
B61: =IFERROR(__xludf.DUMMYFUNCTION("IF(B$43="""","""",IF($AZ61="""","""",IFERROR(Query({CarteirasAtivos},""Select Col3 where Col1 = '""&$AZ61&""'and Col2 = '""&S$21&""'""))))"),"") | C61: =IFERROR(__xludf.DUMMYFUNCTION("IF(C$43="""","""",IF($AZ61="""","""",IFERROR(Query({CarteirasAtivos},""Select Col3 where Col1 = '""&$AZ61&""'and Col2 = '""&T$21&""'""))))"),"") | D61: =IFERROR(__xludf.DUMMYFUNCTION("IF(D$43="""","""",IF($AZ61="""","""",IFERROR(Query({CarteirasAtivos},""Select Col3 where Col1 = '""&$AZ61&""'and Col2 = '""&U$21&""'""))))"),"") | E61: =IFERROR(__xludf.DUMMYFUNCTION("IF(E$43="""","""",IF($AZ61="""","""",IFERROR(Query({CarteirasAtivos},""Select Col3 where Col1 = '""&$AZ61&""'and Col2 = '""&V$21&""'""))))"),"") | F61: =IFERROR(__xludf.DUMMYFUNCTION("IF(F$43="""","""",IF($AZ61="""","""",IFERROR(Query({CarteirasAtivos},""Select Col3 where Col1 = '""&$AZ61&""'and Col2 = '""&W$21&""'""))))"),"") | G61: =IFERROR(__xludf.DUMMYFUNCTION("IF(G$43="""","""",IF($AZ61="""","""",IFERROR(Query({CarteirasAtivos},""Select Col3 where Col1 = '""&$AZ61&""'and Col2 = '""&X$21&""'""))))"),"") | H61: =IFERROR(__xludf.DUMMYFUNCTION("IF(H$43="""","""",IF($AZ61="""","""",IFERROR(Query({CarteirasAtivos},""Select Col3 where Col1 = '""&$AZ61&""'and Col2 = '""&Y$21&""'""))))"),"") | I61: =IFERROR(__xludf.DUMMYFUNCTION("IF(I$43="""","""",IF($AZ61="""","""",IFERROR(Query({CarteirasAtivos},""Select Col3 where Col1 = '""&$AZ61&""'and Col2 = '""&Z$21&""'""))))"),"") | J61: =IFERROR(__xludf.DUMMYFUNCTION("IF(J$43="""","""",IF($AZ61="""","""",IFERROR(Query({CarteirasAtivos},""Select Col3 where Col1 = '""&$AZ61&""'and Col2 = '""&AA$21&""'""))))"),"") | K61: =IFERROR(__xludf.DUMMYFUNCTION("IF(K$43="""","""",IF($AZ61="""","""",IFERROR(Query({CarteirasAtivos},""Select Col3 where Col1 = '""&$AZ61&""'and Col2 = '""&AB$21&""'""))))"),"") | L61: 18 | W61: =IFERROR(__xludf.DUMMYFUNCTION("IF(M61="""","""",sparkline(IFERROR(BF61*100/MAX($BF$44:$BF$153),0),{""charttype"",""bar"";""max"",100;""color1"",IF(BD61>=0,""#4760a5"",""red"")}))"),"") | AG61: =IFERROR(__xludf.DUMMYFUNCTION("IF($M61="""","""",IFERROR(sparkline(query(GOOGLEFINANCE($AZ61,""price"",TODAY()-$AF$43,TODAY(),1),""select Col2 label Col2 ''""),IF($AG$43=""Gráfico de barras"",{""charttype"",""column"";""highcolor"",""red""},{""chartype"",""line""}))))"),"") | AJ61: TRUE | AL61: TRUE | AY61: 18 | BG61: 18 | BO61: 8 | CU61: 16 | CV61: OUTROS | CW61: =IFERROR(__xludf.DUMMYFUNCTION("IFERROR(query({$Q$20:$AL$20},""select Col""&MATCH(CZ61,$Q$21:$AL$21,0)))"),"") | CY61: sem uso no momento | CZ61: =IF(AV8,IF(DF61<>0,"FUNDOS E R.FIXA","-"),"-") -> - | DB61: =IFERROR(DG61/$DG$63,"") | DC61: 1 | DE61: =SUM(DE55:DE58) -> 0 | DF61: =SUM(DF55:DF58) -> 0 | DG61: =SUM(DG55:DG58) -> 0 | DH61: =SUM(DH55:DH58) -> 0 | DI61: =SUM(DI55:DI58) -> 0 | DJ61: =SUM(DJ55:DJ58) -> 0 | DK61: =IF(ConfigOn,SUM(DK55:DK58),0) -> 0 | DL61: =SUM(DL55:DL58) -> 0 | DM61: =IF(ConfigOn,SUM(DM55:DM58),0) -> 0 | DN61: =IF(AV8,((1+DO61)^(1/12))-1,"-") -> - | DO61: 0.036645556 | DP61: 3
B62: =IFERROR(__xludf.DUMMYFUNCTION("IF(B$43="""","""",IF($AZ62="""","""",IFERROR(Query({CarteirasAtivos},""Select Col3 where Col1 = '""&$AZ62&""'and Col2 = '""&S$21&""'""))))"),"") | C62: =IFERROR(__xludf.DUMMYFUNCTION("IF(C$43="""","""",IF($AZ62="""","""",IFERROR(Query({CarteirasAtivos},""Select Col3 where Col1 = '""&$AZ62&""'and Col2 = '""&T$21&""'""))))"),"") | D62: =IFERROR(__xludf.DUMMYFUNCTION("IF(D$43="""","""",IF($AZ62="""","""",IFERROR(Query({CarteirasAtivos},""Select Col3 where Col1 = '""&$AZ62&""'and Col2 = '""&U$21&""'""))))"),"") | E62: =IFERROR(__xludf.DUMMYFUNCTION("IF(E$43="""","""",IF($AZ62="""","""",IFERROR(Query({CarteirasAtivos},""Select Col3 where Col1 = '""&$AZ62&""'and Col2 = '""&V$21&""'""))))"),"") | F62: =IFERROR(__xludf.DUMMYFUNCTION("IF(F$43="""","""",IF($AZ62="""","""",IFERROR(Query({CarteirasAtivos},""Select Col3 where Col1 = '""&$AZ62&""'and Col2 = '""&W$21&""'""))))"),"") | G62: =IFERROR(__xludf.DUMMYFUNCTION("IF(G$43="""","""",IF($AZ62="""","""",IFERROR(Query({CarteirasAtivos},""Select Col3 where Col1 = '""&$AZ62&""'and Col2 = '""&X$21&""'""))))"),"") | H62: =IFERROR(__xludf.DUMMYFUNCTION("IF(H$43="""","""",IF($AZ62="""","""",IFERROR(Query({CarteirasAtivos},""Select Col3 where Col1 = '""&$AZ62&""'and Col2 = '""&Y$21&""'""))))"),"") | I62: =IFERROR(__xludf.DUMMYFUNCTION("IF(I$43="""","""",IF($AZ62="""","""",IFERROR(Query({CarteirasAtivos},""Select Col3 where Col1 = '""&$AZ62&""'and Col2 = '""&Z$21&""'""))))"),"") | J62: =IFERROR(__xludf.DUMMYFUNCTION("IF(J$43="""","""",IF($AZ62="""","""",IFERROR(Query({CarteirasAtivos},""Select Col3 where Col1 = '""&$AZ62&""'and Col2 = '""&AA$21&""'""))))"),"") | K62: =IFERROR(__xludf.DUMMYFUNCTION("IF(K$43="""","""",IF($AZ62="""","""",IFERROR(Query({CarteirasAtivos},""Select Col3 where Col1 = '""&$AZ62&""'and Col2 = '""&AB$21&""'""))))"),"") | L62: 19 | W62: =IFERROR(__xludf.DUMMYFUNCTION("IF(M62="""","""",sparkline(IFERROR(BF62*100/MAX($BF$44:$BF$153),0),{""charttype"",""bar"";""max"",100;""color1"",IF(BD62>=0,""#4760a5"",""red"")}))"),"") | AG62: =IFERROR(__xludf.DUMMYFUNCTION("IF($M62="""","""",IFERROR(sparkline(query(GOOGLEFINANCE($AZ62,""price"",TODAY()-$AF$43,TODAY(),1),""select Col2 label Col2 ''""),IF($AG$43=""Gráfico de barras"",{""charttype"",""column"";""highcolor"",""red""},{""chartype"",""line""}))))"),"") | AJ62: TRUE | AL62: TRUE | AY62: 19 | BG62: 19 | BO62: 9 | CU62: 17 | CV62: ATIVOS SEM CARTEIRA | CW62: =IFERROR(__xludf.DUMMYFUNCTION("IFERROR(query({$Q$20:$AL$20},""select Col""&MATCH(CZ62,$Q$21:$AL$21,0)))"),"") | CX62: DEMAIS | CY62: sem uso no momento | CZ62: =IF(AV8,IF(OR(SUM(DE62:DH62)<>0,SUM(DJ62:DM62)<>0),"DEMAIS OPERAÇÕES","-"),"-") -> - | DB62: =1-DB61-DB60 -> 1 | DC62: - | DE62: =trunc(DF62-DJ62-DK62,2) -> 0 | DF62: =TRUNC(DF63-DF61-DF60,2) -> 0 | DG62: =TRUNC(DG63-DG61-DG60,2) -> 0 | DH62: =TRUNC(DH63-DH61-DH60,2) -> 0 | DI62: =IFERROR(DH62/DF62,0) -> 0 | DJ62: =TRUNC(DJ63-DJ61-DJ60,2) -> 0 | DK62: =TRUNC(DK63-DK61-DK60,2) -> 0 | DL62: =TRUNC(DL63-DL61-DL60,2) -> 0 | DM62: =TRUNC(DM63-DM61-DM60,2) -> 0 | DN62: =IF(AV8,((1+DO62)^(1/12))-1,"-") -> - | DO62: -0.70676828 | DP62: 5
B63: =IFERROR(__xludf.DUMMYFUNCTION("IF(B$43="""","""",IF($AZ63="""","""",IFERROR(Query({CarteirasAtivos},""Select Col3 where Col1 = '""&$AZ63&""'and Col2 = '""&S$21&""'""))))"),"") | C63: =IFERROR(__xludf.DUMMYFUNCTION("IF(C$43="""","""",IF($AZ63="""","""",IFERROR(Query({CarteirasAtivos},""Select Col3 where Col1 = '""&$AZ63&""'and Col2 = '""&T$21&""'""))))"),"") | D63: =IFERROR(__xludf.DUMMYFUNCTION("IF(D$43="""","""",IF($AZ63="""","""",IFERROR(Query({CarteirasAtivos},""Select Col3 where Col1 = '""&$AZ63&""'and Col2 = '""&U$21&""'""))))"),"") | E63: =IFERROR(__xludf.DUMMYFUNCTION("IF(E$43="""","""",IF($AZ63="""","""",IFERROR(Query({CarteirasAtivos},""Select Col3 where Col1 = '""&$AZ63&""'and Col2 = '""&V$21&""'""))))"),"") | F63: =IFERROR(__xludf.DUMMYFUNCTION("IF(F$43="""","""",IF($AZ63="""","""",IFERROR(Query({CarteirasAtivos},""Select Col3 where Col1 = '""&$AZ63&""'and Col2 = '""&W$21&""'""))))"),"") | G63: =IFERROR(__xludf.DUMMYFUNCTION("IF(G$43="""","""",IF($AZ63="""","""",IFERROR(Query({CarteirasAtivos},""Select Col3 where Col1 = '""&$AZ63&""'and Col2 = '""&X$21&""'""))))"),"") | H63: =IFERROR(__xludf.DUMMYFUNCTION("IF(H$43="""","""",IF($AZ63="""","""",IFERROR(Query({CarteirasAtivos},""Select Col3 where Col1 = '""&$AZ63&""'and Col2 = '""&Y$21&""'""))))"),"") | I63: =IFERROR(__xludf.DUMMYFUNCTION("IF(I$43="""","""",IF($AZ63="""","""",IFERROR(Query({CarteirasAtivos},""Select Col3 where Col1 = '""&$AZ63&""'and Col2 = '""&Z$21&""'""))))"),"") | J63: =IFERROR(__xludf.DUMMYFUNCTION("IF(J$43="""","""",IF($AZ63="""","""",IFERROR(Query({CarteirasAtivos},""Select Col3 where Col1 = '""&$AZ63&""'and Col2 = '""&AA$21&""'""))))"),"") | K63: =IFERROR(__xludf.DUMMYFUNCTION("IF(K$43="""","""",IF($AZ63="""","""",IFERROR(Query({CarteirasAtivos},""Select Col3 where Col1 = '""&$AZ63&""'and Col2 = '""&AB$21&""'""))))"),"") | L63: 20 | W63: =IFERROR(__xludf.DUMMYFUNCTION("IF(M63="""","""",sparkline(IFERROR(BF63*100/MAX($BF$44:$BF$153),0),{""charttype"",""bar"";""max"",100;""color1"",IF(BD63>=0,""#4760a5"",""red"")}))"),"") | AG63: =IFERROR(__xludf.DUMMYFUNCTION("IF($M63="""","""",IFERROR(sparkline(query(GOOGLEFINANCE($AZ63,""price"",TODAY()-$AF$43,TODAY(),1),""select Col2 label Col2 ''""),IF($AG$43=""Gráfico de barras"",{""charttype"",""column"";""highcolor"",""red""},{""chartype"",""line""}))))"),"") | AY63: 20 | BG63: 20 | BO63: 10 | CV63: TOTAL | CW63: =IFERROR(__xludf.DUMMYFUNCTION("IFERROR(query({$Q$20:$AL$20},""select Col""&MATCH(CZ63,$Q$21:$AL$21,0)))"),"") | CY63: sem uso no momento | CZ63: =IF(AV8,"TOTAL","-") -> - | DB63: =IF(ConfigOn,100%,"") -> 1 | DC63: - | DE63: =IF(ConfigOn,DF63-DJ63-DK63,"") -> 0 | DF63: =IF(ConfigOn,SUM(portfolio.!O4:O343),"") -> 0 | DG63: =IF(ConfigOn,SUM(portfolio.!AN4:AN343),"") -> 0 | DH63: =IF(ConfigOn,SUM(portfolio.!AO4:AO343),"") -> 0 | DI63: =IFERROR(DH63/DF63,"") | DJ63: =IF(ConfigOn,SUM(proventos!Q5:Q343),"") -> 0 | DK63: =IF(ConfigOn,SUM(op.normal!P5:P343)+DN65,"") -> 0 | DL63: =IF(ConfigOn,DG63-DF63,"") -> 0 | DM63: =IF(ConfigOn,DJ63+DK63+DL63,"") -> 0 | DN63: =IF(ConfigOn,((1+DO63)^(1/12))-1,"-") -> -0.0014149368 | DO63: -0.016847727 | DP63: 0
B64: =IFERROR(__xludf.DUMMYFUNCTION("IF(B$43="""","""",IF($AZ64="""","""",IFERROR(Query({CarteirasAtivos},""Select Col3 where Col1 = '""&$AZ64&""'and Col2 = '""&S$21&""'""))))"),"") | C64: =IFERROR(__xludf.DUMMYFUNCTION("IF(C$43="""","""",IF($AZ64="""","""",IFERROR(Query({CarteirasAtivos},""Select Col3 where Col1 = '""&$AZ64&""'and Col2 = '""&T$21&""'""))))"),"") | D64: =IFERROR(__xludf.DUMMYFUNCTION("IF(D$43="""","""",IF($AZ64="""","""",IFERROR(Query({CarteirasAtivos},""Select Col3 where Col1 = '""&$AZ64&""'and Col2 = '""&U$21&""'""))))"),"") | E64: =IFERROR(__xludf.DUMMYFUNCTION("IF(E$43="""","""",IF($AZ64="""","""",IFERROR(Query({CarteirasAtivos},""Select Col3 where Col1 = '""&$AZ64&""'and Col2 = '""&V$21&""'""))))"),"") | F64: =IFERROR(__xludf.DUMMYFUNCTION("IF(F$43="""","""",IF($AZ64="""","""",IFERROR(Query({CarteirasAtivos},""Select Col3 where Col1 = '""&$AZ64&""'and Col2 = '""&W$21&""'""))))"),"") | G64: =IFERROR(__xludf.DUMMYFUNCTION("IF(G$43="""","""",IF($AZ64="""","""",IFERROR(Query({CarteirasAtivos},""Select Col3 where Col1 = '""&$AZ64&""'and Col2 = '""&X$21&""'""))))"),"") | H64: =IFERROR(__xludf.DUMMYFUNCTION("IF(H$43="""","""",IF($AZ64="""","""",IFERROR(Query({CarteirasAtivos},""Select Col3 where Col1 = '""&$AZ64&""'and Col2 = '""&Y$21&""'""))))"),"") | I64: =IFERROR(__xludf.DUMMYFUNCTION("IF(I$43="""","""",IF($AZ64="""","""",IFERROR(Query({CarteirasAtivos},""Select Col3 where Col1 = '""&$AZ64&""'and Col2 = '""&Z$21&""'""))))"),"") | J64: =IFERROR(__xludf.DUMMYFUNCTION("IF(J$43="""","""",IF($AZ64="""","""",IFERROR(Query({CarteirasAtivos},""Select Col3 where Col1 = '""&$AZ64&""'and Col2 = '""&AA$21&""'""))))"),"") | K64: =IFERROR(__xludf.DUMMYFUNCTION("IF(K$43="""","""",IF($AZ64="""","""",IFERROR(Query({CarteirasAtivos},""Select Col3 where Col1 = '""&$AZ64&""'and Col2 = '""&AB$21&""'""))))"),"") | L64: 21 | W64: =IFERROR(__xludf.DUMMYFUNCTION("IF(M64="""","""",sparkline(IFERROR(BF64*100/MAX($BF$44:$BF$153),0),{""charttype"",""bar"";""max"",100;""color1"",IF(BD64>=0,""#4760a5"",""red"")}))"),"") | AG64: =IFERROR(__xludf.DUMMYFUNCTION("IF($M64="""","""",IFERROR(sparkline(query(GOOGLEFINANCE($AZ64,""price"",TODAY()-$AF$43,TODAY(),1),""select Col2 label Col2 ''""),IF($AG$43=""Gráfico de barras"",{""charttype"",""column"";""highcolor"",""red""},{""chartype"",""line""}))))"),"") | AY64: 21 | BG64: 21
B65: =IFERROR(__xludf.DUMMYFUNCTION("IF(B$43="""","""",IF($AZ65="""","""",IFERROR(Query({CarteirasAtivos},""Select Col3 where Col1 = '""&$AZ65&""'and Col2 = '""&S$21&""'""))))"),"") | C65: =IFERROR(__xludf.DUMMYFUNCTION("IF(C$43="""","""",IF($AZ65="""","""",IFERROR(Query({CarteirasAtivos},""Select Col3 where Col1 = '""&$AZ65&""'and Col2 = '""&T$21&""'""))))"),"") | D65: =IFERROR(__xludf.DUMMYFUNCTION("IF(D$43="""","""",IF($AZ65="""","""",IFERROR(Query({CarteirasAtivos},""Select Col3 where Col1 = '""&$AZ65&""'and Col2 = '""&U$21&""'""))))"),"") | E65: =IFERROR(__xludf.DUMMYFUNCTION("IF(E$43="""","""",IF($AZ65="""","""",IFERROR(Query({CarteirasAtivos},""Select Col3 where Col1 = '""&$AZ65&""'and Col2 = '""&V$21&""'""))))"),"") | F65: =IFERROR(__xludf.DUMMYFUNCTION("IF(F$43="""","""",IF($AZ65="""","""",IFERROR(Query({CarteirasAtivos},""Select Col3 where Col1 = '""&$AZ65&""'and Col2 = '""&W$21&""'""))))"),"") | G65: =IFERROR(__xludf.DUMMYFUNCTION("IF(G$43="""","""",IF($AZ65="""","""",IFERROR(Query({CarteirasAtivos},""Select Col3 where Col1 = '""&$AZ65&""'and Col2 = '""&X$21&""'""))))"),"") | H65: =IFERROR(__xludf.DUMMYFUNCTION("IF(H$43="""","""",IF($AZ65="""","""",IFERROR(Query({CarteirasAtivos},""Select Col3 where Col1 = '""&$AZ65&""'and Col2 = '""&Y$21&""'""))))"),"") | I65: =IFERROR(__xludf.DUMMYFUNCTION("IF(I$43="""","""",IF($AZ65="""","""",IFERROR(Query({CarteirasAtivos},""Select Col3 where Col1 = '""&$AZ65&""'and Col2 = '""&Z$21&""'""))))"),"") | J65: =IFERROR(__xludf.DUMMYFUNCTION("IF(J$43="""","""",IF($AZ65="""","""",IFERROR(Query({CarteirasAtivos},""Select Col3 where Col1 = '""&$AZ65&""'and Col2 = '""&AA$21&""'""))))"),"") | K65: =IFERROR(__xludf.DUMMYFUNCTION("IF(K$43="""","""",IF($AZ65="""","""",IFERROR(Query({CarteirasAtivos},""Select Col3 where Col1 = '""&$AZ65&""'and Col2 = '""&AB$21&""'""))))"),"") | L65: 22 | W65: =IFERROR(__xludf.DUMMYFUNCTION("IF(M65="""","""",sparkline(IFERROR(BF65*100/MAX($BF$44:$BF$153),0),{""charttype"",""bar"";""max"",100;""color1"",IF(BD65>=0,""#4760a5"",""red"")}))"),"") | AG65: =IFERROR(__xludf.DUMMYFUNCTION("IF($M65="""","""",IFERROR(sparkline(query(GOOGLEFINANCE($AZ65,""price"",TODAY()-$AF$43,TODAY(),1),""select Col2 label Col2 ''""),IF($AG$43=""Gráfico de barras"",{""charttype"",""column"";""highcolor"",""red""},{""chartype"",""line""}))))"),"") | AY65: 22 | BG65: 22 | BP65: ACAO1 | BQ65: 100 | DM65: day trade | DN65: =SUM(DN67:DN86) -> 0 | DP65: USERS SELECIONADOS
B66: =IFERROR(__xludf.DUMMYFUNCTION("IF(B$43="""","""",IF($AZ66="""","""",IFERROR(Query({CarteirasAtivos},""Select Col3 where Col1 = '""&$AZ66&""'and Col2 = '""&S$21&""'""))))"),"") | C66: =IFERROR(__xludf.DUMMYFUNCTION("IF(C$43="""","""",IF($AZ66="""","""",IFERROR(Query({CarteirasAtivos},""Select Col3 where Col1 = '""&$AZ66&""'and Col2 = '""&T$21&""'""))))"),"") | D66: =IFERROR(__xludf.DUMMYFUNCTION("IF(D$43="""","""",IF($AZ66="""","""",IFERROR(Query({CarteirasAtivos},""Select Col3 where Col1 = '""&$AZ66&""'and Col2 = '""&U$21&""'""))))"),"") | E66: =IFERROR(__xludf.DUMMYFUNCTION("IF(E$43="""","""",IF($AZ66="""","""",IFERROR(Query({CarteirasAtivos},""Select Col3 where Col1 = '""&$AZ66&""'and Col2 = '""&V$21&""'""))))"),"") | F66: =IFERROR(__xludf.DUMMYFUNCTION("IF(F$43="""","""",IF($AZ66="""","""",IFERROR(Query({CarteirasAtivos},""Select Col3 where Col1 = '""&$AZ66&""'and Col2 = '""&W$21&""'""))))"),"") | G66: =IFERROR(__xludf.DUMMYFUNCTION("IF(G$43="""","""",IF($AZ66="""","""",IFERROR(Query({CarteirasAtivos},""Select Col3 where Col1 = '""&$AZ66&""'and Col2 = '""&X$21&""'""))))"),"") | H66: =IFERROR(__xludf.DUMMYFUNCTION("IF(H$43="""","""",IF($AZ66="""","""",IFERROR(Query({CarteirasAtivos},""Select Col3 where Col1 = '""&$AZ66&""'and Col2 = '""&Y$21&""'""))))"),"") | I66: =IFERROR(__xludf.DUMMYFUNCTION("IF(I$43="""","""",IF($AZ66="""","""",IFERROR(Query({CarteirasAtivos},""Select Col3 where Col1 = '""&$AZ66&""'and Col2 = '""&Z$21&""'""))))"),"") | J66: =IFERROR(__xludf.DUMMYFUNCTION("IF(J$43="""","""",IF($AZ66="""","""",IFERROR(Query({CarteirasAtivos},""Select Col3 where Col1 = '""&$AZ66&""'and Col2 = '""&AA$21&""'""))))"),"") | K66: =IFERROR(__xludf.DUMMYFUNCTION("IF(K$43="""","""",IF($AZ66="""","""",IFERROR(Query({CarteirasAtivos},""Select Col3 where Col1 = '""&$AZ66&""'and Col2 = '""&AB$21&""'""))))"),"") | L66: 23 | W66: =IFERROR(__xludf.DUMMYFUNCTION("IF(M66="""","""",sparkline(IFERROR(BF66*100/MAX($BF$44:$BF$153),0),{""charttype"",""bar"";""max"",100;""color1"",IF(BD66>=0,""#4760a5"",""red"")}))"),"") | AG66: =IFERROR(__xludf.DUMMYFUNCTION("IF($M66="""","""",IFERROR(sparkline(query(GOOGLEFINANCE($AZ66,""price"",TODAY()-$AF$43,TODAY(),1),""select Col2 label Col2 ''""),IF($AG$43=""Gráfico de barras"",{""charttype"",""column"";""highcolor"",""red""},{""chartype"",""line""}))))"),"") | AY66: 23 | BG66: 23 | BP66: ACAO2 | BQ66: 200 | DM66: corretora | DN66: lucro
B67: =IFERROR(__xludf.DUMMYFUNCTION("IF(B$43="""","""",IF($AZ67="""","""",IFERROR(Query({CarteirasAtivos},""Select Col3 where Col1 = '""&$AZ67&""'and Col2 = '""&S$21&""'""))))"),"") | C67: =IFERROR(__xludf.DUMMYFUNCTION("IF(C$43="""","""",IF($AZ67="""","""",IFERROR(Query({CarteirasAtivos},""Select Col3 where Col1 = '""&$AZ67&""'and Col2 = '""&T$21&""'""))))"),"") | D67: =IFERROR(__xludf.DUMMYFUNCTION("IF(D$43="""","""",IF($AZ67="""","""",IFERROR(Query({CarteirasAtivos},""Select Col3 where Col1 = '""&$AZ67&""'and Col2 = '""&U$21&""'""))))"),"") | E67: =IFERROR(__xludf.DUMMYFUNCTION("IF(E$43="""","""",IF($AZ67="""","""",IFERROR(Query({CarteirasAtivos},""Select Col3 where Col1 = '""&$AZ67&""'and Col2 = '""&V$21&""'""))))"),"") | F67: =IFERROR(__xludf.DUMMYFUNCTION("IF(F$43="""","""",IF($AZ67="""","""",IFERROR(Query({CarteirasAtivos},""Select Col3 where Col1 = '""&$AZ67&""'and Col2 = '""&W$21&""'""))))"),"") | G67: =IFERROR(__xludf.DUMMYFUNCTION("IF(G$43="""","""",IF($AZ67="""","""",IFERROR(Query({CarteirasAtivos},""Select Col3 where Col1 = '""&$AZ67&""'and Col2 = '""&X$21&""'""))))"),"") | H67: =IFERROR(__xludf.DUMMYFUNCTION("IF(H$43="""","""",IF($AZ67="""","""",IFERROR(Query({CarteirasAtivos},""Select Col3 where Col1 = '""&$AZ67&""'and Col2 = '""&Y$21&""'""))))"),"") | I67: =IFERROR(__xludf.DUMMYFUNCTION("IF(I$43="""","""",IF($AZ67="""","""",IFERROR(Query({CarteirasAtivos},""Select Col3 where Col1 = '""&$AZ67&""'and Col2 = '""&Z$21&""'""))))"),"") | J67: =IFERROR(__xludf.DUMMYFUNCTION("IF(J$43="""","""",IF($AZ67="""","""",IFERROR(Query({CarteirasAtivos},""Select Col3 where Col1 = '""&$AZ67&""'and Col2 = '""&AA$21&""'""))))"),"") | K67: =IFERROR(__xludf.DUMMYFUNCTION("IF(K$43="""","""",IF($AZ67="""","""",IFERROR(Query({CarteirasAtivos},""Select Col3 where Col1 = '""&$AZ67&""'and Col2 = '""&AB$21&""'""))))"),"") | L67: 24 | W67: =IFERROR(__xludf.DUMMYFUNCTION("IF(M67="""","""",sparkline(IFERROR(BF67*100/MAX($BF$44:$BF$153),0),{""charttype"",""bar"";""max"",100;""color1"",IF(BD67>=0,""#4760a5"",""red"")}))"),"") | AG67: =IFERROR(__xludf.DUMMYFUNCTION("IF($M67="""","""",IFERROR(sparkline(query(GOOGLEFINANCE($AZ67,""price"",TODAY()-$AF$43,TODAY(),1),""select Col2 label Col2 ''""),IF($AG$43=""Gráfico de barras"",{""charttype"",""column"";""highcolor"",""red""},{""chartype"",""line""}))))"),"") | AY67: 24 | BG67: 24 | BP67: ACAO3 | BQ67: 300 | DL67: 1 | DM67: {=sort(unique(op.daytrade!AC5:AC343),0,0)} | DN67: =IF(DM67="","",IFERROR(SUMIFS(op.daytrade!$P$5:$P343,op.daytrade!$AC$5:$AC343,DM67),0)) | DP67: {={IF('portfólio'!R4,'config.parâmetros'!B17,""); IF('portfólio'!U4,'config.parâmetros'!B18,""); IF('portfólio'!X4,'config.parâmetros'!B19,""); IF('portfólio'!AA4,'config.parâmetros'!B20,""); IF('portfólio'!AD4,'config.parâmetros'!B21,""); IF('portfólio'!AG4,'config.parâmetros'!B22,""); IF('portfólio'!AJ4,'config.parâmetros'!B23,"")}}
B68: =IFERROR(__xludf.DUMMYFUNCTION("IF(B$43="""","""",IF($AZ68="""","""",IFERROR(Query({CarteirasAtivos},""Select Col3 where Col1 = '""&$AZ68&""'and Col2 = '""&S$21&""'""))))"),"") | C68: =IFERROR(__xludf.DUMMYFUNCTION("IF(C$43="""","""",IF($AZ68="""","""",IFERROR(Query({CarteirasAtivos},""Select Col3 where Col1 = '""&$AZ68&""'and Col2 = '""&T$21&""'""))))"),"") | D68: =IFERROR(__xludf.DUMMYFUNCTION("IF(D$43="""","""",IF($AZ68="""","""",IFERROR(Query({CarteirasAtivos},""Select Col3 where Col1 = '""&$AZ68&""'and Col2 = '""&U$21&""'""))))"),"") | E68: =IFERROR(__xludf.DUMMYFUNCTION("IF(E$43="""","""",IF($AZ68="""","""",IFERROR(Query({CarteirasAtivos},""Select Col3 where Col1 = '""&$AZ68&""'and Col2 = '""&V$21&""'""))))"),"") | F68: =IFERROR(__xludf.DUMMYFUNCTION("IF(F$43="""","""",IF($AZ68="""","""",IFERROR(Query({CarteirasAtivos},""Select Col3 where Col1 = '""&$AZ68&""'and Col2 = '""&W$21&""'""))))"),"") | G68: =IFERROR(__xludf.DUMMYFUNCTION("IF(G$43="""","""",IF($AZ68="""","""",IFERROR(Query({CarteirasAtivos},""Select Col3 where Col1 = '""&$AZ68&""'and Col2 = '""&X$21&""'""))))"),"") | H68: =IFERROR(__xludf.DUMMYFUNCTION("IF(H$43="""","""",IF($AZ68="""","""",IFERROR(Query({CarteirasAtivos},""Select Col3 where Col1 = '""&$AZ68&""'and Col2 = '""&Y$21&""'""))))"),"") | I68: =IFERROR(__xludf.DUMMYFUNCTION("IF(I$43="""","""",IF($AZ68="""","""",IFERROR(Query({CarteirasAtivos},""Select Col3 where Col1 = '""&$AZ68&""'and Col2 = '""&Z$21&""'""))))"),"") | J68: =IFERROR(__xludf.DUMMYFUNCTION("IF(J$43="""","""",IF($AZ68="""","""",IFERROR(Query({CarteirasAtivos},""Select Col3 where Col1 = '""&$AZ68&""'and Col2 = '""&AA$21&""'""))))"),"") | K68: =IFERROR(__xludf.DUMMYFUNCTION("IF(K$43="""","""",IF($AZ68="""","""",IFERROR(Query({CarteirasAtivos},""Select Col3 where Col1 = '""&$AZ68&""'and Col2 = '""&AB$21&""'""))))"),"") | L68: 25 | W68: =IFERROR(__xludf.DUMMYFUNCTION("IF(M68="""","""",sparkline(IFERROR(BF68*100/MAX($BF$44:$BF$153),0),{""charttype"",""bar"";""max"",100;""color1"",IF(BD68>=0,""#4760a5"",""red"")}))"),"") | AG68: =IFERROR(__xludf.DUMMYFUNCTION("IF($M68="""","""",IFERROR(sparkline(query(GOOGLEFINANCE($AZ68,""price"",TODAY()-$AF$43,TODAY(),1),""select Col2 label Col2 ''""),IF($AG$43=""Gráfico de barras"",{""charttype"",""column"";""highcolor"",""red""},{""chartype"",""line""}))))"),"") | AY68: 25 | BG68: 25 | BP68: ACAO4 | BQ68: 400 | DL68: 2 | DN68: =IF(DM68="","",IFERROR(SUMIFS(op.daytrade!$P$5:$P343,op.daytrade!$AC$5:$AC343,DM68),0))
B69: =IFERROR(__xludf.DUMMYFUNCTION("IF(B$43="""","""",IF($AZ69="""","""",IFERROR(Query({CarteirasAtivos},""Select Col3 where Col1 = '""&$AZ69&""'and Col2 = '""&S$21&""'""))))"),"") | C69: =IFERROR(__xludf.DUMMYFUNCTION("IF(C$43="""","""",IF($AZ69="""","""",IFERROR(Query({CarteirasAtivos},""Select Col3 where Col1 = '""&$AZ69&""'and Col2 = '""&T$21&""'""))))"),"") | D69: =IFERROR(__xludf.DUMMYFUNCTION("IF(D$43="""","""",IF($AZ69="""","""",IFERROR(Query({CarteirasAtivos},""Select Col3 where Col1 = '""&$AZ69&""'and Col2 = '""&U$21&""'""))))"),"") | E69: =IFERROR(__xludf.DUMMYFUNCTION("IF(E$43="""","""",IF($AZ69="""","""",IFERROR(Query({CarteirasAtivos},""Select Col3 where Col1 = '""&$AZ69&""'and Col2 = '""&V$21&""'""))))"),"") | F69: =IFERROR(__xludf.DUMMYFUNCTION("IF(F$43="""","""",IF($AZ69="""","""",IFERROR(Query({CarteirasAtivos},""Select Col3 where Col1 = '""&$AZ69&""'and Col2 = '""&W$21&""'""))))"),"") | G69: =IFERROR(__xludf.DUMMYFUNCTION("IF(G$43="""","""",IF($AZ69="""","""",IFERROR(Query({CarteirasAtivos},""Select Col3 where Col1 = '""&$AZ69&""'and Col2 = '""&X$21&""'""))))"),"") | H69: =IFERROR(__xludf.DUMMYFUNCTION("IF(H$43="""","""",IF($AZ69="""","""",IFERROR(Query({CarteirasAtivos},""Select Col3 where Col1 = '""&$AZ69&""'and Col2 = '""&Y$21&""'""))))"),"") | I69: =IFERROR(__xludf.DUMMYFUNCTION("IF(I$43="""","""",IF($AZ69="""","""",IFERROR(Query({CarteirasAtivos},""Select Col3 where Col1 = '""&$AZ69&""'and Col2 = '""&Z$21&""'""))))"),"") | J69: =IFERROR(__xludf.DUMMYFUNCTION("IF(J$43="""","""",IF($AZ69="""","""",IFERROR(Query({CarteirasAtivos},""Select Col3 where Col1 = '""&$AZ69&""'and Col2 = '""&AA$21&""'""))))"),"") | K69: =IFERROR(__xludf.DUMMYFUNCTION("IF(K$43="""","""",IF($AZ69="""","""",IFERROR(Query({CarteirasAtivos},""Select Col3 where Col1 = '""&$AZ69&""'and Col2 = '""&AB$21&""'""))))"),"") | L69: 26 | W69: =IFERROR(__xludf.DUMMYFUNCTION("IF(M69="""","""",sparkline(IFERROR(BF69*100/MAX($BF$44:$BF$153),0),{""charttype"",""bar"";""max"",100;""color1"",IF(BD69>=0,""#4760a5"",""red"")}))"),"") | AG69: =IFERROR(__xludf.DUMMYFUNCTION("IF($M69="""","""",IFERROR(sparkline(query(GOOGLEFINANCE($AZ69,""price"",TODAY()-$AF$43,TODAY(),1),""select Col2 label Col2 ''""),IF($AG$43=""Gráfico de barras"",{""charttype"",""column"";""highcolor"",""red""},{""chartype"",""line""}))))"),"") | AY69: 26 | BG69: 26 | BP69: ACAO5 | BQ69: 500 | DL69: 3 | DN69: =IF(DM69="","",IFERROR(SUMIFS(op.daytrade!$P$5:$P343,op.daytrade!$AC$5:$AC343,DM69),0))
B70: =IFERROR(__xludf.DUMMYFUNCTION("IF(B$43="""","""",IF($AZ70="""","""",IFERROR(Query({CarteirasAtivos},""Select Col3 where Col1 = '""&$AZ70&""'and Col2 = '""&S$21&""'""))))"),"") | C70: =IFERROR(__xludf.DUMMYFUNCTION("IF(C$43="""","""",IF($AZ70="""","""",IFERROR(Query({CarteirasAtivos},""Select Col3 where Col1 = '""&$AZ70&""'and Col2 = '""&T$21&""'""))))"),"") | D70: =IFERROR(__xludf.DUMMYFUNCTION("IF(D$43="""","""",IF($AZ70="""","""",IFERROR(Query({CarteirasAtivos},""Select Col3 where Col1 = '""&$AZ70&""'and Col2 = '""&U$21&""'""))))"),"") | E70: =IFERROR(__xludf.DUMMYFUNCTION("IF(E$43="""","""",IF($AZ70="""","""",IFERROR(Query({CarteirasAtivos},""Select Col3 where Col1 = '""&$AZ70&""'and Col2 = '""&V$21&""'""))))"),"") | F70: =IFERROR(__xludf.DUMMYFUNCTION("IF(F$43="""","""",IF($AZ70="""","""",IFERROR(Query({CarteirasAtivos},""Select Col3 where Col1 = '""&$AZ70&""'and Col2 = '""&W$21&""'""))))"),"") | G70: =IFERROR(__xludf.DUMMYFUNCTION("IF(G$43="""","""",IF($AZ70="""","""",IFERROR(Query({CarteirasAtivos},""Select Col3 where Col1 = '""&$AZ70&""'and Col2 = '""&X$21&""'""))))"),"") | H70: =IFERROR(__xludf.DUMMYFUNCTION("IF(H$43="""","""",IF($AZ70="""","""",IFERROR(Query({CarteirasAtivos},""Select Col3 where Col1 = '""&$AZ70&""'and Col2 = '""&Y$21&""'""))))"),"") | I70: =IFERROR(__xludf.DUMMYFUNCTION("IF(I$43="""","""",IF($AZ70="""","""",IFERROR(Query({CarteirasAtivos},""Select Col3 where Col1 = '""&$AZ70&""'and Col2 = '""&Z$21&""'""))))"),"") | J70: =IFERROR(__xludf.DUMMYFUNCTION("IF(J$43="""","""",IF($AZ70="""","""",IFERROR(Query({CarteirasAtivos},""Select Col3 where Col1 = '""&$AZ70&""'and Col2 = '""&AA$21&""'""))))"),"") | K70: =IFERROR(__xludf.DUMMYFUNCTION("IF(K$43="""","""",IF($AZ70="""","""",IFERROR(Query({CarteirasAtivos},""Select Col3 where Col1 = '""&$AZ70&""'and Col2 = '""&AB$21&""'""))))"),"") | L70: 27 | W70: =IFERROR(__xludf.DUMMYFUNCTION("IF(M70="""","""",sparkline(IFERROR(BF70*100/MAX($BF$44:$BF$153),0),{""charttype"",""bar"";""max"",100;""color1"",IF(BD70>=0,""#4760a5"",""red"")}))"),"") | AG70: =IFERROR(__xludf.DUMMYFUNCTION("IF($M70="""","""",IFERROR(sparkline(query(GOOGLEFINANCE($AZ70,""price"",TODAY()-$AF$43,TODAY(),1),""select Col2 label Col2 ''""),IF($AG$43=""Gráfico de barras"",{""charttype"",""column"";""highcolor"",""red""},{""chartype"",""line""}))))"),"") | AY70: 27 | BG70: 27 | BP70: ACAO6 | BQ70: -100 | DL70: 4 | DN70: =IF(DM70="","",IFERROR(SUMIFS(op.daytrade!$P$5:$P343,op.daytrade!$AC$5:$AC343,DM70),0))
B71: =IFERROR(__xludf.DUMMYFUNCTION("IF(B$43="""","""",IF($AZ71="""","""",IFERROR(Query({CarteirasAtivos},""Select Col3 where Col1 = '""&$AZ71&""'and Col2 = '""&S$21&""'""))))"),"") | C71: =IFERROR(__xludf.DUMMYFUNCTION("IF(C$43="""","""",IF($AZ71="""","""",IFERROR(Query({CarteirasAtivos},""Select Col3 where Col1 = '""&$AZ71&""'and Col2 = '""&T$21&""'""))))"),"") | D71: =IFERROR(__xludf.DUMMYFUNCTION("IF(D$43="""","""",IF($AZ71="""","""",IFERROR(Query({CarteirasAtivos},""Select Col3 where Col1 = '""&$AZ71&""'and Col2 = '""&U$21&""'""))))"),"") | E71: =IFERROR(__xludf.DUMMYFUNCTION("IF(E$43="""","""",IF($AZ71="""","""",IFERROR(Query({CarteirasAtivos},""Select Col3 where Col1 = '""&$AZ71&""'and Col2 = '""&V$21&""'""))))"),"") | F71: =IFERROR(__xludf.DUMMYFUNCTION("IF(F$43="""","""",IF($AZ71="""","""",IFERROR(Query({CarteirasAtivos},""Select Col3 where Col1 = '""&$AZ71&""'and Col2 = '""&W$21&""'""))))"),"") | G71: =IFERROR(__xludf.DUMMYFUNCTION("IF(G$43="""","""",IF($AZ71="""","""",IFERROR(Query({CarteirasAtivos},""Select Col3 where Col1 = '""&$AZ71&""'and Col2 = '""&X$21&""'""))))"),"") | H71: =IFERROR(__xludf.DUMMYFUNCTION("IF(H$43="""","""",IF($AZ71="""","""",IFERROR(Query({CarteirasAtivos},""Select Col3 where Col1 = '""&$AZ71&""'and Col2 = '""&Y$21&""'""))))"),"") | I71: =IFERROR(__xludf.DUMMYFUNCTION("IF(I$43="""","""",IF($AZ71="""","""",IFERROR(Query({CarteirasAtivos},""Select Col3 where Col1 = '""&$AZ71&""'and Col2 = '""&Z$21&""'""))))"),"") | J71: =IFERROR(__xludf.DUMMYFUNCTION("IF(J$43="""","""",IF($AZ71="""","""",IFERROR(Query({CarteirasAtivos},""Select Col3 where Col1 = '""&$AZ71&""'and Col2 = '""&AA$21&""'""))))"),"") | K71: =IFERROR(__xludf.DUMMYFUNCTION("IF(K$43="""","""",IF($AZ71="""","""",IFERROR(Query({CarteirasAtivos},""Select Col3 where Col1 = '""&$AZ71&""'and Col2 = '""&AB$21&""'""))))"),"") | L71: 28 | W71: =IFERROR(__xludf.DUMMYFUNCTION("IF(M71="""","""",sparkline(IFERROR(BF71*100/MAX($BF$44:$BF$153),0),{""charttype"",""bar"";""max"",100;""color1"",IF(BD71>=0,""#4760a5"",""red"")}))"),"") | AG71: =IFERROR(__xludf.DUMMYFUNCTION("IF($M71="""","""",IFERROR(sparkline(query(GOOGLEFINANCE($AZ71,""price"",TODAY()-$AF$43,TODAY(),1),""select Col2 label Col2 ''""),IF($AG$43=""Gráfico de barras"",{""charttype"",""column"";""highcolor"",""red""},{""chartype"",""line""}))))"),"") | AY71: 28 | BG71: 28 | BP71: ACAO7 | BQ71: -200 | DL71: 5 | DN71: =IF(DM71="","",IFERROR(SUMIFS(op.daytrade!$P$5:$P343,op.daytrade!$AC$5:$AC343,DM71),0))
B72: =IFERROR(__xludf.DUMMYFUNCTION("IF(B$43="""","""",IF($AZ72="""","""",IFERROR(Query({CarteirasAtivos},""Select Col3 where Col1 = '""&$AZ72&""'and Col2 = '""&S$21&""'""))))"),"") | C72: =IFERROR(__xludf.DUMMYFUNCTION("IF(C$43="""","""",IF($AZ72="""","""",IFERROR(Query({CarteirasAtivos},""Select Col3 where Col1 = '""&$AZ72&""'and Col2 = '""&T$21&""'""))))"),"") | D72: =IFERROR(__xludf.DUMMYFUNCTION("IF(D$43="""","""",IF($AZ72="""","""",IFERROR(Query({CarteirasAtivos},""Select Col3 where Col1 = '""&$AZ72&""'and Col2 = '""&U$21&""'""))))"),"") | E72: =IFERROR(__xludf.DUMMYFUNCTION("IF(E$43="""","""",IF($AZ72="""","""",IFERROR(Query({CarteirasAtivos},""Select Col3 where Col1 = '""&$AZ72&""'and Col2 = '""&V$21&""'""))))"),"") | F72: =IFERROR(__xludf.DUMMYFUNCTION("IF(F$43="""","""",IF($AZ72="""","""",IFERROR(Query({CarteirasAtivos},""Select Col3 where Col1 = '""&$AZ72&""'and Col2 = '""&W$21&""'""))))"),"") | G72: =IFERROR(__xludf.DUMMYFUNCTION("IF(G$43="""","""",IF($AZ72="""","""",IFERROR(Query({CarteirasAtivos},""Select Col3 where Col1 = '""&$AZ72&""'and Col2 = '""&X$21&""'""))))"),"") | H72: =IFERROR(__xludf.DUMMYFUNCTION("IF(H$43="""","""",IF($AZ72="""","""",IFERROR(Query({CarteirasAtivos},""Select Col3 where Col1 = '""&$AZ72&""'and Col2 = '""&Y$21&""'""))))"),"") | I72: =IFERROR(__xludf.DUMMYFUNCTION("IF(I$43="""","""",IF($AZ72="""","""",IFERROR(Query({CarteirasAtivos},""Select Col3 where Col1 = '""&$AZ72&""'and Col2 = '""&Z$21&""'""))))"),"") | J72: =IFERROR(__xludf.DUMMYFUNCTION("IF(J$43="""","""",IF($AZ72="""","""",IFERROR(Query({CarteirasAtivos},""Select Col3 where Col1 = '""&$AZ72&""'and Col2 = '""&AA$21&""'""))))"),"") | K72: =IFERROR(__xludf.DUMMYFUNCTION("IF(K$43="""","""",IF($AZ72="""","""",IFERROR(Query({CarteirasAtivos},""Select Col3 where Col1 = '""&$AZ72&""'and Col2 = '""&AB$21&""'""))))"),"") | L72: 29 | W72: =IFERROR(__xludf.DUMMYFUNCTION("IF(M72="""","""",sparkline(IFERROR(BF72*100/MAX($BF$44:$BF$153),0),{""charttype"",""bar"";""max"",100;""color1"",IF(BD72>=0,""#4760a5"",""red"")}))"),"") | AG72: =IFERROR(__xludf.DUMMYFUNCTION("IF($M72="""","""",IFERROR(sparkline(query(GOOGLEFINANCE($AZ72,""price"",TODAY()-$AF$43,TODAY(),1),""select Col2 label Col2 ''""),IF($AG$43=""Gráfico de barras"",{""charttype"",""column"";""highcolor"",""red""},{""chartype"",""line""}))))"),"") | AY72: 29 | BG72: 29 | BP72: ACAO8 | BQ72: -300 | DL72: 6 | DN72: =IF(DM72="","",IFERROR(SUMIFS(op.daytrade!$P$5:$P343,op.daytrade!$AC$5:$AC343,DM72),0))
B73: =IFERROR(__xludf.DUMMYFUNCTION("IF(B$43="""","""",IF($AZ73="""","""",IFERROR(Query({CarteirasAtivos},""Select Col3 where Col1 = '""&$AZ73&""'and Col2 = '""&S$21&""'""))))"),"") | C73: =IFERROR(__xludf.DUMMYFUNCTION("IF(C$43="""","""",IF($AZ73="""","""",IFERROR(Query({CarteirasAtivos},""Select Col3 where Col1 = '""&$AZ73&""'and Col2 = '""&T$21&""'""))))"),"") | D73: =IFERROR(__xludf.DUMMYFUNCTION("IF(D$43="""","""",IF($AZ73="""","""",IFERROR(Query({CarteirasAtivos},""Select Col3 where Col1 = '""&$AZ73&""'and Col2 = '""&U$21&""'""))))"),"") | E73: =IFERROR(__xludf.DUMMYFUNCTION("IF(E$43="""","""",IF($AZ73="""","""",IFERROR(Query({CarteirasAtivos},""Select Col3 where Col1 = '""&$AZ73&""'and Col2 = '""&V$21&""'""))))"),"") | F73: =IFERROR(__xludf.DUMMYFUNCTION("IF(F$43="""","""",IF($AZ73="""","""",IFERROR(Query({CarteirasAtivos},""Select Col3 where Col1 = '""&$AZ73&""'and Col2 = '""&W$21&""'""))))"),"") | G73: =IFERROR(__xludf.DUMMYFUNCTION("IF(G$43="""","""",IF($AZ73="""","""",IFERROR(Query({CarteirasAtivos},""Select Col3 where Col1 = '""&$AZ73&""'and Col2 = '""&X$21&""'""))))"),"") | H73: =IFERROR(__xludf.DUMMYFUNCTION("IF(H$43="""","""",IF($AZ73="""","""",IFERROR(Query({CarteirasAtivos},""Select Col3 where Col1 = '""&$AZ73&""'and Col2 = '""&Y$21&""'""))))"),"") | I73: =IFERROR(__xludf.DUMMYFUNCTION("IF(I$43="""","""",IF($AZ73="""","""",IFERROR(Query({CarteirasAtivos},""Select Col3 where Col1 = '""&$AZ73&""'and Col2 = '""&Z$21&""'""))))"),"") | J73: =IFERROR(__xludf.DUMMYFUNCTION("IF(J$43="""","""",IF($AZ73="""","""",IFERROR(Query({CarteirasAtivos},""Select Col3 where Col1 = '""&$AZ73&""'and Col2 = '""&AA$21&""'""))))"),"") | K73: =IFERROR(__xludf.DUMMYFUNCTION("IF(K$43="""","""",IF($AZ73="""","""",IFERROR(Query({CarteirasAtivos},""Select Col3 where Col1 = '""&$AZ73&""'and Col2 = '""&AB$21&""'""))))"),"") | L73: 30 | W73: =IFERROR(__xludf.DUMMYFUNCTION("IF(M73="""","""",sparkline(IFERROR(BF73*100/MAX($BF$44:$BF$153),0),{""charttype"",""bar"";""max"",100;""color1"",IF(BD73>=0,""#4760a5"",""red"")}))"),"") | AG73: =IFERROR(__xludf.DUMMYFUNCTION("IF($M73="""","""",IFERROR(sparkline(query(GOOGLEFINANCE($AZ73,""price"",TODAY()-$AF$43,TODAY(),1),""select Col2 label Col2 ''""),IF($AG$43=""Gráfico de barras"",{""charttype"",""column"";""highcolor"",""red""},{""chartype"",""line""}))))"),"") | AY73: 30 | BG73: 30 | BP73: ACAO9 | BQ73: -400 | DL73: 7 | DN73: =IF(DM73="","",IFERROR(SUMIFS(op.daytrade!$P$5:$P343,op.daytrade!$AC$5:$AC343,DM73),0))
B74: =IFERROR(__xludf.DUMMYFUNCTION("IF(B$43="""","""",IF($AZ74="""","""",IFERROR(Query({CarteirasAtivos},""Select Col3 where Col1 = '""&$AZ74&""'and Col2 = '""&S$21&""'""))))"),"") | C74: =IFERROR(__xludf.DUMMYFUNCTION("IF(C$43="""","""",IF($AZ74="""","""",IFERROR(Query({CarteirasAtivos},""Select Col3 where Col1 = '""&$AZ74&""'and Col2 = '""&T$21&""'""))))"),"") | D74: =IFERROR(__xludf.DUMMYFUNCTION("IF(D$43="""","""",IF($AZ74="""","""",IFERROR(Query({CarteirasAtivos},""Select Col3 where Col1 = '""&$AZ74&""'and Col2 = '""&U$21&""'""))))"),"") | E74: =IFERROR(__xludf.DUMMYFUNCTION("IF(E$43="""","""",IF($AZ74="""","""",IFERROR(Query({CarteirasAtivos},""Select Col3 where Col1 = '""&$AZ74&""'and Col2 = '""&V$21&""'""))))"),"") | F74: =IFERROR(__xludf.DUMMYFUNCTION("IF(F$43="""","""",IF($AZ74="""","""",IFERROR(Query({CarteirasAtivos},""Select Col3 where Col1 = '""&$AZ74&""'and Col2 = '""&W$21&""'""))))"),"") | G74: =IFERROR(__xludf.DUMMYFUNCTION("IF(G$43="""","""",IF($AZ74="""","""",IFERROR(Query({CarteirasAtivos},""Select Col3 where Col1 = '""&$AZ74&""'and Col2 = '""&X$21&""'""))))"),"") | H74: =IFERROR(__xludf.DUMMYFUNCTION("IF(H$43="""","""",IF($AZ74="""","""",IFERROR(Query({CarteirasAtivos},""Select Col3 where Col1 = '""&$AZ74&""'and Col2 = '""&Y$21&""'""))))"),"") | I74: =IFERROR(__xludf.DUMMYFUNCTION("IF(I$43="""","""",IF($AZ74="""","""",IFERROR(Query({CarteirasAtivos},""Select Col3 where Col1 = '""&$AZ74&""'and Col2 = '""&Z$21&""'""))))"),"") | J74: =IFERROR(__xludf.DUMMYFUNCTION("IF(J$43="""","""",IF($AZ74="""","""",IFERROR(Query({CarteirasAtivos},""Select Col3 where Col1 = '""&$AZ74&""'and Col2 = '""&AA$21&""'""))))"),"") | K74: =IFERROR(__xludf.DUMMYFUNCTION("IF(K$43="""","""",IF($AZ74="""","""",IFERROR(Query({CarteirasAtivos},""Select Col3 where Col1 = '""&$AZ74&""'and Col2 = '""&AB$21&""'""))))"),"") | L74: 31 | W74: =IFERROR(__xludf.DUMMYFUNCTION("IF(M74="""","""",sparkline(IFERROR(BF74*100/MAX($BF$44:$BF$153),0),{""charttype"",""bar"";""max"",100;""color1"",IF(BD74>=0,""#4760a5"",""red"")}))"),"") | AG74: =IFERROR(__xludf.DUMMYFUNCTION("IF($M74="""","""",IFERROR(sparkline(query(GOOGLEFINANCE($AZ74,""price"",TODAY()-$AF$43,TODAY(),1),""select Col2 label Col2 ''""),IF($AG$43=""Gráfico de barras"",{""charttype"",""column"";""highcolor"",""red""},{""chartype"",""line""}))))"),"") | AY74: 31 | BG74: 31 | BP74: ACAO10 | BQ74: -500 | DL74: 8 | DN74: =IF(DM74="","",IFERROR(SUMIFS(op.daytrade!$P$5:$P343,op.daytrade!$AC$5:$AC343,DM74),0))
B75: =IFERROR(__xludf.DUMMYFUNCTION("IF(B$43="""","""",IF($AZ75="""","""",IFERROR(Query({CarteirasAtivos},""Select Col3 where Col1 = '""&$AZ75&""'and Col2 = '""&S$21&""'""))))"),"") | C75: =IFERROR(__xludf.DUMMYFUNCTION("IF(C$43="""","""",IF($AZ75="""","""",IFERROR(Query({CarteirasAtivos},""Select Col3 where Col1 = '""&$AZ75&""'and Col2 = '""&T$21&""'""))))"),"") | D75: =IFERROR(__xludf.DUMMYFUNCTION("IF(D$43="""","""",IF($AZ75="""","""",IFERROR(Query({CarteirasAtivos},""Select Col3 where Col1 = '""&$AZ75&""'and Col2 = '""&U$21&""'""))))"),"") | E75: =IFERROR(__xludf.DUMMYFUNCTION("IF(E$43="""","""",IF($AZ75="""","""",IFERROR(Query({CarteirasAtivos},""Select Col3 where Col1 = '""&$AZ75&""'and Col2 = '""&V$21&""'""))))"),"") | F75: =IFERROR(__xludf.DUMMYFUNCTION("IF(F$43="""","""",IF($AZ75="""","""",IFERROR(Query({CarteirasAtivos},""Select Col3 where Col1 = '""&$AZ75&""'and Col2 = '""&W$21&""'""))))"),"") | G75: =IFERROR(__xludf.DUMMYFUNCTION("IF(G$43="""","""",IF($AZ75="""","""",IFERROR(Query({CarteirasAtivos},""Select Col3 where Col1 = '""&$AZ75&""'and Col2 = '""&X$21&""'""))))"),"") | H75: =IFERROR(__xludf.DUMMYFUNCTION("IF(H$43="""","""",IF($AZ75="""","""",IFERROR(Query({CarteirasAtivos},""Select Col3 where Col1 = '""&$AZ75&""'and Col2 = '""&Y$21&""'""))))"),"") | I75: =IFERROR(__xludf.DUMMYFUNCTION("IF(I$43="""","""",IF($AZ75="""","""",IFERROR(Query({CarteirasAtivos},""Select Col3 where Col1 = '""&$AZ75&""'and Col2 = '""&Z$21&""'""))))"),"") | J75: =IFERROR(__xludf.DUMMYFUNCTION("IF(J$43="""","""",IF($AZ75="""","""",IFERROR(Query({CarteirasAtivos},""Select Col3 where Col1 = '""&$AZ75&""'and Col2 = '""&AA$21&""'""))))"),"") | K75: =IFERROR(__xludf.DUMMYFUNCTION("IF(K$43="""","""",IF($AZ75="""","""",IFERROR(Query({CarteirasAtivos},""Select Col3 where Col1 = '""&$AZ75&""'and Col2 = '""&AB$21&""'""))))"),"") | L75: 32 | W75: =IFERROR(__xludf.DUMMYFUNCTION("IF(M75="""","""",sparkline(IFERROR(BF75*100/MAX($BF$44:$BF$153),0),{""charttype"",""bar"";""max"",100;""color1"",IF(BD75>=0,""#4760a5"",""red"")}))"),"") | AG75: =IFERROR(__xludf.DUMMYFUNCTION("IF($M75="""","""",IFERROR(sparkline(query(GOOGLEFINANCE($AZ75,""price"",TODAY()-$AF$43,TODAY(),1),""select Col2 label Col2 ''""),IF($AG$43=""Gráfico de barras"",{""charttype"",""column"";""highcolor"",""red""},{""chartype"",""line""}))))"),"") | AY75: 32 | BG75: 32 | DL75: 9 | DN75: =IF(DM75="","",IFERROR(SUMIFS(op.daytrade!$P$5:$P343,op.daytrade!$AC$5:$AC343,DM75),0)) | DP75: NADA SEL?
B76: =IFERROR(__xludf.DUMMYFUNCTION("IF(B$43="""","""",IF($AZ76="""","""",IFERROR(Query({CarteirasAtivos},""Select Col3 where Col1 = '""&$AZ76&""'and Col2 = '""&S$21&""'""))))"),"") | C76: =IFERROR(__xludf.DUMMYFUNCTION("IF(C$43="""","""",IF($AZ76="""","""",IFERROR(Query({CarteirasAtivos},""Select Col3 where Col1 = '""&$AZ76&""'and Col2 = '""&T$21&""'""))))"),"") | D76: =IFERROR(__xludf.DUMMYFUNCTION("IF(D$43="""","""",IF($AZ76="""","""",IFERROR(Query({CarteirasAtivos},""Select Col3 where Col1 = '""&$AZ76&""'and Col2 = '""&U$21&""'""))))"),"") | E76: =IFERROR(__xludf.DUMMYFUNCTION("IF(E$43="""","""",IF($AZ76="""","""",IFERROR(Query({CarteirasAtivos},""Select Col3 where Col1 = '""&$AZ76&""'and Col2 = '""&V$21&""'""))))"),"") | F76: =IFERROR(__xludf.DUMMYFUNCTION("IF(F$43="""","""",IF($AZ76="""","""",IFERROR(Query({CarteirasAtivos},""Select Col3 where Col1 = '""&$AZ76&""'and Col2 = '""&W$21&""'""))))"),"") | G76: =IFERROR(__xludf.DUMMYFUNCTION("IF(G$43="""","""",IF($AZ76="""","""",IFERROR(Query({CarteirasAtivos},""Select Col3 where Col1 = '""&$AZ76&""'and Col2 = '""&X$21&""'""))))"),"") | H76: =IFERROR(__xludf.DUMMYFUNCTION("IF(H$43="""","""",IF($AZ76="""","""",IFERROR(Query({CarteirasAtivos},""Select Col3 where Col1 = '""&$AZ76&""'and Col2 = '""&Y$21&""'""))))"),"") | I76: =IFERROR(__xludf.DUMMYFUNCTION("IF(I$43="""","""",IF($AZ76="""","""",IFERROR(Query({CarteirasAtivos},""Select Col3 where Col1 = '""&$AZ76&""'and Col2 = '""&Z$21&""'""))))"),"") | J76: =IFERROR(__xludf.DUMMYFUNCTION("IF(J$43="""","""",IF($AZ76="""","""",IFERROR(Query({CarteirasAtivos},""Select Col3 where Col1 = '""&$AZ76&""'and Col2 = '""&AA$21&""'""))))"),"") | K76: =IFERROR(__xludf.DUMMYFUNCTION("IF(K$43="""","""",IF($AZ76="""","""",IFERROR(Query({CarteirasAtivos},""Select Col3 where Col1 = '""&$AZ76&""'and Col2 = '""&AB$21&""'""))))"),"") | L76: 33 | W76: =IFERROR(__xludf.DUMMYFUNCTION("IF(M76="""","""",sparkline(IFERROR(BF76*100/MAX($BF$44:$BF$153),0),{""charttype"",""bar"";""max"",100;""color1"",IF(BD76>=0,""#4760a5"",""red"")}))"),"") | AG76: =IFERROR(__xludf.DUMMYFUNCTION("IF($M76="""","""",IFERROR(sparkline(query(GOOGLEFINANCE($AZ76,""price"",TODAY()-$AF$43,TODAY(),1),""select Col2 label Col2 ''""),IF($AG$43=""Gráfico de barras"",{""charttype"",""column"";""highcolor"",""red""},{""chartype"",""line""}))))"),"") | AY76: 33 | BG76: 33 | DL76: 10 | DN76: =IF(DM76="","",IFERROR(SUMIFS(op.daytrade!$P$5:$P343,op.daytrade!$AC$5:$AC343,DM76),0)) | DP76: =COUNTIF(DP67:DP73,"?*")=0 -> TRUE
B77: =IFERROR(__xludf.DUMMYFUNCTION("IF(B$43="""","""",IF($AZ77="""","""",IFERROR(Query({CarteirasAtivos},""Select Col3 where Col1 = '""&$AZ77&""'and Col2 = '""&S$21&""'""))))"),"") | C77: =IFERROR(__xludf.DUMMYFUNCTION("IF(C$43="""","""",IF($AZ77="""","""",IFERROR(Query({CarteirasAtivos},""Select Col3 where Col1 = '""&$AZ77&""'and Col2 = '""&T$21&""'""))))"),"") | D77: =IFERROR(__xludf.DUMMYFUNCTION("IF(D$43="""","""",IF($AZ77="""","""",IFERROR(Query({CarteirasAtivos},""Select Col3 where Col1 = '""&$AZ77&""'and Col2 = '""&U$21&""'""))))"),"") | E77: =IFERROR(__xludf.DUMMYFUNCTION("IF(E$43="""","""",IF($AZ77="""","""",IFERROR(Query({CarteirasAtivos},""Select Col3 where Col1 = '""&$AZ77&""'and Col2 = '""&V$21&""'""))))"),"") | F77: =IFERROR(__xludf.DUMMYFUNCTION("IF(F$43="""","""",IF($AZ77="""","""",IFERROR(Query({CarteirasAtivos},""Select Col3 where Col1 = '""&$AZ77&""'and Col2 = '""&W$21&""'""))))"),"") | G77: =IFERROR(__xludf.DUMMYFUNCTION("IF(G$43="""","""",IF($AZ77="""","""",IFERROR(Query({CarteirasAtivos},""Select Col3 where Col1 = '""&$AZ77&""'and Col2 = '""&X$21&""'""))))"),"") | H77: =IFERROR(__xludf.DUMMYFUNCTION("IF(H$43="""","""",IF($AZ77="""","""",IFERROR(Query({CarteirasAtivos},""Select Col3 where Col1 = '""&$AZ77&""'and Col2 = '""&Y$21&""'""))))"),"") | I77: =IFERROR(__xludf.DUMMYFUNCTION("IF(I$43="""","""",IF($AZ77="""","""",IFERROR(Query({CarteirasAtivos},""Select Col3 where Col1 = '""&$AZ77&""'and Col2 = '""&Z$21&""'""))))"),"") | J77: =IFERROR(__xludf.DUMMYFUNCTION("IF(J$43="""","""",IF($AZ77="""","""",IFERROR(Query({CarteirasAtivos},""Select Col3 where Col1 = '""&$AZ77&""'and Col2 = '""&AA$21&""'""))))"),"") | K77: =IFERROR(__xludf.DUMMYFUNCTION("IF(K$43="""","""",IF($AZ77="""","""",IFERROR(Query({CarteirasAtivos},""Select Col3 where Col1 = '""&$AZ77&""'and Col2 = '""&AB$21&""'""))))"),"") | L77: 34 | W77: =IFERROR(__xludf.DUMMYFUNCTION("IF(M77="""","""",sparkline(IFERROR(BF77*100/MAX($BF$44:$BF$153),0),{""charttype"",""bar"";""max"",100;""color1"",IF(BD77>=0,""#4760a5"",""red"")}))"),"") | AG77: =IFERROR(__xludf.DUMMYFUNCTION("IF($M77="""","""",IFERROR(sparkline(query(GOOGLEFINANCE($AZ77,""price"",TODAY()-$AF$43,TODAY(),1),""select Col2 label Col2 ''""),IF($AG$43=""Gráfico de barras"",{""charttype"",""column"";""highcolor"",""red""},{""chartype"",""line""}))))"),"") | AY77: 34 | BG77: 34 | BP77: INDICADORES | BR77: =today() -> 46092 | BS77: =IF(WEEKDAY(BR77)=7,1,IF(WEEKDAY(BR77)=1,2,0)) -> 0 | BT77: Fator FX | BU77: Changepct_fx | DL77: 11 | DN77: =IF(DM77="","",IFERROR(SUMIFS(op.daytrade!$P$5:$P343,op.daytrade!$AC$5:$AC343,DM77),0))
B78: =IFERROR(__xludf.DUMMYFUNCTION("IF(B$43="""","""",IF($AZ78="""","""",IFERROR(Query({CarteirasAtivos},""Select Col3 where Col1 = '""&$AZ78&""'and Col2 = '""&S$21&""'""))))"),"") | C78: =IFERROR(__xludf.DUMMYFUNCTION("IF(C$43="""","""",IF($AZ78="""","""",IFERROR(Query({CarteirasAtivos},""Select Col3 where Col1 = '""&$AZ78&""'and Col2 = '""&T$21&""'""))))"),"") | D78: =IFERROR(__xludf.DUMMYFUNCTION("IF(D$43="""","""",IF($AZ78="""","""",IFERROR(Query({CarteirasAtivos},""Select Col3 where Col1 = '""&$AZ78&""'and Col2 = '""&U$21&""'""))))"),"") | E78: =IFERROR(__xludf.DUMMYFUNCTION("IF(E$43="""","""",IF($AZ78="""","""",IFERROR(Query({CarteirasAtivos},""Select Col3 where Col1 = '""&$AZ78&""'and Col2 = '""&V$21&""'""))))"),"") | F78: =IFERROR(__xludf.DUMMYFUNCTION("IF(F$43="""","""",IF($AZ78="""","""",IFERROR(Query({CarteirasAtivos},""Select Col3 where Col1 = '""&$AZ78&""'and Col2 = '""&W$21&""'""))))"),"") | G78: =IFERROR(__xludf.DUMMYFUNCTION("IF(G$43="""","""",IF($AZ78="""","""",IFERROR(Query({CarteirasAtivos},""Select Col3 where Col1 = '""&$AZ78&""'and Col2 = '""&X$21&""'""))))"),"") | H78: =IFERROR(__xludf.DUMMYFUNCTION("IF(H$43="""","""",IF($AZ78="""","""",IFERROR(Query({CarteirasAtivos},""Select Col3 where Col1 = '""&$AZ78&""'and Col2 = '""&Y$21&""'""))))"),"") | I78: =IFERROR(__xludf.DUMMYFUNCTION("IF(I$43="""","""",IF($AZ78="""","""",IFERROR(Query({CarteirasAtivos},""Select Col3 where Col1 = '""&$AZ78&""'and Col2 = '""&Z$21&""'""))))"),"") | J78: =IFERROR(__xludf.DUMMYFUNCTION("IF(J$43="""","""",IF($AZ78="""","""",IFERROR(Query({CarteirasAtivos},""Select Col3 where Col1 = '""&$AZ78&""'and Col2 = '""&AA$21&""'""))))"),"") | K78: =IFERROR(__xludf.DUMMYFUNCTION("IF(K$43="""","""",IF($AZ78="""","""",IFERROR(Query({CarteirasAtivos},""Select Col3 where Col1 = '""&$AZ78&""'and Col2 = '""&AB$21&""'""))))"),"") | L78: 35 | W78: =IFERROR(__xludf.DUMMYFUNCTION("IF(M78="""","""",sparkline(IFERROR(BF78*100/MAX($BF$44:$BF$153),0),{""charttype"",""bar"";""max"",100;""color1"",IF(BD78>=0,""#4760a5"",""red"")}))"),"") | AG78: =IFERROR(__xludf.DUMMYFUNCTION("IF($M78="""","""",IFERROR(sparkline(query(GOOGLEFINANCE($AZ78,""price"",TODAY()-$AF$43,TODAY(),1),""select Col2 label Col2 ''""),IF($AG$43=""Gráfico de barras"",{""charttype"",""column"";""highcolor"",""red""},{""chartype"",""line""}))))"),"") | AY78: 35 | BG78: 35 | BT78: BRLUSD | BU78: BRLUSD | DL78: 12 | DN78: =IF(DM78="","",IFERROR(SUMIFS(op.daytrade!$P$5:$P343,op.daytrade!$AC$5:$AC343,DM78),0))
B79: =IFERROR(__xludf.DUMMYFUNCTION("IF(B$43="""","""",IF($AZ79="""","""",IFERROR(Query({CarteirasAtivos},""Select Col3 where Col1 = '""&$AZ79&""'and Col2 = '""&S$21&""'""))))"),"") | C79: =IFERROR(__xludf.DUMMYFUNCTION("IF(C$43="""","""",IF($AZ79="""","""",IFERROR(Query({CarteirasAtivos},""Select Col3 where Col1 = '""&$AZ79&""'and Col2 = '""&T$21&""'""))))"),"") | D79: =IFERROR(__xludf.DUMMYFUNCTION("IF(D$43="""","""",IF($AZ79="""","""",IFERROR(Query({CarteirasAtivos},""Select Col3 where Col1 = '""&$AZ79&""'and Col2 = '""&U$21&""'""))))"),"") | E79: =IFERROR(__xludf.DUMMYFUNCTION("IF(E$43="""","""",IF($AZ79="""","""",IFERROR(Query({CarteirasAtivos},""Select Col3 where Col1 = '""&$AZ79&""'and Col2 = '""&V$21&""'""))))"),"") | F79: =IFERROR(__xludf.DUMMYFUNCTION("IF(F$43="""","""",IF($AZ79="""","""",IFERROR(Query({CarteirasAtivos},""Select Col3 where Col1 = '""&$AZ79&""'and Col2 = '""&W$21&""'""))))"),"") | G79: =IFERROR(__xludf.DUMMYFUNCTION("IF(G$43="""","""",IF($AZ79="""","""",IFERROR(Query({CarteirasAtivos},""Select Col3 where Col1 = '""&$AZ79&""'and Col2 = '""&X$21&""'""))))"),"") | H79: =IFERROR(__xludf.DUMMYFUNCTION("IF(H$43="""","""",IF($AZ79="""","""",IFERROR(Query({CarteirasAtivos},""Select Col3 where Col1 = '""&$AZ79&""'and Col2 = '""&Y$21&""'""))))"),"") | I79: =IFERROR(__xludf.DUMMYFUNCTION("IF(I$43="""","""",IF($AZ79="""","""",IFERROR(Query({CarteirasAtivos},""Select Col3 where Col1 = '""&$AZ79&""'and Col2 = '""&Z$21&""'""))))"),"") | J79: =IFERROR(__xludf.DUMMYFUNCTION("IF(J$43="""","""",IF($AZ79="""","""",IFERROR(Query({CarteirasAtivos},""Select Col3 where Col1 = '""&$AZ79&""'and Col2 = '""&AA$21&""'""))))"),"") | K79: =IFERROR(__xludf.DUMMYFUNCTION("IF(K$43="""","""",IF($AZ79="""","""",IFERROR(Query({CarteirasAtivos},""Select Col3 where Col1 = '""&$AZ79&""'and Col2 = '""&AB$21&""'""))))"),"") | L79: 36 | W79: =IFERROR(__xludf.DUMMYFUNCTION("IF(M79="""","""",sparkline(IFERROR(BF79*100/MAX($BF$44:$BF$153),0),{""charttype"",""bar"";""max"",100;""color1"",IF(BD79>=0,""#4760a5"",""red"")}))"),"") | AG79: =IFERROR(__xludf.DUMMYFUNCTION("IF($M79="""","""",IFERROR(sparkline(query(GOOGLEFINANCE($AZ79,""price"",TODAY()-$AF$43,TODAY(),1),""select Col2 label Col2 ''""),IF($AG$43=""Gráfico de barras"",{""charttype"",""column"";""highcolor"",""red""},{""chartype"",""line""}))))"),"") | AY79: 36 | BG79: 36 | BP79: INDICADOR | BQ79: PRICE | BR79: CHANGE | BS79: CHANGEPCT | BT79: =IFERROR(__xludf.DUMMYFUNCTION("googlefinance(""BRLUSD"")"),0.1925743) -> 0.1925743 | BU79: =IFERROR(__xludf.DUMMYFUNCTION("IFERROR(INDEX(SORT(GOOGLEFINANCE(""BRLUSD"",""price"",TODAY()-3,TODAY(),1),1,0),2,2),BT79)"),0.1936521) -> 0.1936521 | DL79: 13 | DN79: =IF(DM79="","",IFERROR(SUMIFS(op.daytrade!$P$5:$P343,op.daytrade!$AC$5:$AC343,DM79),0))
B80: =IFERROR(__xludf.DUMMYFUNCTION("IF(B$43="""","""",IF($AZ80="""","""",IFERROR(Query({CarteirasAtivos},""Select Col3 where Col1 = '""&$AZ80&""'and Col2 = '""&S$21&""'""))))"),"") | C80: =IFERROR(__xludf.DUMMYFUNCTION("IF(C$43="""","""",IF($AZ80="""","""",IFERROR(Query({CarteirasAtivos},""Select Col3 where Col1 = '""&$AZ80&""'and Col2 = '""&T$21&""'""))))"),"") | D80: =IFERROR(__xludf.DUMMYFUNCTION("IF(D$43="""","""",IF($AZ80="""","""",IFERROR(Query({CarteirasAtivos},""Select Col3 where Col1 = '""&$AZ80&""'and Col2 = '""&U$21&""'""))))"),"") | E80: =IFERROR(__xludf.DUMMYFUNCTION("IF(E$43="""","""",IF($AZ80="""","""",IFERROR(Query({CarteirasAtivos},""Select Col3 where Col1 = '""&$AZ80&""'and Col2 = '""&V$21&""'""))))"),"") | F80: =IFERROR(__xludf.DUMMYFUNCTION("IF(F$43="""","""",IF($AZ80="""","""",IFERROR(Query({CarteirasAtivos},""Select Col3 where Col1 = '""&$AZ80&""'and Col2 = '""&W$21&""'""))))"),"") | G80: =IFERROR(__xludf.DUMMYFUNCTION("IF(G$43="""","""",IF($AZ80="""","""",IFERROR(Query({CarteirasAtivos},""Select Col3 where Col1 = '""&$AZ80&""'and Col2 = '""&X$21&""'""))))"),"") | H80: =IFERROR(__xludf.DUMMYFUNCTION("IF(H$43="""","""",IF($AZ80="""","""",IFERROR(Query({CarteirasAtivos},""Select Col3 where Col1 = '""&$AZ80&""'and Col2 = '""&Y$21&""'""))))"),"") | I80: =IFERROR(__xludf.DUMMYFUNCTION("IF(I$43="""","""",IF($AZ80="""","""",IFERROR(Query({CarteirasAtivos},""Select Col3 where Col1 = '""&$AZ80&""'and Col2 = '""&Z$21&""'""))))"),"") | J80: =IFERROR(__xludf.DUMMYFUNCTION("IF(J$43="""","""",IF($AZ80="""","""",IFERROR(Query({CarteirasAtivos},""Select Col3 where Col1 = '""&$AZ80&""'and Col2 = '""&AA$21&""'""))))"),"") | K80: =IFERROR(__xludf.DUMMYFUNCTION("IF(K$43="""","""",IF($AZ80="""","""",IFERROR(Query({CarteirasAtivos},""Select Col3 where Col1 = '""&$AZ80&""'and Col2 = '""&AB$21&""'""))))"),"") | L80: 37 | W80: =IFERROR(__xludf.DUMMYFUNCTION("IF(M80="""","""",sparkline(IFERROR(BF80*100/MAX($BF$44:$BF$153),0),{""charttype"",""bar"";""max"",100;""color1"",IF(BD80>=0,""#4760a5"",""red"")}))"),"") | AG80: =IFERROR(__xludf.DUMMYFUNCTION("IF($M80="""","""",IFERROR(sparkline(query(GOOGLEFINANCE($AZ80,""price"",TODAY()-$AF$43,TODAY(),1),""select Col2 label Col2 ''""),IF($AG$43=""Gráfico de barras"",{""charttype"",""column"";""highcolor"",""red""},{""chartype"",""line""}))))"),"") | AY80: 37 | BG80: 37 | BP80: IBOV | BQ80: =IFERROR(__xludf.DUMMYFUNCTION("IF(NOT(ConfigOn),"""",googlefinance(""INDEXBVMF:""&$BP80,BQ$79))"),183969.34) -> 183969.34 | BR80: =IFERROR(__xludf.DUMMYFUNCTION("IF(NOT(ConfigOn),"""",googlefinance(""INDEXBVMF:""&$BP80,BR$79))"),522.34) -> 522.34 | BS80: =IFERROR(__xludf.DUMMYFUNCTION("IF(NOT(ConfigOn),"""",googlefinance(""INDEXBVMF:""&$BP80,BS$79))"),0.28) -> 0.28 | BT80: BRLUSD | BU80: BRLUSD | DL80: 14 | DN80: =IF(DM80="","",IFERROR(SUMIFS(op.daytrade!$P$5:$P343,op.daytrade!$AC$5:$AC343,DM80),0))
B81: =IFERROR(__xludf.DUMMYFUNCTION("IF(B$43="""","""",IF($AZ81="""","""",IFERROR(Query({CarteirasAtivos},""Select Col3 where Col1 = '""&$AZ81&""'and Col2 = '""&S$21&""'""))))"),"") | C81: =IFERROR(__xludf.DUMMYFUNCTION("IF(C$43="""","""",IF($AZ81="""","""",IFERROR(Query({CarteirasAtivos},""Select Col3 where Col1 = '""&$AZ81&""'and Col2 = '""&T$21&""'""))))"),"") | D81: =IFERROR(__xludf.DUMMYFUNCTION("IF(D$43="""","""",IF($AZ81="""","""",IFERROR(Query({CarteirasAtivos},""Select Col3 where Col1 = '""&$AZ81&""'and Col2 = '""&U$21&""'""))))"),"") | E81: =IFERROR(__xludf.DUMMYFUNCTION("IF(E$43="""","""",IF($AZ81="""","""",IFERROR(Query({CarteirasAtivos},""Select Col3 where Col1 = '""&$AZ81&""'and Col2 = '""&V$21&""'""))))"),"") | F81: =IFERROR(__xludf.DUMMYFUNCTION("IF(F$43="""","""",IF($AZ81="""","""",IFERROR(Query({CarteirasAtivos},""Select Col3 where Col1 = '""&$AZ81&""'and Col2 = '""&W$21&""'""))))"),"") | G81: =IFERROR(__xludf.DUMMYFUNCTION("IF(G$43="""","""",IF($AZ81="""","""",IFERROR(Query({CarteirasAtivos},""Select Col3 where Col1 = '""&$AZ81&""'and Col2 = '""&X$21&""'""))))"),"") | H81: =IFERROR(__xludf.DUMMYFUNCTION("IF(H$43="""","""",IF($AZ81="""","""",IFERROR(Query({CarteirasAtivos},""Select Col3 where Col1 = '""&$AZ81&""'and Col2 = '""&Y$21&""'""))))"),"") | I81: =IFERROR(__xludf.DUMMYFUNCTION("IF(I$43="""","""",IF($AZ81="""","""",IFERROR(Query({CarteirasAtivos},""Select Col3 where Col1 = '""&$AZ81&""'and Col2 = '""&Z$21&""'""))))"),"") | J81: =IFERROR(__xludf.DUMMYFUNCTION("IF(J$43="""","""",IF($AZ81="""","""",IFERROR(Query({CarteirasAtivos},""Select Col3 where Col1 = '""&$AZ81&""'and Col2 = '""&AA$21&""'""))))"),"") | K81: =IFERROR(__xludf.DUMMYFUNCTION("IF(K$43="""","""",IF($AZ81="""","""",IFERROR(Query({CarteirasAtivos},""Select Col3 where Col1 = '""&$AZ81&""'and Col2 = '""&AB$21&""'""))))"),"") | L81: 38 | W81: =IFERROR(__xludf.DUMMYFUNCTION("IF(M81="""","""",sparkline(IFERROR(BF81*100/MAX($BF$44:$BF$153),0),{""charttype"",""bar"";""max"",100;""color1"",IF(BD81>=0,""#4760a5"",""red"")}))"),"") | AG81: =IFERROR(__xludf.DUMMYFUNCTION("IF($M81="""","""",IFERROR(sparkline(query(GOOGLEFINANCE($AZ81,""price"",TODAY()-$AF$43,TODAY(),1),""select Col2 label Col2 ''""),IF($AG$43=""Gráfico de barras"",{""charttype"",""column"";""highcolor"",""red""},{""chartype"",""line""}))))"),"") | AY81: 38 | BG81: 38 | BP81: IFIX | BQ81: =IFERROR(__xludf.DUMMYFUNCTION("IF(NOT(ConfigOn),"""",googlefinance(""INDEXBVMF:""&$BP81,BQ$79))"),3873.59) -> 3873.59 | BR81: =IFERROR(__xludf.DUMMYFUNCTION("IF(NOT(ConfigOn),"""",googlefinance(""INDEXBVMF:""&$BP81,BR$79))"),-2.86) -> -2.86 | BS81: =IFERROR(__xludf.DUMMYFUNCTION("IF(NOT(ConfigOn),"""",googlefinance(""INDEXBVMF:""&$BP81,BS$79))"),-0.07) -> -0.07 | BT81: =IFERROR(__xludf.DUMMYFUNCTION("googlefinance(""USDBRL"")"),5.19280091) -> 5.1928009 | BU81: =IFERROR(__xludf.DUMMYFUNCTION("IFERROR(INDEX(SORT(GOOGLEFINANCE(""USDBRL"",""price"",TODAY()-3,TODAY(),1),1,0),2,2),BT81)"),5.1639) -> 5.1639 | DL81: 15 | DN81: =IF(DM81="","",IFERROR(SUMIFS(op.daytrade!$P$5:$P343,op.daytrade!$AC$5:$AC343,DM81),0))
B82: =IFERROR(__xludf.DUMMYFUNCTION("IF(B$43="""","""",IF($AZ82="""","""",IFERROR(Query({CarteirasAtivos},""Select Col3 where Col1 = '""&$AZ82&""'and Col2 = '""&S$21&""'""))))"),"") | C82: =IFERROR(__xludf.DUMMYFUNCTION("IF(C$43="""","""",IF($AZ82="""","""",IFERROR(Query({CarteirasAtivos},""Select Col3 where Col1 = '""&$AZ82&""'and Col2 = '""&T$21&""'""))))"),"") | D82: =IFERROR(__xludf.DUMMYFUNCTION("IF(D$43="""","""",IF($AZ82="""","""",IFERROR(Query({CarteirasAtivos},""Select Col3 where Col1 = '""&$AZ82&""'and Col2 = '""&U$21&""'""))))"),"") | E82: =IFERROR(__xludf.DUMMYFUNCTION("IF(E$43="""","""",IF($AZ82="""","""",IFERROR(Query({CarteirasAtivos},""Select Col3 where Col1 = '""&$AZ82&""'and Col2 = '""&V$21&""'""))))"),"") | F82: =IFERROR(__xludf.DUMMYFUNCTION("IF(F$43="""","""",IF($AZ82="""","""",IFERROR(Query({CarteirasAtivos},""Select Col3 where Col1 = '""&$AZ82&""'and Col2 = '""&W$21&""'""))))"),"") | G82: =IFERROR(__xludf.DUMMYFUNCTION("IF(G$43="""","""",IF($AZ82="""","""",IFERROR(Query({CarteirasAtivos},""Select Col3 where Col1 = '""&$AZ82&""'and Col2 = '""&X$21&""'""))))"),"") | H82: =IFERROR(__xludf.DUMMYFUNCTION("IF(H$43="""","""",IF($AZ82="""","""",IFERROR(Query({CarteirasAtivos},""Select Col3 where Col1 = '""&$AZ82&""'and Col2 = '""&Y$21&""'""))))"),"") | I82: =IFERROR(__xludf.DUMMYFUNCTION("IF(I$43="""","""",IF($AZ82="""","""",IFERROR(Query({CarteirasAtivos},""Select Col3 where Col1 = '""&$AZ82&""'and Col2 = '""&Z$21&""'""))))"),"") | J82: =IFERROR(__xludf.DUMMYFUNCTION("IF(J$43="""","""",IF($AZ82="""","""",IFERROR(Query({CarteirasAtivos},""Select Col3 where Col1 = '""&$AZ82&""'and Col2 = '""&AA$21&""'""))))"),"") | K82: =IFERROR(__xludf.DUMMYFUNCTION("IF(K$43="""","""",IF($AZ82="""","""",IFERROR(Query({CarteirasAtivos},""Select Col3 where Col1 = '""&$AZ82&""'and Col2 = '""&AB$21&""'""))))"),"") | L82: 39 | W82: =IFERROR(__xludf.DUMMYFUNCTION("IF(M82="""","""",sparkline(IFERROR(BF82*100/MAX($BF$44:$BF$153),0),{""charttype"",""bar"";""max"",100;""color1"",IF(BD82>=0,""#4760a5"",""red"")}))"),"") | AG82: =IFERROR(__xludf.DUMMYFUNCTION("IF($M82="""","""",IFERROR(sparkline(query(GOOGLEFINANCE($AZ82,""price"",TODAY()-$AF$43,TODAY(),1),""select Col2 label Col2 ''""),IF($AG$43=""Gráfico de barras"",{""charttype"",""column"";""highcolor"",""red""},{""chartype"",""line""}))))"),"") | AY82: 39 | BG82: 39 | DL82: 16 | DN82: =IF(DM82="","",IFERROR(SUMIFS(op.daytrade!$P$5:$P343,op.daytrade!$AC$5:$AC343,DM82),0))
B83: =IFERROR(__xludf.DUMMYFUNCTION("IF(B$43="""","""",IF($AZ83="""","""",IFERROR(Query({CarteirasAtivos},""Select Col3 where Col1 = '""&$AZ83&""'and Col2 = '""&S$21&""'""))))"),"") | C83: =IFERROR(__xludf.DUMMYFUNCTION("IF(C$43="""","""",IF($AZ83="""","""",IFERROR(Query({CarteirasAtivos},""Select Col3 where Col1 = '""&$AZ83&""'and Col2 = '""&T$21&""'""))))"),"") | D83: =IFERROR(__xludf.DUMMYFUNCTION("IF(D$43="""","""",IF($AZ83="""","""",IFERROR(Query({CarteirasAtivos},""Select Col3 where Col1 = '""&$AZ83&""'and Col2 = '""&U$21&""'""))))"),"") | E83: =IFERROR(__xludf.DUMMYFUNCTION("IF(E$43="""","""",IF($AZ83="""","""",IFERROR(Query({CarteirasAtivos},""Select Col3 where Col1 = '""&$AZ83&""'and Col2 = '""&V$21&""'""))))"),"") | F83: =IFERROR(__xludf.DUMMYFUNCTION("IF(F$43="""","""",IF($AZ83="""","""",IFERROR(Query({CarteirasAtivos},""Select Col3 where Col1 = '""&$AZ83&""'and Col2 = '""&W$21&""'""))))"),"") | G83: =IFERROR(__xludf.DUMMYFUNCTION("IF(G$43="""","""",IF($AZ83="""","""",IFERROR(Query({CarteirasAtivos},""Select Col3 where Col1 = '""&$AZ83&""'and Col2 = '""&X$21&""'""))))"),"") | H83: =IFERROR(__xludf.DUMMYFUNCTION("IF(H$43="""","""",IF($AZ83="""","""",IFERROR(Query({CarteirasAtivos},""Select Col3 where Col1 = '""&$AZ83&""'and Col2 = '""&Y$21&""'""))))"),"") | I83: =IFERROR(__xludf.DUMMYFUNCTION("IF(I$43="""","""",IF($AZ83="""","""",IFERROR(Query({CarteirasAtivos},""Select Col3 where Col1 = '""&$AZ83&""'and Col2 = '""&Z$21&""'""))))"),"") | J83: =IFERROR(__xludf.DUMMYFUNCTION("IF(J$43="""","""",IF($AZ83="""","""",IFERROR(Query({CarteirasAtivos},""Select Col3 where Col1 = '""&$AZ83&""'and Col2 = '""&AA$21&""'""))))"),"") | K83: =IFERROR(__xludf.DUMMYFUNCTION("IF(K$43="""","""",IF($AZ83="""","""",IFERROR(Query({CarteirasAtivos},""Select Col3 where Col1 = '""&$AZ83&""'and Col2 = '""&AB$21&""'""))))"),"") | L83: 40 | W83: =IFERROR(__xludf.DUMMYFUNCTION("IF(M83="""","""",sparkline(IFERROR(BF83*100/MAX($BF$44:$BF$153),0),{""charttype"",""bar"";""max"",100;""color1"",IF(BD83>=0,""#4760a5"",""red"")}))"),"") | AG83: =IFERROR(__xludf.DUMMYFUNCTION("IF($M83="""","""",IFERROR(sparkline(query(GOOGLEFINANCE($AZ83,""price"",TODAY()-$AF$43,TODAY(),1),""select Col2 label Col2 ''""),IF($AG$43=""Gráfico de barras"",{""charttype"",""column"";""highcolor"",""red""},{""chartype"",""line""}))))"),"") | AY83: 40 | BG83: 40 | BP83: IBOV | BQ83: =COUNTA(BQ86:BQ98)-2 -> 10 | DL83: 17 | DN83: =IF(DM83="","",IFERROR(SUMIFS(op.daytrade!$P$5:$P343,op.daytrade!$AC$5:$AC343,DM83),0))
B84: =IFERROR(__xludf.DUMMYFUNCTION("IF(B$43="""","""",IF($AZ84="""","""",IFERROR(Query({CarteirasAtivos},""Select Col3 where Col1 = '""&$AZ84&""'and Col2 = '""&S$21&""'""))))"),"") | C84: =IFERROR(__xludf.DUMMYFUNCTION("IF(C$43="""","""",IF($AZ84="""","""",IFERROR(Query({CarteirasAtivos},""Select Col3 where Col1 = '""&$AZ84&""'and Col2 = '""&T$21&""'""))))"),"") | D84: =IFERROR(__xludf.DUMMYFUNCTION("IF(D$43="""","""",IF($AZ84="""","""",IFERROR(Query({CarteirasAtivos},""Select Col3 where Col1 = '""&$AZ84&""'and Col2 = '""&U$21&""'""))))"),"") | E84: =IFERROR(__xludf.DUMMYFUNCTION("IF(E$43="""","""",IF($AZ84="""","""",IFERROR(Query({CarteirasAtivos},""Select Col3 where Col1 = '""&$AZ84&""'and Col2 = '""&V$21&""'""))))"),"") | F84: =IFERROR(__xludf.DUMMYFUNCTION("IF(F$43="""","""",IF($AZ84="""","""",IFERROR(Query({CarteirasAtivos},""Select Col3 where Col1 = '""&$AZ84&""'and Col2 = '""&W$21&""'""))))"),"") | G84: =IFERROR(__xludf.DUMMYFUNCTION("IF(G$43="""","""",IF($AZ84="""","""",IFERROR(Query({CarteirasAtivos},""Select Col3 where Col1 = '""&$AZ84&""'and Col2 = '""&X$21&""'""))))"),"") | H84: =IFERROR(__xludf.DUMMYFUNCTION("IF(H$43="""","""",IF($AZ84="""","""",IFERROR(Query({CarteirasAtivos},""Select Col3 where Col1 = '""&$AZ84&""'and Col2 = '""&Y$21&""'""))))"),"") | I84: =IFERROR(__xludf.DUMMYFUNCTION("IF(I$43="""","""",IF($AZ84="""","""",IFERROR(Query({CarteirasAtivos},""Select Col3 where Col1 = '""&$AZ84&""'and Col2 = '""&Z$21&""'""))))"),"") | J84: =IFERROR(__xludf.DUMMYFUNCTION("IF(J$43="""","""",IF($AZ84="""","""",IFERROR(Query({CarteirasAtivos},""Select Col3 where Col1 = '""&$AZ84&""'and Col2 = '""&AA$21&""'""))))"),"") | K84: =IFERROR(__xludf.DUMMYFUNCTION("IF(K$43="""","""",IF($AZ84="""","""",IFERROR(Query({CarteirasAtivos},""Select Col3 where Col1 = '""&$AZ84&""'and Col2 = '""&AB$21&""'""))))"),"") | L84: 41 | W84: =IFERROR(__xludf.DUMMYFUNCTION("IF(M84="""","""",sparkline(IFERROR(BF84*100/MAX($BF$44:$BF$153),0),{""charttype"",""bar"";""max"",100;""color1"",IF(BD84>=0,""#4760a5"",""red"")}))"),"") | AG84: =IFERROR(__xludf.DUMMYFUNCTION("IF($M84="""","""",IFERROR(sparkline(query(GOOGLEFINANCE($AZ84,""price"",TODAY()-$AF$43,TODAY(),1),""select Col2 label Col2 ''""),IF($AG$43=""Gráfico de barras"",{""charttype"",""column"";""highcolor"",""red""},{""chartype"",""line""}))))"),"") | AY84: 41 | BG84: 41 | DL84: 18 | DN84: =IF(DM84="","",IFERROR(SUMIFS(op.daytrade!$P$5:$P343,op.daytrade!$AC$5:$AC343,DM84),0))
B85: =IFERROR(__xludf.DUMMYFUNCTION("IF(B$43="""","""",IF($AZ85="""","""",IFERROR(Query({CarteirasAtivos},""Select Col3 where Col1 = '""&$AZ85&""'and Col2 = '""&S$21&""'""))))"),"") | C85: =IFERROR(__xludf.DUMMYFUNCTION("IF(C$43="""","""",IF($AZ85="""","""",IFERROR(Query({CarteirasAtivos},""Select Col3 where Col1 = '""&$AZ85&""'and Col2 = '""&T$21&""'""))))"),"") | D85: =IFERROR(__xludf.DUMMYFUNCTION("IF(D$43="""","""",IF($AZ85="""","""",IFERROR(Query({CarteirasAtivos},""Select Col3 where Col1 = '""&$AZ85&""'and Col2 = '""&U$21&""'""))))"),"") | E85: =IFERROR(__xludf.DUMMYFUNCTION("IF(E$43="""","""",IF($AZ85="""","""",IFERROR(Query({CarteirasAtivos},""Select Col3 where Col1 = '""&$AZ85&""'and Col2 = '""&V$21&""'""))))"),"") | F85: =IFERROR(__xludf.DUMMYFUNCTION("IF(F$43="""","""",IF($AZ85="""","""",IFERROR(Query({CarteirasAtivos},""Select Col3 where Col1 = '""&$AZ85&""'and Col2 = '""&W$21&""'""))))"),"") | G85: =IFERROR(__xludf.DUMMYFUNCTION("IF(G$43="""","""",IF($AZ85="""","""",IFERROR(Query({CarteirasAtivos},""Select Col3 where Col1 = '""&$AZ85&""'and Col2 = '""&X$21&""'""))))"),"") | H85: =IFERROR(__xludf.DUMMYFUNCTION("IF(H$43="""","""",IF($AZ85="""","""",IFERROR(Query({CarteirasAtivos},""Select Col3 where Col1 = '""&$AZ85&""'and Col2 = '""&Y$21&""'""))))"),"") | I85: =IFERROR(__xludf.DUMMYFUNCTION("IF(I$43="""","""",IF($AZ85="""","""",IFERROR(Query({CarteirasAtivos},""Select Col3 where Col1 = '""&$AZ85&""'and Col2 = '""&Z$21&""'""))))"),"") | J85: =IFERROR(__xludf.DUMMYFUNCTION("IF(J$43="""","""",IF($AZ85="""","""",IFERROR(Query({CarteirasAtivos},""Select Col3 where Col1 = '""&$AZ85&""'and Col2 = '""&AA$21&""'""))))"),"") | K85: =IFERROR(__xludf.DUMMYFUNCTION("IF(K$43="""","""",IF($AZ85="""","""",IFERROR(Query({CarteirasAtivos},""Select Col3 where Col1 = '""&$AZ85&""'and Col2 = '""&AB$21&""'""))))"),"") | L85: 42 | W85: =IFERROR(__xludf.DUMMYFUNCTION("IF(M85="""","""",sparkline(IFERROR(BF85*100/MAX($BF$44:$BF$153),0),{""charttype"",""bar"";""max"",100;""color1"",IF(BD85>=0,""#4760a5"",""red"")}))"),"") | AG85: =IFERROR(__xludf.DUMMYFUNCTION("IF($M85="""","""",IFERROR(sparkline(query(GOOGLEFINANCE($AZ85,""price"",TODAY()-$AF$43,TODAY(),1),""select Col2 label Col2 ''""),IF($AG$43=""Gráfico de barras"",{""charttype"",""column"";""highcolor"",""red""},{""chartype"",""line""}))))"),"") | AY85: 42 | BG85: 42 | BP85: semana | BQ85: data | BR85: price | BS85: change | BT85: changepct | BU85: grafico | DL85: 19 | DN85: =IF(DM85="","",IFERROR(SUMIFS(op.daytrade!$P$5:$P343,op.daytrade!$AC$5:$AC343,DM85),0))
B86: =IFERROR(__xludf.DUMMYFUNCTION("IF(B$43="""","""",IF($AZ86="""","""",IFERROR(Query({CarteirasAtivos},""Select Col3 where Col1 = '""&$AZ86&""'and Col2 = '""&S$21&""'""))))"),"") | C86: =IFERROR(__xludf.DUMMYFUNCTION("IF(C$43="""","""",IF($AZ86="""","""",IFERROR(Query({CarteirasAtivos},""Select Col3 where Col1 = '""&$AZ86&""'and Col2 = '""&T$21&""'""))))"),"") | D86: =IFERROR(__xludf.DUMMYFUNCTION("IF(D$43="""","""",IF($AZ86="""","""",IFERROR(Query({CarteirasAtivos},""Select Col3 where Col1 = '""&$AZ86&""'and Col2 = '""&U$21&""'""))))"),"") | E86: =IFERROR(__xludf.DUMMYFUNCTION("IF(E$43="""","""",IF($AZ86="""","""",IFERROR(Query({CarteirasAtivos},""Select Col3 where Col1 = '""&$AZ86&""'and Col2 = '""&V$21&""'""))))"),"") | F86: =IFERROR(__xludf.DUMMYFUNCTION("IF(F$43="""","""",IF($AZ86="""","""",IFERROR(Query({CarteirasAtivos},""Select Col3 where Col1 = '""&$AZ86&""'and Col2 = '""&W$21&""'""))))"),"") | G86: =IFERROR(__xludf.DUMMYFUNCTION("IF(G$43="""","""",IF($AZ86="""","""",IFERROR(Query({CarteirasAtivos},""Select Col3 where Col1 = '""&$AZ86&""'and Col2 = '""&X$21&""'""))))"),"") | H86: =IFERROR(__xludf.DUMMYFUNCTION("IF(H$43="""","""",IF($AZ86="""","""",IFERROR(Query({CarteirasAtivos},""Select Col3 where Col1 = '""&$AZ86&""'and Col2 = '""&Y$21&""'""))))"),"") | I86: =IFERROR(__xludf.DUMMYFUNCTION("IF(I$43="""","""",IF($AZ86="""","""",IFERROR(Query({CarteirasAtivos},""Select Col3 where Col1 = '""&$AZ86&""'and Col2 = '""&Z$21&""'""))))"),"") | J86: =IFERROR(__xludf.DUMMYFUNCTION("IF(J$43="""","""",IF($AZ86="""","""",IFERROR(Query({CarteirasAtivos},""Select Col3 where Col1 = '""&$AZ86&""'and Col2 = '""&AA$21&""'""))))"),"") | K86: =IFERROR(__xludf.DUMMYFUNCTION("IF(K$43="""","""",IF($AZ86="""","""",IFERROR(Query({CarteirasAtivos},""Select Col3 where Col1 = '""&$AZ86&""'and Col2 = '""&AB$21&""'""))))"),"") | L86: 43 | W86: =IFERROR(__xludf.DUMMYFUNCTION("IF(M86="""","""",sparkline(IFERROR(BF86*100/MAX($BF$44:$BF$153),0),{""charttype"",""bar"";""max"",100;""color1"",IF(BD86>=0,""#4760a5"",""red"")}))"),"") | AG86: =IFERROR(__xludf.DUMMYFUNCTION("IF($M86="""","""",IFERROR(sparkline(query(GOOGLEFINANCE($AZ86,""price"",TODAY()-$AF$43,TODAY(),1),""select Col2 label Col2 ''""),IF($AG$43=""Gráfico de barras"",{""charttype"",""column"";""highcolor"",""red""},{""chartype"",""line""}))))"),"") | AY86: 43 | BG86: 43 | BP86: {=IF(NOT(ConfigOn),"",TEXT(BQ86:BQ98,"dddd"))} -> quarta-feira | BQ86: =IFERROR(__xludf.DUMMYFUNCTION("IF(NOT(ConfigOn),"""",IFERROR(query({GOOGLEFINANCE(""INDEXBVMF:""&$BP$83,""price"",$BR$77-14,$BR$77);IF($BS$77=0,$BR$77,""""),IF($BS$77=0,GoogleFinance(""INDEXBVMF:""&$BP$83),"""")}, ""select Col1, Col2 label Col1 '', Col2 ''"")))"),46078.705555555556) -> 46078.706 | BR86: =IFERROR(__xludf.DUMMYFUNCTION("""COMPUTED_VALUE"""),191247.46) -> 191247.46 | DL86: 20 | DN86: =IF(DM86="","",IFERROR(SUMIFS(op.daytrade!$P$5:$P343,op.daytrade!$AC$5:$AC343,DM86),0))
B87: =IFERROR(__xludf.DUMMYFUNCTION("IF(B$43="""","""",IF($AZ87="""","""",IFERROR(Query({CarteirasAtivos},""Select Col3 where Col1 = '""&$AZ87&""'and Col2 = '""&S$21&""'""))))"),"") | C87: =IFERROR(__xludf.DUMMYFUNCTION("IF(C$43="""","""",IF($AZ87="""","""",IFERROR(Query({CarteirasAtivos},""Select Col3 where Col1 = '""&$AZ87&""'and Col2 = '""&T$21&""'""))))"),"") | D87: =IFERROR(__xludf.DUMMYFUNCTION("IF(D$43="""","""",IF($AZ87="""","""",IFERROR(Query({CarteirasAtivos},""Select Col3 where Col1 = '""&$AZ87&""'and Col2 = '""&U$21&""'""))))"),"") | E87: =IFERROR(__xludf.DUMMYFUNCTION("IF(E$43="""","""",IF($AZ87="""","""",IFERROR(Query({CarteirasAtivos},""Select Col3 where Col1 = '""&$AZ87&""'and Col2 = '""&V$21&""'""))))"),"") | F87: =IFERROR(__xludf.DUMMYFUNCTION("IF(F$43="""","""",IF($AZ87="""","""",IFERROR(Query({CarteirasAtivos},""Select Col3 where Col1 = '""&$AZ87&""'and Col2 = '""&W$21&""'""))))"),"") | G87: =IFERROR(__xludf.DUMMYFUNCTION("IF(G$43="""","""",IF($AZ87="""","""",IFERROR(Query({CarteirasAtivos},""Select Col3 where Col1 = '""&$AZ87&""'and Col2 = '""&X$21&""'""))))"),"") | H87: =IFERROR(__xludf.DUMMYFUNCTION("IF(H$43="""","""",IF($AZ87="""","""",IFERROR(Query({CarteirasAtivos},""Select Col3 where Col1 = '""&$AZ87&""'and Col2 = '""&Y$21&""'""))))"),"") | I87: =IFERROR(__xludf.DUMMYFUNCTION("IF(I$43="""","""",IF($AZ87="""","""",IFERROR(Query({CarteirasAtivos},""Select Col3 where Col1 = '""&$AZ87&""'and Col2 = '""&Z$21&""'""))))"),"") | J87: =IFERROR(__xludf.DUMMYFUNCTION("IF(J$43="""","""",IF($AZ87="""","""",IFERROR(Query({CarteirasAtivos},""Select Col3 where Col1 = '""&$AZ87&""'and Col2 = '""&AA$21&""'""))))"),"") | K87: =IFERROR(__xludf.DUMMYFUNCTION("IF(K$43="""","""",IF($AZ87="""","""",IFERROR(Query({CarteirasAtivos},""Select Col3 where Col1 = '""&$AZ87&""'and Col2 = '""&AB$21&""'""))))"),"") | L87: 44 | W87: =IFERROR(__xludf.DUMMYFUNCTION("IF(M87="""","""",sparkline(IFERROR(BF87*100/MAX($BF$44:$BF$153),0),{""charttype"",""bar"";""max"",100;""color1"",IF(BD87>=0,""#4760a5"",""red"")}))"),"") | AG87: =IFERROR(__xludf.DUMMYFUNCTION("IF($M87="""","""",IFERROR(sparkline(query(GOOGLEFINANCE($AZ87,""price"",TODAY()-$AF$43,TODAY(),1),""select Col2 label Col2 ''""),IF($AG$43=""Gráfico de barras"",{""charttype"",""column"";""highcolor"",""red""},{""chartype"",""line""}))))"),"") | AY87: 44 | BG87: 44 | BO87: 1 | BP87: quinta-feira | BQ87: =IFERROR(__xludf.DUMMYFUNCTION("""COMPUTED_VALUE"""),46079.705555555556) -> 46079.706 | BR87: =IFERROR(__xludf.DUMMYFUNCTION("""COMPUTED_VALUE"""),191005.02) -> 191005.02 | BS87: {=if(BQ87:BQ98="","",BR87:BR98-BR86:BR97)} -> -242.44 | BT87: {=if(BQ87:BQ98="","",((BR87:BR98/BR86:BR97)-1)*100)} -> -0.1267677 | BU87: =IFERROR(__xludf.DUMMYFUNCTION("query({BS87:BS98},""select Col1 limit ""&10)"),-242.44000000000233) -> -242.44
B88: =IFERROR(__xludf.DUMMYFUNCTION("IF(B$43="""","""",IF($AZ88="""","""",IFERROR(Query({CarteirasAtivos},""Select Col3 where Col1 = '""&$AZ88&""'and Col2 = '""&S$21&""'""))))"),"") | C88: =IFERROR(__xludf.DUMMYFUNCTION("IF(C$43="""","""",IF($AZ88="""","""",IFERROR(Query({CarteirasAtivos},""Select Col3 where Col1 = '""&$AZ88&""'and Col2 = '""&T$21&""'""))))"),"") | D88: =IFERROR(__xludf.DUMMYFUNCTION("IF(D$43="""","""",IF($AZ88="""","""",IFERROR(Query({CarteirasAtivos},""Select Col3 where Col1 = '""&$AZ88&""'and Col2 = '""&U$21&""'""))))"),"") | E88: =IFERROR(__xludf.DUMMYFUNCTION("IF(E$43="""","""",IF($AZ88="""","""",IFERROR(Query({CarteirasAtivos},""Select Col3 where Col1 = '""&$AZ88&""'and Col2 = '""&V$21&""'""))))"),"") | F88: =IFERROR(__xludf.DUMMYFUNCTION("IF(F$43="""","""",IF($AZ88="""","""",IFERROR(Query({CarteirasAtivos},""Select Col3 where Col1 = '""&$AZ88&""'and Col2 = '""&W$21&""'""))))"),"") | G88: =IFERROR(__xludf.DUMMYFUNCTION("IF(G$43="""","""",IF($AZ88="""","""",IFERROR(Query({CarteirasAtivos},""Select Col3 where Col1 = '""&$AZ88&""'and Col2 = '""&X$21&""'""))))"),"") | H88: =IFERROR(__xludf.DUMMYFUNCTION("IF(H$43="""","""",IF($AZ88="""","""",IFERROR(Query({CarteirasAtivos},""Select Col3 where Col1 = '""&$AZ88&""'and Col2 = '""&Y$21&""'""))))"),"") | I88: =IFERROR(__xludf.DUMMYFUNCTION("IF(I$43="""","""",IF($AZ88="""","""",IFERROR(Query({CarteirasAtivos},""Select Col3 where Col1 = '""&$AZ88&""'and Col2 = '""&Z$21&""'""))))"),"") | J88: =IFERROR(__xludf.DUMMYFUNCTION("IF(J$43="""","""",IF($AZ88="""","""",IFERROR(Query({CarteirasAtivos},""Select Col3 where Col1 = '""&$AZ88&""'and Col2 = '""&AA$21&""'""))))"),"") | K88: =IFERROR(__xludf.DUMMYFUNCTION("IF(K$43="""","""",IF($AZ88="""","""",IFERROR(Query({CarteirasAtivos},""Select Col3 where Col1 = '""&$AZ88&""'and Col2 = '""&AB$21&""'""))))"),"") | L88: 45 | W88: =IFERROR(__xludf.DUMMYFUNCTION("IF(M88="""","""",sparkline(IFERROR(BF88*100/MAX($BF$44:$BF$153),0),{""charttype"",""bar"";""max"",100;""color1"",IF(BD88>=0,""#4760a5"",""red"")}))"),"") | AG88: =IFERROR(__xludf.DUMMYFUNCTION("IF($M88="""","""",IFERROR(sparkline(query(GOOGLEFINANCE($AZ88,""price"",TODAY()-$AF$43,TODAY(),1),""select Col2 label Col2 ''""),IF($AG$43=""Gráfico de barras"",{""charttype"",""column"";""highcolor"",""red""},{""chartype"",""line""}))))"),"") | AY88: 45 | BG88: 45 | BO88: 2 | BP88: sexta-feira | BQ88: =IFERROR(__xludf.DUMMYFUNCTION("""COMPUTED_VALUE"""),46080.705555555556) -> 46080.706 | BR88: =IFERROR(__xludf.DUMMYFUNCTION("""COMPUTED_VALUE"""),188786.98) -> 188786.98 | BS88: -2218.04 | BT88: -1.161247 | BU88: =IFERROR(__xludf.DUMMYFUNCTION("""COMPUTED_VALUE"""),-2218.039999999979) -> -2218.04
B89: =IFERROR(__xludf.DUMMYFUNCTION("IF(B$43="""","""",IF($AZ89="""","""",IFERROR(Query({CarteirasAtivos},""Select Col3 where Col1 = '""&$AZ89&""'and Col2 = '""&S$21&""'""))))"),"") | C89: =IFERROR(__xludf.DUMMYFUNCTION("IF(C$43="""","""",IF($AZ89="""","""",IFERROR(Query({CarteirasAtivos},""Select Col3 where Col1 = '""&$AZ89&""'and Col2 = '""&T$21&""'""))))"),"") | D89: =IFERROR(__xludf.DUMMYFUNCTION("IF(D$43="""","""",IF($AZ89="""","""",IFERROR(Query({CarteirasAtivos},""Select Col3 where Col1 = '""&$AZ89&""'and Col2 = '""&U$21&""'""))))"),"") | E89: =IFERROR(__xludf.DUMMYFUNCTION("IF(E$43="""","""",IF($AZ89="""","""",IFERROR(Query({CarteirasAtivos},""Select Col3 where Col1 = '""&$AZ89&""'and Col2 = '""&V$21&""'""))))"),"") | F89: =IFERROR(__xludf.DUMMYFUNCTION("IF(F$43="""","""",IF($AZ89="""","""",IFERROR(Query({CarteirasAtivos},""Select Col3 where Col1 = '""&$AZ89&""'and Col2 = '""&W$21&""'""))))"),"") | G89: =IFERROR(__xludf.DUMMYFUNCTION("IF(G$43="""","""",IF($AZ89="""","""",IFERROR(Query({CarteirasAtivos},""Select Col3 where Col1 = '""&$AZ89&""'and Col2 = '""&X$21&""'""))))"),"") | H89: =IFERROR(__xludf.DUMMYFUNCTION("IF(H$43="""","""",IF($AZ89="""","""",IFERROR(Query({CarteirasAtivos},""Select Col3 where Col1 = '""&$AZ89&""'and Col2 = '""&Y$21&""'""))))"),"") | I89: =IFERROR(__xludf.DUMMYFUNCTION("IF(I$43="""","""",IF($AZ89="""","""",IFERROR(Query({CarteirasAtivos},""Select Col3 where Col1 = '""&$AZ89&""'and Col2 = '""&Z$21&""'""))))"),"") | J89: =IFERROR(__xludf.DUMMYFUNCTION("IF(J$43="""","""",IF($AZ89="""","""",IFERROR(Query({CarteirasAtivos},""Select Col3 where Col1 = '""&$AZ89&""'and Col2 = '""&AA$21&""'""))))"),"") | K89: =IFERROR(__xludf.DUMMYFUNCTION("IF(K$43="""","""",IF($AZ89="""","""",IFERROR(Query({CarteirasAtivos},""Select Col3 where Col1 = '""&$AZ89&""'and Col2 = '""&AB$21&""'""))))"),"") | L89: 46 | W89: =IFERROR(__xludf.DUMMYFUNCTION("IF(M89="""","""",sparkline(IFERROR(BF89*100/MAX($BF$44:$BF$153),0),{""charttype"",""bar"";""max"",100;""color1"",IF(BD89>=0,""#4760a5"",""red"")}))"),"") | AG89: =IFERROR(__xludf.DUMMYFUNCTION("IF($M89="""","""",IFERROR(sparkline(query(GOOGLEFINANCE($AZ89,""price"",TODAY()-$AF$43,TODAY(),1),""select Col2 label Col2 ''""),IF($AG$43=""Gráfico de barras"",{""charttype"",""column"";""highcolor"",""red""},{""chartype"",""line""}))))"),"") | AY89: 46 | BG89: 46 | BO89: 3 | BP89: segunda-feira | BQ89: =IFERROR(__xludf.DUMMYFUNCTION("""COMPUTED_VALUE"""),46083.705555555556) -> 46083.706 | BR89: =IFERROR(__xludf.DUMMYFUNCTION("""COMPUTED_VALUE"""),189307.02) -> 189307.02 | BS89: 520.04 | BT89: 0.27546391 | BU89: =IFERROR(__xludf.DUMMYFUNCTION("""COMPUTED_VALUE"""),520.039999999979) -> 520.04
B90: =IFERROR(__xludf.DUMMYFUNCTION("IF(B$43="""","""",IF($AZ90="""","""",IFERROR(Query({CarteirasAtivos},""Select Col3 where Col1 = '""&$AZ90&""'and Col2 = '""&S$21&""'""))))"),"") | C90: =IFERROR(__xludf.DUMMYFUNCTION("IF(C$43="""","""",IF($AZ90="""","""",IFERROR(Query({CarteirasAtivos},""Select Col3 where Col1 = '""&$AZ90&""'and Col2 = '""&T$21&""'""))))"),"") | D90: =IFERROR(__xludf.DUMMYFUNCTION("IF(D$43="""","""",IF($AZ90="""","""",IFERROR(Query({CarteirasAtivos},""Select Col3 where Col1 = '""&$AZ90&""'and Col2 = '""&U$21&""'""))))"),"") | E90: =IFERROR(__xludf.DUMMYFUNCTION("IF(E$43="""","""",IF($AZ90="""","""",IFERROR(Query({CarteirasAtivos},""Select Col3 where Col1 = '""&$AZ90&""'and Col2 = '""&V$21&""'""))))"),"") | F90: =IFERROR(__xludf.DUMMYFUNCTION("IF(F$43="""","""",IF($AZ90="""","""",IFERROR(Query({CarteirasAtivos},""Select Col3 where Col1 = '""&$AZ90&""'and Col2 = '""&W$21&""'""))))"),"") | G90: =IFERROR(__xludf.DUMMYFUNCTION("IF(G$43="""","""",IF($AZ90="""","""",IFERROR(Query({CarteirasAtivos},""Select Col3 where Col1 = '""&$AZ90&""'and Col2 = '""&X$21&""'""))))"),"") | H90: =IFERROR(__xludf.DUMMYFUNCTION("IF(H$43="""","""",IF($AZ90="""","""",IFERROR(Query({CarteirasAtivos},""Select Col3 where Col1 = '""&$AZ90&""'and Col2 = '""&Y$21&""'""))))"),"") | I90: =IFERROR(__xludf.DUMMYFUNCTION("IF(I$43="""","""",IF($AZ90="""","""",IFERROR(Query({CarteirasAtivos},""Select Col3 where Col1 = '""&$AZ90&""'and Col2 = '""&Z$21&""'""))))"),"") | J90: =IFERROR(__xludf.DUMMYFUNCTION("IF(J$43="""","""",IF($AZ90="""","""",IFERROR(Query({CarteirasAtivos},""Select Col3 where Col1 = '""&$AZ90&""'and Col2 = '""&AA$21&""'""))))"),"") | K90: =IFERROR(__xludf.DUMMYFUNCTION("IF(K$43="""","""",IF($AZ90="""","""",IFERROR(Query({CarteirasAtivos},""Select Col3 where Col1 = '""&$AZ90&""'and Col2 = '""&AB$21&""'""))))"),"") | L90: 47 | W90: =IFERROR(__xludf.DUMMYFUNCTION("IF(M90="""","""",sparkline(IFERROR(BF90*100/MAX($BF$44:$BF$153),0),{""charttype"",""bar"";""max"",100;""color1"",IF(BD90>=0,""#4760a5"",""red"")}))"),"") | AG90: =IFERROR(__xludf.DUMMYFUNCTION("IF($M90="""","""",IFERROR(sparkline(query(GOOGLEFINANCE($AZ90,""price"",TODAY()-$AF$43,TODAY(),1),""select Col2 label Col2 ''""),IF($AG$43=""Gráfico de barras"",{""charttype"",""column"";""highcolor"",""red""},{""chartype"",""line""}))))"),"") | AY90: 47 | BG90: 47 | BO90: 4 | BP90: terça-feira | BQ90: =IFERROR(__xludf.DUMMYFUNCTION("""COMPUTED_VALUE"""),46084.705555555556) -> 46084.706 | BR90: =IFERROR(__xludf.DUMMYFUNCTION("""COMPUTED_VALUE"""),183104.87) -> 183104.87 | BS90: -6202.15 | BT90: -3.2762388 | BU90: =IFERROR(__xludf.DUMMYFUNCTION("""COMPUTED_VALUE"""),-6202.149999999994) -> -6202.15
B91: =IFERROR(__xludf.DUMMYFUNCTION("IF(B$43="""","""",IF($AZ91="""","""",IFERROR(Query({CarteirasAtivos},""Select Col3 where Col1 = '""&$AZ91&""'and Col2 = '""&S$21&""'""))))"),"") | C91: =IFERROR(__xludf.DUMMYFUNCTION("IF(C$43="""","""",IF($AZ91="""","""",IFERROR(Query({CarteirasAtivos},""Select Col3 where Col1 = '""&$AZ91&""'and Col2 = '""&T$21&""'""))))"),"") | D91: =IFERROR(__xludf.DUMMYFUNCTION("IF(D$43="""","""",IF($AZ91="""","""",IFERROR(Query({CarteirasAtivos},""Select Col3 where Col1 = '""&$AZ91&""'and Col2 = '""&U$21&""'""))))"),"") | E91: =IFERROR(__xludf.DUMMYFUNCTION("IF(E$43="""","""",IF($AZ91="""","""",IFERROR(Query({CarteirasAtivos},""Select Col3 where Col1 = '""&$AZ91&""'and Col2 = '""&V$21&""'""))))"),"") | F91: =IFERROR(__xludf.DUMMYFUNCTION("IF(F$43="""","""",IF($AZ91="""","""",IFERROR(Query({CarteirasAtivos},""Select Col3 where Col1 = '""&$AZ91&""'and Col2 = '""&W$21&""'""))))"),"") | G91: =IFERROR(__xludf.DUMMYFUNCTION("IF(G$43="""","""",IF($AZ91="""","""",IFERROR(Query({CarteirasAtivos},""Select Col3 where Col1 = '""&$AZ91&""'and Col2 = '""&X$21&""'""))))"),"") | H91: =IFERROR(__xludf.DUMMYFUNCTION("IF(H$43="""","""",IF($AZ91="""","""",IFERROR(Query({CarteirasAtivos},""Select Col3 where Col1 = '""&$AZ91&""'and Col2 = '""&Y$21&""'""))))"),"") | I91: =IFERROR(__xludf.DUMMYFUNCTION("IF(I$43="""","""",IF($AZ91="""","""",IFERROR(Query({CarteirasAtivos},""Select Col3 where Col1 = '""&$AZ91&""'and Col2 = '""&Z$21&""'""))))"),"") | J91: =IFERROR(__xludf.DUMMYFUNCTION("IF(J$43="""","""",IF($AZ91="""","""",IFERROR(Query({CarteirasAtivos},""Select Col3 where Col1 = '""&$AZ91&""'and Col2 = '""&AA$21&""'""))))"),"") | K91: =IFERROR(__xludf.DUMMYFUNCTION("IF(K$43="""","""",IF($AZ91="""","""",IFERROR(Query({CarteirasAtivos},""Select Col3 where Col1 = '""&$AZ91&""'and Col2 = '""&AB$21&""'""))))"),"") | L91: 48 | W91: =IFERROR(__xludf.DUMMYFUNCTION("IF(M91="""","""",sparkline(IFERROR(BF91*100/MAX($BF$44:$BF$153),0),{""charttype"",""bar"";""max"",100;""color1"",IF(BD91>=0,""#4760a5"",""red"")}))"),"") | AG91: =IFERROR(__xludf.DUMMYFUNCTION("IF($M91="""","""",IFERROR(sparkline(query(GOOGLEFINANCE($AZ91,""price"",TODAY()-$AF$43,TODAY(),1),""select Col2 label Col2 ''""),IF($AG$43=""Gráfico de barras"",{""charttype"",""column"";""highcolor"",""red""},{""chartype"",""line""}))))"),"") | AY91: 48 | BG91: 48 | BO91: 5 | BP91: quarta-feira | BQ91: =IFERROR(__xludf.DUMMYFUNCTION("""COMPUTED_VALUE"""),46085.705555555556) -> 46085.706 | BR91: =IFERROR(__xludf.DUMMYFUNCTION("""COMPUTED_VALUE"""),185366.44) -> 185366.44 | BS91: 2261.57 | BT91: 1.2351228 | BU91: =IFERROR(__xludf.DUMMYFUNCTION("""COMPUTED_VALUE"""),2261.570000000007) -> 2261.57
B92: =IFERROR(__xludf.DUMMYFUNCTION("IF(B$43="""","""",IF($AZ92="""","""",IFERROR(Query({CarteirasAtivos},""Select Col3 where Col1 = '""&$AZ92&""'and Col2 = '""&S$21&""'""))))"),"") | C92: =IFERROR(__xludf.DUMMYFUNCTION("IF(C$43="""","""",IF($AZ92="""","""",IFERROR(Query({CarteirasAtivos},""Select Col3 where Col1 = '""&$AZ92&""'and Col2 = '""&T$21&""'""))))"),"") | D92: =IFERROR(__xludf.DUMMYFUNCTION("IF(D$43="""","""",IF($AZ92="""","""",IFERROR(Query({CarteirasAtivos},""Select Col3 where Col1 = '""&$AZ92&""'and Col2 = '""&U$21&""'""))))"),"") | E92: =IFERROR(__xludf.DUMMYFUNCTION("IF(E$43="""","""",IF($AZ92="""","""",IFERROR(Query({CarteirasAtivos},""Select Col3 where Col1 = '""&$AZ92&""'and Col2 = '""&V$21&""'""))))"),"") | F92: =IFERROR(__xludf.DUMMYFUNCTION("IF(F$43="""","""",IF($AZ92="""","""",IFERROR(Query({CarteirasAtivos},""Select Col3 where Col1 = '""&$AZ92&""'and Col2 = '""&W$21&""'""))))"),"") | G92: =IFERROR(__xludf.DUMMYFUNCTION("IF(G$43="""","""",IF($AZ92="""","""",IFERROR(Query({CarteirasAtivos},""Select Col3 where Col1 = '""&$AZ92&""'and Col2 = '""&X$21&""'""))))"),"") | H92: =IFERROR(__xludf.DUMMYFUNCTION("IF(H$43="""","""",IF($AZ92="""","""",IFERROR(Query({CarteirasAtivos},""Select Col3 where Col1 = '""&$AZ92&""'and Col2 = '""&Y$21&""'""))))"),"") | I92: =IFERROR(__xludf.DUMMYFUNCTION("IF(I$43="""","""",IF($AZ92="""","""",IFERROR(Query({CarteirasAtivos},""Select Col3 where Col1 = '""&$AZ92&""'and Col2 = '""&Z$21&""'""))))"),"") | J92: =IFERROR(__xludf.DUMMYFUNCTION("IF(J$43="""","""",IF($AZ92="""","""",IFERROR(Query({CarteirasAtivos},""Select Col3 where Col1 = '""&$AZ92&""'and Col2 = '""&AA$21&""'""))))"),"") | K92: =IFERROR(__xludf.DUMMYFUNCTION("IF(K$43="""","""",IF($AZ92="""","""",IFERROR(Query({CarteirasAtivos},""Select Col3 where Col1 = '""&$AZ92&""'and Col2 = '""&AB$21&""'""))))"),"") | L92: 49 | W92: =IFERROR(__xludf.DUMMYFUNCTION("IF(M92="""","""",sparkline(IFERROR(BF92*100/MAX($BF$44:$BF$153),0),{""charttype"",""bar"";""max"",100;""color1"",IF(BD92>=0,""#4760a5"",""red"")}))"),"") | AG92: =IFERROR(__xludf.DUMMYFUNCTION("IF($M92="""","""",IFERROR(sparkline(query(GOOGLEFINANCE($AZ92,""price"",TODAY()-$AF$43,TODAY(),1),""select Col2 label Col2 ''""),IF($AG$43=""Gráfico de barras"",{""charttype"",""column"";""highcolor"",""red""},{""chartype"",""line""}))))"),"") | AY92: 49 | BG92: 49 | BO92: 6 | BP92: quinta-feira | BQ92: =IFERROR(__xludf.DUMMYFUNCTION("""COMPUTED_VALUE"""),46086.705555555556) -> 46086.706 | BR92: =IFERROR(__xludf.DUMMYFUNCTION("""COMPUTED_VALUE"""),180463.84) -> 180463.84 | BS92: -4902.6 | BT92: -2.6448153 | BU92: =IFERROR(__xludf.DUMMYFUNCTION("""COMPUTED_VALUE"""),-4902.600000000006) -> -4902.6
B93: =IFERROR(__xludf.DUMMYFUNCTION("IF(B$43="""","""",IF($AZ93="""","""",IFERROR(Query({CarteirasAtivos},""Select Col3 where Col1 = '""&$AZ93&""'and Col2 = '""&S$21&""'""))))"),"") | C93: =IFERROR(__xludf.DUMMYFUNCTION("IF(C$43="""","""",IF($AZ93="""","""",IFERROR(Query({CarteirasAtivos},""Select Col3 where Col1 = '""&$AZ93&""'and Col2 = '""&T$21&""'""))))"),"") | D93: =IFERROR(__xludf.DUMMYFUNCTION("IF(D$43="""","""",IF($AZ93="""","""",IFERROR(Query({CarteirasAtivos},""Select Col3 where Col1 = '""&$AZ93&""'and Col2 = '""&U$21&""'""))))"),"") | E93: =IFERROR(__xludf.DUMMYFUNCTION("IF(E$43="""","""",IF($AZ93="""","""",IFERROR(Query({CarteirasAtivos},""Select Col3 where Col1 = '""&$AZ93&""'and Col2 = '""&V$21&""'""))))"),"") | F93: =IFERROR(__xludf.DUMMYFUNCTION("IF(F$43="""","""",IF($AZ93="""","""",IFERROR(Query({CarteirasAtivos},""Select Col3 where Col1 = '""&$AZ93&""'and Col2 = '""&W$21&""'""))))"),"") | G93: =IFERROR(__xludf.DUMMYFUNCTION("IF(G$43="""","""",IF($AZ93="""","""",IFERROR(Query({CarteirasAtivos},""Select Col3 where Col1 = '""&$AZ93&""'and Col2 = '""&X$21&""'""))))"),"") | H93: =IFERROR(__xludf.DUMMYFUNCTION("IF(H$43="""","""",IF($AZ93="""","""",IFERROR(Query({CarteirasAtivos},""Select Col3 where Col1 = '""&$AZ93&""'and Col2 = '""&Y$21&""'""))))"),"") | I93: =IFERROR(__xludf.DUMMYFUNCTION("IF(I$43="""","""",IF($AZ93="""","""",IFERROR(Query({CarteirasAtivos},""Select Col3 where Col1 = '""&$AZ93&""'and Col2 = '""&Z$21&""'""))))"),"") | J93: =IFERROR(__xludf.DUMMYFUNCTION("IF(J$43="""","""",IF($AZ93="""","""",IFERROR(Query({CarteirasAtivos},""Select Col3 where Col1 = '""&$AZ93&""'and Col2 = '""&AA$21&""'""))))"),"") | K93: =IFERROR(__xludf.DUMMYFUNCTION("IF(K$43="""","""",IF($AZ93="""","""",IFERROR(Query({CarteirasAtivos},""Select Col3 where Col1 = '""&$AZ93&""'and Col2 = '""&AB$21&""'""))))"),"") | L93: 50 | W93: =IFERROR(__xludf.DUMMYFUNCTION("IF(M93="""","""",sparkline(IFERROR(BF93*100/MAX($BF$44:$BF$153),0),{""charttype"",""bar"";""max"",100;""color1"",IF(BD93>=0,""#4760a5"",""red"")}))"),"") | AG93: =IFERROR(__xludf.DUMMYFUNCTION("IF($M93="""","""",IFERROR(sparkline(query(GOOGLEFINANCE($AZ93,""price"",TODAY()-$AF$43,TODAY(),1),""select Col2 label Col2 ''""),IF($AG$43=""Gráfico de barras"",{""charttype"",""column"";""highcolor"",""red""},{""chartype"",""line""}))))"),"") | AY93: 50 | BG93: 50 | BO93: 7 | BP93: sexta-feira | BQ93: =IFERROR(__xludf.DUMMYFUNCTION("""COMPUTED_VALUE"""),46087.705555555556) -> 46087.706 | BR93: =IFERROR(__xludf.DUMMYFUNCTION("""COMPUTED_VALUE"""),179364.82) -> 179364.82 | BS93: -1099.02 | BT93: -0.60899735 | BU93: =IFERROR(__xludf.DUMMYFUNCTION("""COMPUTED_VALUE"""),-1099.0199999999895) -> -1099.02
B94: =IFERROR(__xludf.DUMMYFUNCTION("IF(B$43="""","""",IF($AZ94="""","""",IFERROR(Query({CarteirasAtivos},""Select Col3 where Col1 = '""&$AZ94&""'and Col2 = '""&S$21&""'""))))"),"") | C94: =IFERROR(__xludf.DUMMYFUNCTION("IF(C$43="""","""",IF($AZ94="""","""",IFERROR(Query({CarteirasAtivos},""Select Col3 where Col1 = '""&$AZ94&""'and Col2 = '""&T$21&""'""))))"),"") | D94: =IFERROR(__xludf.DUMMYFUNCTION("IF(D$43="""","""",IF($AZ94="""","""",IFERROR(Query({CarteirasAtivos},""Select Col3 where Col1 = '""&$AZ94&""'and Col2 = '""&U$21&""'""))))"),"") | E94: =IFERROR(__xludf.DUMMYFUNCTION("IF(E$43="""","""",IF($AZ94="""","""",IFERROR(Query({CarteirasAtivos},""Select Col3 where Col1 = '""&$AZ94&""'and Col2 = '""&V$21&""'""))))"),"") | F94: =IFERROR(__xludf.DUMMYFUNCTION("IF(F$43="""","""",IF($AZ94="""","""",IFERROR(Query({CarteirasAtivos},""Select Col3 where Col1 = '""&$AZ94&""'and Col2 = '""&W$21&""'""))))"),"") | G94: =IFERROR(__xludf.DUMMYFUNCTION("IF(G$43="""","""",IF($AZ94="""","""",IFERROR(Query({CarteirasAtivos},""Select Col3 where Col1 = '""&$AZ94&""'and Col2 = '""&X$21&""'""))))"),"") | H94: =IFERROR(__xludf.DUMMYFUNCTION("IF(H$43="""","""",IF($AZ94="""","""",IFERROR(Query({CarteirasAtivos},""Select Col3 where Col1 = '""&$AZ94&""'and Col2 = '""&Y$21&""'""))))"),"") | I94: =IFERROR(__xludf.DUMMYFUNCTION("IF(I$43="""","""",IF($AZ94="""","""",IFERROR(Query({CarteirasAtivos},""Select Col3 where Col1 = '""&$AZ94&""'and Col2 = '""&Z$21&""'""))))"),"") | J94: =IFERROR(__xludf.DUMMYFUNCTION("IF(J$43="""","""",IF($AZ94="""","""",IFERROR(Query({CarteirasAtivos},""Select Col3 where Col1 = '""&$AZ94&""'and Col2 = '""&AA$21&""'""))))"),"") | K94: =IFERROR(__xludf.DUMMYFUNCTION("IF(K$43="""","""",IF($AZ94="""","""",IFERROR(Query({CarteirasAtivos},""Select Col3 where Col1 = '""&$AZ94&""'and Col2 = '""&AB$21&""'""))))"),"") | L94: 51 | W94: =IFERROR(__xludf.DUMMYFUNCTION("IF(M94="""","""",sparkline(IFERROR(BF94*100/MAX($BF$44:$BF$153),0),{""charttype"",""bar"";""max"",100;""color1"",IF(BD94>=0,""#4760a5"",""red"")}))"),"") | AG94: =IFERROR(__xludf.DUMMYFUNCTION("IF($M94="""","""",IFERROR(sparkline(query(GOOGLEFINANCE($AZ94,""price"",TODAY()-$AF$43,TODAY(),1),""select Col2 label Col2 ''""),IF($AG$43=""Gráfico de barras"",{""charttype"",""column"";""highcolor"",""red""},{""chartype"",""line""}))))"),"") | AY94: 51 | BG94: 51 | BO94: 8 | BP94: segunda-feira | BQ94: =IFERROR(__xludf.DUMMYFUNCTION("""COMPUTED_VALUE"""),46090.705555555556) -> 46090.706 | BR94: =IFERROR(__xludf.DUMMYFUNCTION("""COMPUTED_VALUE"""),180915.36) -> 180915.36 | BS94: 1550.54 | BT94: 0.8644616 | BU94: =IFERROR(__xludf.DUMMYFUNCTION("""COMPUTED_VALUE"""),1550.539999999979) -> 1550.54
B95: =IFERROR(__xludf.DUMMYFUNCTION("IF(B$43="""","""",IF($AZ95="""","""",IFERROR(Query({CarteirasAtivos},""Select Col3 where Col1 = '""&$AZ95&""'and Col2 = '""&S$21&""'""))))"),"") | C95: =IFERROR(__xludf.DUMMYFUNCTION("IF(C$43="""","""",IF($AZ95="""","""",IFERROR(Query({CarteirasAtivos},""Select Col3 where Col1 = '""&$AZ95&""'and Col2 = '""&T$21&""'""))))"),"") | D95: =IFERROR(__xludf.DUMMYFUNCTION("IF(D$43="""","""",IF($AZ95="""","""",IFERROR(Query({CarteirasAtivos},""Select Col3 where Col1 = '""&$AZ95&""'and Col2 = '""&U$21&""'""))))"),"") | E95: =IFERROR(__xludf.DUMMYFUNCTION("IF(E$43="""","""",IF($AZ95="""","""",IFERROR(Query({CarteirasAtivos},""Select Col3 where Col1 = '""&$AZ95&""'and Col2 = '""&V$21&""'""))))"),"") | F95: =IFERROR(__xludf.DUMMYFUNCTION("IF(F$43="""","""",IF($AZ95="""","""",IFERROR(Query({CarteirasAtivos},""Select Col3 where Col1 = '""&$AZ95&""'and Col2 = '""&W$21&""'""))))"),"") | G95: =IFERROR(__xludf.DUMMYFUNCTION("IF(G$43="""","""",IF($AZ95="""","""",IFERROR(Query({CarteirasAtivos},""Select Col3 where Col1 = '""&$AZ95&""'and Col2 = '""&X$21&""'""))))"),"") | H95: =IFERROR(__xludf.DUMMYFUNCTION("IF(H$43="""","""",IF($AZ95="""","""",IFERROR(Query({CarteirasAtivos},""Select Col3 where Col1 = '""&$AZ95&""'and Col2 = '""&Y$21&""'""))))"),"") | I95: =IFERROR(__xludf.DUMMYFUNCTION("IF(I$43="""","""",IF($AZ95="""","""",IFERROR(Query({CarteirasAtivos},""Select Col3 where Col1 = '""&$AZ95&""'and Col2 = '""&Z$21&""'""))))"),"") | J95: =IFERROR(__xludf.DUMMYFUNCTION("IF(J$43="""","""",IF($AZ95="""","""",IFERROR(Query({CarteirasAtivos},""Select Col3 where Col1 = '""&$AZ95&""'and Col2 = '""&AA$21&""'""))))"),"") | K95: =IFERROR(__xludf.DUMMYFUNCTION("IF(K$43="""","""",IF($AZ95="""","""",IFERROR(Query({CarteirasAtivos},""Select Col3 where Col1 = '""&$AZ95&""'and Col2 = '""&AB$21&""'""))))"),"") | L95: 52 | W95: =IFERROR(__xludf.DUMMYFUNCTION("IF(M95="""","""",sparkline(IFERROR(BF95*100/MAX($BF$44:$BF$153),0),{""charttype"",""bar"";""max"",100;""color1"",IF(BD95>=0,""#4760a5"",""red"")}))"),"") | AG95: =IFERROR(__xludf.DUMMYFUNCTION("IF($M95="""","""",IFERROR(sparkline(query(GOOGLEFINANCE($AZ95,""price"",TODAY()-$AF$43,TODAY(),1),""select Col2 label Col2 ''""),IF($AG$43=""Gráfico de barras"",{""charttype"",""column"";""highcolor"",""red""},{""chartype"",""line""}))))"),"") | AY95: 52 | BG95: 52 | BO95: 9 | BP95: terça-feira | BQ95: =IFERROR(__xludf.DUMMYFUNCTION("""COMPUTED_VALUE"""),46091.705555555556) -> 46091.706 | BR95: =IFERROR(__xludf.DUMMYFUNCTION("""COMPUTED_VALUE"""),183447.0) -> 183447 | BS95: 2531.64 | BT95: 1.3993505 | BU95: =IFERROR(__xludf.DUMMYFUNCTION("""COMPUTED_VALUE"""),2531.640000000014) -> 2531.64
B96: =IFERROR(__xludf.DUMMYFUNCTION("IF(B$43="""","""",IF($AZ96="""","""",IFERROR(Query({CarteirasAtivos},""Select Col3 where Col1 = '""&$AZ96&""'and Col2 = '""&S$21&""'""))))"),"") | C96: =IFERROR(__xludf.DUMMYFUNCTION("IF(C$43="""","""",IF($AZ96="""","""",IFERROR(Query({CarteirasAtivos},""Select Col3 where Col1 = '""&$AZ96&""'and Col2 = '""&T$21&""'""))))"),"") | D96: =IFERROR(__xludf.DUMMYFUNCTION("IF(D$43="""","""",IF($AZ96="""","""",IFERROR(Query({CarteirasAtivos},""Select Col3 where Col1 = '""&$AZ96&""'and Col2 = '""&U$21&""'""))))"),"") | E96: =IFERROR(__xludf.DUMMYFUNCTION("IF(E$43="""","""",IF($AZ96="""","""",IFERROR(Query({CarteirasAtivos},""Select Col3 where Col1 = '""&$AZ96&""'and Col2 = '""&V$21&""'""))))"),"") | F96: =IFERROR(__xludf.DUMMYFUNCTION("IF(F$43="""","""",IF($AZ96="""","""",IFERROR(Query({CarteirasAtivos},""Select Col3 where Col1 = '""&$AZ96&""'and Col2 = '""&W$21&""'""))))"),"") | G96: =IFERROR(__xludf.DUMMYFUNCTION("IF(G$43="""","""",IF($AZ96="""","""",IFERROR(Query({CarteirasAtivos},""Select Col3 where Col1 = '""&$AZ96&""'and Col2 = '""&X$21&""'""))))"),"") | H96: =IFERROR(__xludf.DUMMYFUNCTION("IF(H$43="""","""",IF($AZ96="""","""",IFERROR(Query({CarteirasAtivos},""Select Col3 where Col1 = '""&$AZ96&""'and Col2 = '""&Y$21&""'""))))"),"") | I96: =IFERROR(__xludf.DUMMYFUNCTION("IF(I$43="""","""",IF($AZ96="""","""",IFERROR(Query({CarteirasAtivos},""Select Col3 where Col1 = '""&$AZ96&""'and Col2 = '""&Z$21&""'""))))"),"") | J96: =IFERROR(__xludf.DUMMYFUNCTION("IF(J$43="""","""",IF($AZ96="""","""",IFERROR(Query({CarteirasAtivos},""Select Col3 where Col1 = '""&$AZ96&""'and Col2 = '""&AA$21&""'""))))"),"") | K96: =IFERROR(__xludf.DUMMYFUNCTION("IF(K$43="""","""",IF($AZ96="""","""",IFERROR(Query({CarteirasAtivos},""Select Col3 where Col1 = '""&$AZ96&""'and Col2 = '""&AB$21&""'""))))"),"") | L96: 53 | W96: =IFERROR(__xludf.DUMMYFUNCTION("IF(M96="""","""",sparkline(IFERROR(BF96*100/MAX($BF$44:$BF$153),0),{""charttype"",""bar"";""max"",100;""color1"",IF(BD96>=0,""#4760a5"",""red"")}))"),"") | AG96: =IFERROR(__xludf.DUMMYFUNCTION("IF($M96="""","""",IFERROR(sparkline(query(GOOGLEFINANCE($AZ96,""price"",TODAY()-$AF$43,TODAY(),1),""select Col2 label Col2 ''""),IF($AG$43=""Gráfico de barras"",{""charttype"",""column"";""highcolor"",""red""},{""chartype"",""line""}))))"),"") | AY96: 53 | BG96: 53 | BO96: 10 | BP96: quarta-feira | BQ96: =IFERROR(__xludf.DUMMYFUNCTION("""COMPUTED_VALUE"""),46092.705555555556) -> 46092.706 | BR96: =IFERROR(__xludf.DUMMYFUNCTION("""COMPUTED_VALUE"""),183969.35) -> 183969.35 | BS96: 522.35 | BT96: 0.28474164 | BU96: =IFERROR(__xludf.DUMMYFUNCTION("""COMPUTED_VALUE"""),522.3500000000058) -> 522.35
B97: =IFERROR(__xludf.DUMMYFUNCTION("IF(B$43="""","""",IF($AZ97="""","""",IFERROR(Query({CarteirasAtivos},""Select Col3 where Col1 = '""&$AZ97&""'and Col2 = '""&S$21&""'""))))"),"") | C97: =IFERROR(__xludf.DUMMYFUNCTION("IF(C$43="""","""",IF($AZ97="""","""",IFERROR(Query({CarteirasAtivos},""Select Col3 where Col1 = '""&$AZ97&""'and Col2 = '""&T$21&""'""))))"),"") | D97: =IFERROR(__xludf.DUMMYFUNCTION("IF(D$43="""","""",IF($AZ97="""","""",IFERROR(Query({CarteirasAtivos},""Select Col3 where Col1 = '""&$AZ97&""'and Col2 = '""&U$21&""'""))))"),"") | E97: =IFERROR(__xludf.DUMMYFUNCTION("IF(E$43="""","""",IF($AZ97="""","""",IFERROR(Query({CarteirasAtivos},""Select Col3 where Col1 = '""&$AZ97&""'and Col2 = '""&V$21&""'""))))"),"") | F97: =IFERROR(__xludf.DUMMYFUNCTION("IF(F$43="""","""",IF($AZ97="""","""",IFERROR(Query({CarteirasAtivos},""Select Col3 where Col1 = '""&$AZ97&""'and Col2 = '""&W$21&""'""))))"),"") | G97: =IFERROR(__xludf.DUMMYFUNCTION("IF(G$43="""","""",IF($AZ97="""","""",IFERROR(Query({CarteirasAtivos},""Select Col3 where Col1 = '""&$AZ97&""'and Col2 = '""&X$21&""'""))))"),"") | H97: =IFERROR(__xludf.DUMMYFUNCTION("IF(H$43="""","""",IF($AZ97="""","""",IFERROR(Query({CarteirasAtivos},""Select Col3 where Col1 = '""&$AZ97&""'and Col2 = '""&Y$21&""'""))))"),"") | I97: =IFERROR(__xludf.DUMMYFUNCTION("IF(I$43="""","""",IF($AZ97="""","""",IFERROR(Query({CarteirasAtivos},""Select Col3 where Col1 = '""&$AZ97&""'and Col2 = '""&Z$21&""'""))))"),"") | J97: =IFERROR(__xludf.DUMMYFUNCTION("IF(J$43="""","""",IF($AZ97="""","""",IFERROR(Query({CarteirasAtivos},""Select Col3 where Col1 = '""&$AZ97&""'and Col2 = '""&AA$21&""'""))))"),"") | K97: =IFERROR(__xludf.DUMMYFUNCTION("IF(K$43="""","""",IF($AZ97="""","""",IFERROR(Query({CarteirasAtivos},""Select Col3 where Col1 = '""&$AZ97&""'and Col2 = '""&AB$21&""'""))))"),"") | L97: 54 | W97: =IFERROR(__xludf.DUMMYFUNCTION("IF(M97="""","""",sparkline(IFERROR(BF97*100/MAX($BF$44:$BF$153),0),{""charttype"",""bar"";""max"",100;""color1"",IF(BD97>=0,""#4760a5"",""red"")}))"),"") | AG97: =IFERROR(__xludf.DUMMYFUNCTION("IF($M97="""","""",IFERROR(sparkline(query(GOOGLEFINANCE($AZ97,""price"",TODAY()-$AF$43,TODAY(),1),""select Col2 label Col2 ''""),IF($AG$43=""Gráfico de barras"",{""charttype"",""column"";""highcolor"",""red""},{""chartype"",""line""}))))"),"") | AY97: 54 | BG97: 54 | BP97: quarta-feira | BQ97: =IFERROR(__xludf.DUMMYFUNCTION("""COMPUTED_VALUE"""),46092.0) -> 46092 | BR97: =IFERROR(__xludf.DUMMYFUNCTION("""COMPUTED_VALUE"""),183969.34) -> 183969.34 | BS97: -0.01 | BT97: -5.4356881e-06
B98: =IFERROR(__xludf.DUMMYFUNCTION("IF(B$43="""","""",IF($AZ98="""","""",IFERROR(Query({CarteirasAtivos},""Select Col3 where Col1 = '""&$AZ98&""'and Col2 = '""&S$21&""'""))))"),"") | C98: =IFERROR(__xludf.DUMMYFUNCTION("IF(C$43="""","""",IF($AZ98="""","""",IFERROR(Query({CarteirasAtivos},""Select Col3 where Col1 = '""&$AZ98&""'and Col2 = '""&T$21&""'""))))"),"") | D98: =IFERROR(__xludf.DUMMYFUNCTION("IF(D$43="""","""",IF($AZ98="""","""",IFERROR(Query({CarteirasAtivos},""Select Col3 where Col1 = '""&$AZ98&""'and Col2 = '""&U$21&""'""))))"),"") | E98: =IFERROR(__xludf.DUMMYFUNCTION("IF(E$43="""","""",IF($AZ98="""","""",IFERROR(Query({CarteirasAtivos},""Select Col3 where Col1 = '""&$AZ98&""'and Col2 = '""&V$21&""'""))))"),"") | F98: =IFERROR(__xludf.DUMMYFUNCTION("IF(F$43="""","""",IF($AZ98="""","""",IFERROR(Query({CarteirasAtivos},""Select Col3 where Col1 = '""&$AZ98&""'and Col2 = '""&W$21&""'""))))"),"") | G98: =IFERROR(__xludf.DUMMYFUNCTION("IF(G$43="""","""",IF($AZ98="""","""",IFERROR(Query({CarteirasAtivos},""Select Col3 where Col1 = '""&$AZ98&""'and Col2 = '""&X$21&""'""))))"),"") | H98: =IFERROR(__xludf.DUMMYFUNCTION("IF(H$43="""","""",IF($AZ98="""","""",IFERROR(Query({CarteirasAtivos},""Select Col3 where Col1 = '""&$AZ98&""'and Col2 = '""&Y$21&""'""))))"),"") | I98: =IFERROR(__xludf.DUMMYFUNCTION("IF(I$43="""","""",IF($AZ98="""","""",IFERROR(Query({CarteirasAtivos},""Select Col3 where Col1 = '""&$AZ98&""'and Col2 = '""&Z$21&""'""))))"),"") | J98: =IFERROR(__xludf.DUMMYFUNCTION("IF(J$43="""","""",IF($AZ98="""","""",IFERROR(Query({CarteirasAtivos},""Select Col3 where Col1 = '""&$AZ98&""'and Col2 = '""&AA$21&""'""))))"),"") | K98: =IFERROR(__xludf.DUMMYFUNCTION("IF(K$43="""","""",IF($AZ98="""","""",IFERROR(Query({CarteirasAtivos},""Select Col3 where Col1 = '""&$AZ98&""'and Col2 = '""&AB$21&""'""))))"),"") | L98: 55 | W98: =IFERROR(__xludf.DUMMYFUNCTION("IF(M98="""","""",sparkline(IFERROR(BF98*100/MAX($BF$44:$BF$153),0),{""charttype"",""bar"";""max"",100;""color1"",IF(BD98>=0,""#4760a5"",""red"")}))"),"") | AG98: =IFERROR(__xludf.DUMMYFUNCTION("IF($M98="""","""",IFERROR(sparkline(query(GOOGLEFINANCE($AZ98,""price"",TODAY()-$AF$43,TODAY(),1),""select Col2 label Col2 ''""),IF($AG$43=""Gráfico de barras"",{""charttype"",""column"";""highcolor"",""red""},{""chartype"",""line""}))))"),"") | AY98: 55 | BG98: 55 | BP98: sábado
B99: =IFERROR(__xludf.DUMMYFUNCTION("IF(B$43="""","""",IF($AZ99="""","""",IFERROR(Query({CarteirasAtivos},""Select Col3 where Col1 = '""&$AZ99&""'and Col2 = '""&S$21&""'""))))"),"") | C99: =IFERROR(__xludf.DUMMYFUNCTION("IF(C$43="""","""",IF($AZ99="""","""",IFERROR(Query({CarteirasAtivos},""Select Col3 where Col1 = '""&$AZ99&""'and Col2 = '""&T$21&""'""))))"),"") | D99: =IFERROR(__xludf.DUMMYFUNCTION("IF(D$43="""","""",IF($AZ99="""","""",IFERROR(Query({CarteirasAtivos},""Select Col3 where Col1 = '""&$AZ99&""'and Col2 = '""&U$21&""'""))))"),"") | E99: =IFERROR(__xludf.DUMMYFUNCTION("IF(E$43="""","""",IF($AZ99="""","""",IFERROR(Query({CarteirasAtivos},""Select Col3 where Col1 = '""&$AZ99&""'and Col2 = '""&V$21&""'""))))"),"") | F99: =IFERROR(__xludf.DUMMYFUNCTION("IF(F$43="""","""",IF($AZ99="""","""",IFERROR(Query({CarteirasAtivos},""Select Col3 where Col1 = '""&$AZ99&""'and Col2 = '""&W$21&""'""))))"),"") | G99: =IFERROR(__xludf.DUMMYFUNCTION("IF(G$43="""","""",IF($AZ99="""","""",IFERROR(Query({CarteirasAtivos},""Select Col3 where Col1 = '""&$AZ99&""'and Col2 = '""&X$21&""'""))))"),"") | H99: =IFERROR(__xludf.DUMMYFUNCTION("IF(H$43="""","""",IF($AZ99="""","""",IFERROR(Query({CarteirasAtivos},""Select Col3 where Col1 = '""&$AZ99&""'and Col2 = '""&Y$21&""'""))))"),"") | I99: =IFERROR(__xludf.DUMMYFUNCTION("IF(I$43="""","""",IF($AZ99="""","""",IFERROR(Query({CarteirasAtivos},""Select Col3 where Col1 = '""&$AZ99&""'and Col2 = '""&Z$21&""'""))))"),"") | J99: =IFERROR(__xludf.DUMMYFUNCTION("IF(J$43="""","""",IF($AZ99="""","""",IFERROR(Query({CarteirasAtivos},""Select Col3 where Col1 = '""&$AZ99&""'and Col2 = '""&AA$21&""'""))))"),"") | K99: =IFERROR(__xludf.DUMMYFUNCTION("IF(K$43="""","""",IF($AZ99="""","""",IFERROR(Query({CarteirasAtivos},""Select Col3 where Col1 = '""&$AZ99&""'and Col2 = '""&AB$21&""'""))))"),"") | L99: 56 | W99: =IFERROR(__xludf.DUMMYFUNCTION("IF(M99="""","""",sparkline(IFERROR(BF99*100/MAX($BF$44:$BF$153),0),{""charttype"",""bar"";""max"",100;""color1"",IF(BD99>=0,""#4760a5"",""red"")}))"),"") | AG99: =IFERROR(__xludf.DUMMYFUNCTION("IF($M99="""","""",IFERROR(sparkline(query(GOOGLEFINANCE($AZ99,""price"",TODAY()-$AF$43,TODAY(),1),""select Col2 label Col2 ''""),IF($AG$43=""Gráfico de barras"",{""charttype"",""column"";""highcolor"",""red""},{""chartype"",""line""}))))"),"") | AY99: 56 | BG99: 56
